Workbook

Sheet DESPLEGABLES
A1: ESCUELA | D1: MODALIDAD DE EXAMEN | G1: STATUS DE DOCUMENTOS | J1: CAMPAÑAS | L1: EVENTOS
A2: COMUNICACIONES | D2: ORDINARIO | G2: PENDIENTE TODO | J2: Open Day 1 | L2: Open Day 1
A3: TURISMO | D3: TERCIO SUPERIOR | G3: ENTREGADO-COMPLETO | J3: Open Day 2 | L3: Open Day 2
A4: PSICOLOGIA | D4: EXAMEN DIGITAL | G4: PEND. CERTIFICADO | J4: Open Day 3 | L4: Open Day 3
D5: COMPLEMENTACIÓN ACADÉMICA | G5: PEND. DNI | J5: Open Day 4 | L5: Open Day 4
D6: PRIMERA ALTERNATIVA | G6: PEND. DECLARACION JURADA | J6: Taller Vivencial 1 | L6: Taller Vivencial 1
A7: RESPUESTA | D7: TRASLADA INTERNO | J7: Taller Vivencial 2 | L7: Taller Vivencial 2
A8: SI | D8: TRASLADO EXTERNO | J8: Taller Vivencial 3 | L8: Taller Vivencial 3
A9: NO | D9: CEA | J9: Visita Guiada | L9: Taller Vivencial 4
A10: EN PROCESO | D10: PA | J10: Examen Digital | L10: Taller Vivencial 5
J11: Admisión regular | L11: Taller Vivencial 6
J12: Complementación académica | L12: Taller Vivencial 7
L13: Visita Guiada
G14: ÁREA QUE ATIENDE
D15: ORIGEN DE DATA | G15: DIREC. COMUNICACIONES
A16: SEMESTRE | D16: BASE ANTIGUA | G16: DIREC. TURISMO
A17: 2025-II | D17: PAUTA DIGITAL | G17: DIREC. PSICOLOGIA
A18: 2026-I | D18: EVENTO PRESENCIAL | G18: COORDINACIÓN
D19: WEB | G19: ORA
A20: MODALIDAD | D20: CENTRAL | G20: TESORERÍA | J20: ESTADO DEL POSTULANTE
A21: REACTUALIZACIÓN DE MATRÍCULA | D21: COUNTER | G21: OTI | J21: 4to
A22: REGULAR | D22: EXPOUNIVERSIDAD | G22: COMERCIAL | J22: 5to
A23: DEFICIENCIA ACADÉMICA | D23: VISITA A COLEGIOS | J23: Terminó el colegio
A24: RESERVA DE MATRÍCULA | J24: Tiene título técnico
G25: CONTACTO I
A26: RETIRO DE CICLO | D26: ASESORES | G26: MOSTRÓ INTERÉS | J26: No tiene título técnico
A27: INGRESANTE | D27: MELISA ARCIGA | G27: SE ENVIÓ INFORMACIÓN
D28: SHEYLA PEÑA | G28: NO CONTESTA
D29: PYA PINTO | G29: INCONTACTABLE
A30: STATUS ACADÉMICO | D30: LILYA ESPINOZA | G30: EVALUANDO OPCIONES
A31: NO INSCRITO | D31: ESTRELLA VERGARA | G31: SELECCIONÓ OTRA UNIVERSIDAD
A32: INSCRITO | G32: OTROS
A33: ADMITIDO
A34: MATRICULADO | D34: SEDE
D35: SURQUILLO
A36: TIPO DE EXAMEN | D36: SANTA ANITA
A37: VIRTUAL | D37: COMAS
A38: PRESENCIAL
D40: PAGO INSCRIPCION
A41: STATUS EXAMEN | D41: SI - EXAMEN PRESENCIAL
A42: RINDIO VIRTUAL | D42: NO - VIRTUAL
A43: RINDIO PRESENCIAL
A44: RENDIRA VIRTUAL
A45: RENDIRA PRESENCIAL
A47: CONTACTO II Y III
A48: SI CONFIRMÓ PARA EL EVENTO
A49: NO CONFIRMÓ PARA EL EVENTO
A50: ESPERANDO CONFIRMACIÓN PARA EL EVENTO
A51: MOSTRÓ INTERÉS
A52: NO HUBO PROGRESO
A53: MOSTRÓ INTERÉS
A54: NO HUBO PROGRESO
A55: MOSTRÓ INTERÉS
... A58: INCONTACTABLE

Sheet BASE DE DATOS
A1: DNI | B1: NOMBRES | C1: CELULAR | D1: CORREO | E1: COLEGIO DE PROCEDENCIA | F1: MODALIDAD | G1: ESCUELA | H1: ORIGEN | I1: SEDE | J1: SEMESTRE | K1: CAMPAÑA | L1: EVENTO | M1: FECHA DE INGRESO DE LEAD | N1: CONTACTO I | O1: CONTACTO II | P1: CONTACTO III | Q1: ¿PAGÓ DERECHO DE INSCRIPCIÓN? | R1: STATUS ACADÉMICO | S1: TIPO DE EXAMEN | T1: STATUS DE EXAMEN | U1: ENTREGA DE DOCUMENTOS | V1: OBSERVACION | W1: ASESORA
A2: 0 | B2: Percy flores quintana | C2: 51987654321 | D2: percy91.9fm@gmail.com | E2: terminé_el_colegio | G2: COMUNICACIONES | H2: PAUTA DIGITAL | K2: Open Day 3 | L2: Open Day 3 | M2: 45880 | N2: INCONTACTABLE | O2: INCONTACTABLE | P2: INCONTACTABLE | W2: Sheyla Peña
A3: 0 | B3: Jorge Luis | C3: 924212271 | D3: valuis854@gmail.com | E3: terminé_el_colegio | G3: TURISMO | H3: PAUTA DIGITAL | I3: SURQUILLO | K3: Visita Guiada | M3: 45846 | N3: SE ENVIÓ INFORMACIÓN | O3: NO CONTESTA | P3: NO CONTESTA | V3: jueves_11_a.m. | W3: Pya Pinto
A4: 0 | B4: Gian Taco melo | C4: 916287392 | D4: #¿NOMBRE? | G4: PSICOLOGIA | H4: CENTRAL | M4: 45859 | N4: SE ENVIÓ INFORMACIÓN | W4: Melisa Arciga
A5: 0 | B5: Jorge Luis orellano Fernández | C5: 51911111111 | D5: jtacuri@gmail.com | E5: terminé_el_colegio | G5: PSICOLOGIA | H5: PAUTA DIGITAL | K5: Examen Digital | L5: Examen Digital | M5: 45873 | N5: INCONTACTABLE | O5: INCONTACTABLE | P5: INCONTACTABLE | W5: Melisa Arciga
A6: 0 | B6: Elita Valverde | C6: 51991831956 | D6: clauvalverdebravo@gmail.com | E6: terminé_el_colegio | G6: TURISMO | H6: PAUTA DIGITAL | K6: Admisión regular | L6: Admisión regular | M6: 45880 | N6: SE ENVIÓ INFORMACIÓN | W6: Melisa Arciga
A7: 0 | B7: Florpumacayomartinez@gmail.com | C7: 51974540792 | D7: florpumacayomartinez@gmail.com | E7: terminé_el_colegio | G7: COMUNICACIONES | H7: PAUTA DIGITAL | K7: Taller Vivencial 3 | M7: 45856 | N7: SE ENVIÓ INFORMACIÓN | P7: NO CONTESTA | W7: Lilya Espinoza
A8: 0.8195499 | B8: Daniel Cornejo Marsano | C8: 935177607 | G8: COMUNICACIONES | H8: COUNTER | J8: 2026-I | L8: Taller Vivencial 3 | N8: MOSTRÓ INTERÉS | W8: Sheyla Peña
A9: 14 | B9: DAYANA ANGELICA | C9: 920459419 | G9: PSICOLOGIA | H9: CENTRAL | J9: 2025-II | N9: SE ENVIÓ INFORMACIÓN | O9: NO CONTESTA | W9: Melisa Arciga
A10: 35 | B10: ALVARO MORAN RODRIGUEZ | C10: 928768676 | G10: PSICOLOGIA | H10: CENTRAL | J10: 2025-II | N10: SE ENVIÓ INFORMACIÓN | O10: MOSTRÓ INTERÉS | W10: Melisa Arciga
A11: 78 | B11: IRMA LLAMOCCA | C11: 926617690 | G11: PSICOLOGIA | H11: CENTRAL | J11: 2025-II | N11: SE ENVIÓ INFORMACIÓN | O11: NO CONTESTA | W11: Melisa Arciga
A12: 578 | B12: KRISSTEL OTINIANO PALACIOS | C12: 922583646 | G12: COMUNICACIONES | H12: CENTRAL | I12: SURQUILLO | J12: 2025-II | N12: SE ENVIÓ INFORMACIÓN | W12: Melisa Arciga
A13: 85728 | B13: Isis Manrique | C13: 924459370 | D13: danaisis@hotmail.com | G13: PSICOLOGIA | H13: CENTRAL | I13: LIMA | L13: Taller Vivencial 3 | M13: 45854 | N13: SE ENVIO INFORMACION | O13: NO CONTESTA | W13: Pya Pinto
A14: 95016 | B14: KARLA NICOLE ACEVEDO ESPINOZA | C14: 936432292 | D14: KARLACEVEDO2009@GMAIL.COM | G14: PSICOLOGIA | H14: CENTRAL | J14: 2025-II | M14: 45841 | N14: SE ENVIÓ INFORMACIÓN | O14: NO CONTESTA | W14: Estrella Vergara
A15: 112233 | B15: Milagros Sandro Del Pozo | C15: 952686711 | D15: d00498116x@perueduca.edu.pe | E15: 5TO | F15: ORDINARIO | G15: PSICOLOGIA | H15: PAUTA DIGITAL | I15: SURQUILLO | L15: Taller Vivencial 3 | M15: 45845 | N15: SE ENVIÓ INFORMACIÓN | O15: EVALUANDO OPCIONES | P15: EVALUANDO OPCIONES | W15: Pya Pinto
A16: 125877 | B16: Carmel Art | C16: 51947468123 | D16: Carmencita_art@hotmail.com | E16: TERMINÉ EL COLEGIO | F16: ORDINARIO | G16: PSICOLOGIA | H16: PAUTA DIGITAL | J16: 2025-II | L16: Taller Vivencial 3 | N16: SE ENVIÓ INFORMACIÓN | W16: Sheyla Peña
A17: 283550 | B17: Natacha Hernandez Caruto | C17: 51908875718 | D17: caruto_18@hotmail.com | G17: PSICOLOGIA | H17: CENTRAL | J17: 2025-II | M17: 45841 | N17: SE ENVIÓ INFORMACIÓN | V17: CENTRAL | W17: Lilya Espinoza
A18: 428783 | B18: Jesús Paúcar Moreano | C18: 934063636 | D18: jpaucar2@gmail.com | E18: terminé_el_colegio | G18: COMUNICACIONES | H18: PAUTA DIGITAL | K18: Open Day 3 | L18: Open Day 3 | M18: 45876 | N18: SE ENVIÓ INFORMACIÓN | W18: Estrella Vergara
A19: 507578 | B19: Mery Sosa Camma | C19: 51 992 352 828 | D19: merysosa06@gmail.com | G19: TURISMO | H19: EVENTO PRESENCIAL | I19: SURQUILLO | J19: 2025-II | N19: NO CONTESTA | O19: NO CONTESTA | P19: NO CONTESTA | W19: Lilya Espinoza
A20: 513208 | B20: David Maquera | C20: 51999225125 | D20: dmaquera2004@gmail.com | G20: PSICOLOGIA | H20: CENTRAL | J20: 2025-II | M20: 45841 | N20: SE ENVIÓ INFORMACIÓN | V20: CENTRAL | W20: Pya Pinto
A21: 606162 | B21: hermelinda segobia huarancca | C21: 937382639 | G21: TURISMO | H21: CENTRAL | L21: Open Day 3 | M21: 45880 | N21: MOSTRO INTERES | O21: SI CONFIRMÓ PARA EL EVENTO | P21: SI CONFIRMÓ PARA EL EVENTO | W21: Pya Pinto
A22: 613148 | B22: COLMENARES LUGO GABRIEL | C22: 51920305634 | D22: gabrielcolmenares774@gmail.com | G22: PSICOLOGIA | H22: PAUTA DIGITAL | J22: 2025-II | K22: Open Day 2 | L22: Open Day 2 | N22: SE ENVIÓ INFORMACIÓN | W22: Lilya Espinoza
A23: 618432 | B23: Diego Penito | C23: 942139910 | D23: Diego.penito@gmail.com | G23: TURISMO | H23: PAUTA DIGITAL | I23: SURQUILLO | J23: 2025-II | N23: SE ENVIÓ INFORMACIÓN | O23: NO CONTESTA | P23: NO CONTESTA | W23: Melisa Arciga
A24: 714637 | B24: Gabriela | C24: 938219941 | D24: fiestaslamiley@gmail.com | G24: PSICOLOGIA | H24: PAUTA DIGITAL | I24: SURQUILLO | J24: 2025-II | N24: SE ENVIÓ INFORMACIÓN | O24: NO CONTESTA | W24: Melisa Arciga
A25: 722570 | B25: Oriana | C25: 51938937145 | D25: oriana.reve@gmail.com | G25: COMUNICACIONES | H25: PAUTA DIGITAL | I25: SURQUILLO | J25: 2025-II | K25: Taller Vivencial 3 | L25: Taller Vivencial 3 | N25: MOSTRÓ INTERÉS | O25: SI CONFIRMÓ PARA EL EVENTO | W25: Pya Pinto
A26: 806080 | B26: Greisy Primera | C26: 948064920 | D26: primerageily@gmail.com | G26: PSICOLOGIA | H26: CENTRAL | J26: 2025-II | N26: SE ENVIÓ INFORMACIÓN | O26: MOSTRÓ INTERÉS | W26: Melisa Arciga
A27: 857281 | B27: Isis Manrique | C27: 51924459370 | D27: danaisis@hotmail.com | E27: terminé_el_colegio | F27: ORDINARIO | G27: PSICOLOGIA | H27: PAUTA DIGITAL | K27: Admisión regular | L27: Admisión regular | M27: 45849 | N27: SE ENVIÓ INFORMACIÓN | W27: Estrella Vergara
A28: 912327 | B28: Diego Vega | C28: 915269388 | D28: dvegacn@gmail.com | G28: COMUNICACIONES | H28: PAUTA DIGITAL | J28: 2025-II | K28: Taller Vivencial 2 | L28: Taller Vivencial 3 | N28: SE ENVIÓ INFORMACIÓN | O28: NO CONTESTA | W28: Sheyla Peña
A29: 919237 | B29: the_diamond_dv | C29: 51915111599 | D29: ferjesus88@hotmail.com | G29: COMUNICACIONES | H29: PAUTA DIGITAL | I29: SURQUILLO | J29: 2025-II | K29: Open Day 2 | L29: Open Day 2 | N29: NO CONTESTA | O29: NO CONTESTA | P29: NO CONTESTA | W29: Pya Pinto
A30: 1114661 | B30: Marco Andres | C30: 902632791 | D30: marcoamaya2008@gmail.com | G30: TURISMO | H30: CENTRAL | J30: 2025-II | M30: 45841 | N30: SE ENVIÓ INFORMACIÓN | V30: CENTRAL | W30: Pya Pinto
A31: 1345107 | B31: Liz Regina Maraza | C31: 973133850 | D31: rhondagroupholding@gmail.com | E31: terminé_el_colegio | F31: ORDINARIO | G31: PSICOLOGIA | H31: PAUTA DIGITAL | I31: SURQUILLO | J31: 2025-II | N31: SE ENVIÓ INFORMACIÓN | O31: MOSTRÓ INTERÉS | W31: Melisa Arciga
A32: 1367992 | B32: EMILIA PONCELEON MARTINEZ | C32: 982752611 | D32: emiliaponceleon@gmail.com | G32: COMUNICACIONES | H32: CENTRAL | J32: 2025-II | M32: 45841 | N32: SE ENVIÓ INFORMACIÓN | V32: CENTRAL | W32: Lilya Espinoza
A33: 1438773 | B33: Francia Elena Cruz Herrera | C33: 51965825500 | D33: franciaherrera1626@hotmail.com | G33: PSICOLOGIA | H33: PAUTA DIGITAL | J33: 2025-II | K33: Open Day 2 | L33: Open Day 2 | N33: SE ENVIÓ INFORMACIÓN | W33: Lilya Espinoza
A34: 1457920 | B34: Camila Victoria Campos | C34: 930769860 | D34: gatitolover27@gmail.com | G34: PSICOLOGIA | H34: CENTRAL | J34: 2025-II | M34: 45841 | N34: SE ENVIÓ INFORMACIÓN | V34: CENTRAL | W34: Pya Pinto
A35: 1461367 | B35: Roxana urbina | C35: 936019829 | D35: roxanaurbina_10297@hotmail.com | G35: PSICOLOGIA | H35: WEB | J35: 2025-II | M35: 45841 | N35: OTROS | V35: DIO EXAMEN EN CENTRAL | W35: Lilya Espinoza
A36: 1545103 | B36: Renata Franco | C36: 939281557 | D36: renatafranco86@gmail.com | E36: TERMINÉ EL COLEGIO | F36: ORDINARIO | G36: PSICOLOGIA | H36: PAUTA DIGITAL | I36: SURQUILLO | J36: 2025-II | N36: NO CONTESTA | W36: Estrella Vergara
A37: 1670664 | B37: Marco Paredes | C37: 51903433502 | D37: marcoantoniopa.so171@gmail.com | G37: TURISMO | H37: CENTRAL | J37: 2025-II | M37: 45841 | N37: SE ENVIÓ INFORMACIÓN | V37: CENTRAL | W37: Lilya Espinoza
A38: 1862131 | B38: Richard Lenin | C38: 933655616 | D38: richardlenin@gmail.com | E38: terminé_el_colegio | G38: COMUNICACIONES | H38: CENTRAL | K38: Examen Digital | L38: Examen Digital | M38: 45880 | N38: SE ENVIO INFORMACION | W38: Pya Pinto
A39: 1862131 | B39: Richard Lenin | C39: 933655616 | D39: richardlenin@gmail.com | G39: COMUNICACIONES | H39: CENTRAL | L39: Open Day 3 | M39: 45880 | N39: SE ENVIO INFORMACION | W39: Pya Pinto
A40: 1942861 | B40: ANTONIO PAEZ TOMASSI | C40: 931125510 | G40: PSICOLOGIA | H40: CENTRAL | J40: 2025-II | M40: 45841 | N40: INCONTACTABLE | O40: NO CONTESTA | V40: CENTRAL | W40: Sheyla Peña
A41: 2418105 | B41: Dora De la Ciudad de los Vientos | C41: 51918008424 | D41: aguilardorah@gmail.com | G41: COMUNICACIONES | H41: CENTRAL | L41: Open Day 3 | M41: 45854 | N41: SE ENVIÓ INFORMACIÓN | W41: Sheyla Peña
A42: 2446588 | B42: Lourdes Vega Mansilla | C42: 51966601094 | D42: lourdesvegamansilla6@gmail.com | E42: terminé_el_colegio | G42: PSICOLOGIA | H42: PAUTA DIGITAL | K42: Examen Digital | M42: 45855 | N42: SE ENVIÓ INFORMACIÓN | P42: MOSTRÓ INTERÉS | W42: Lilya Espinoza
A43: 2743138 | B43: Victor Manuel Tume Ruíz | C43: 949780981 | D43: victortumelocutor@gmail.com | F43: COMPLEMENTACIÓN ACADÉMICA | G43: COMUNICACIONES | H43: PAUTA DIGITAL | I43: SURQUILLO | M43: 45845 | N43: SE ENVIÓ INFORMACIÓN | O43: NO CONTESTA | P43: NO CONTESTA | V43: TITULADO TÉCNICO | W43: Pya Pinto
A44: 2879220 | B44: Carolina Caro | C44: 991887301 | D44: Carolina.silva@gruposcp.com | G44: COMUNICACIONES | H44: PAUTA DIGITAL | J44: 2025-II | K44: Open Day 2 | L44: Taller Vivencial 3 | N44: MOSTRÓ INTERÉS | O44: MOSTRÓ INTERÉS | W44: Sheyla Peña
A45: 2899433 | B45: Jessica Abramonte Benites | C45: 51968140062 | D45: jessica.abramonte2@gmail.vom | G45: COMUNICACIONES | H45: CENTRAL | J45: 2025-II | L45: Taller Vivencial 3 | M45: 45841 | N45: SELECCIONO OTRA UNIVERSIDAD | O45: SELECCIONO OTRA UNIVERSIDAD | V45: INSCRITA X CENTRAL USMP | W45: Sheyla Peña
A46: 2944074 | B46: Carlos Toro | C46: 987800311 | D46: robertochumbiauca01@gmail.com | G46: PSICOLOGIA | H46: PAUTA DIGITAL | I46: SURQUILLO | J46: 2025-II | N46: SE ENVIÓ INFORMACIÓN | O46: MOSTRÓ INTERÉS | W46: Melisa Arciga
A47: 3017830 | B47: Enderson Monsalve | C47: 937181895 | D47: enderjosemonsalve@hotmail.com | G47: PSICOLOGIA | H47: CENTRAL | I47: LIMA | L47: Taller Vivencial 3 | M47: 45854 | N47: SE ENVIO INFORMACION | O47: NO CONTESTA | W47: Pya Pinto
A48: 3034445 | B48: Annither Vilchez | C48: 51918386755 | D48: annithervilchez@gmail.com | G48: PSICOLOGIA | H48: PAUTA DIGITAL | I48: SURQUILLO | J48: 2025-II | K48: Open Day 2 | L48: Open Day 2 | N48: NO CONTESTA | O48: NO CONTESTA | P48: NO CONTESTA | W48: Pya Pinto
A49: 3071791 | B49: Waleska Bravo noguera | C49: 51906106848 | D49: waleskabr10@gmail.com | E49: Juana Alarco de Dammert | F49: PRIMERA ALTERNATIVA | G49: PSICOLOGIA | H49: PAUTA DIGITAL | I49: SURQUILLO | J49: 2026-I | N49: MOSTRÓ INTERÉS | O49: MOSTRÓ INTERÉS | P49: MOSTRÓ INTERÉS | Q49: NO- VIRTUAL | R49: ADMITIDO | S49: VIRTUAL | T49: RINDIO VIRTUAL | U49: PENDIENTE TODO | W49: Lilya Espinoza
A50: 3494278 | B50: Hector Eduardo Querevalu Ruesta | C50: 954964281 | D50: eventosprotocolares1972@gmail.com | E50: NO TIENE TÍTULO TÉCNICO | F50: COMPLEMENTACIÓN ACADÉMICA | G50: COMUNICACIONES | H50: PAUTA DIGITAL | I50: SURQUILLO | J50: 2025-II | N50: NO CONTESTA | W50: Estrella Vergara
A51: 3508862 | B51: Sulma Benavides Paz | C51: 51955870128 | D51: sulmaben@sulmaben.com | E51: 5to_de_secundaria | G51: COMUNICACIONES | H51: PAUTA DIGITAL | K51: Open Day 3 | L51: Open Day 3 | M51: 45876 | N51: SE ENVIÓ INFORMACIÓN | W51: Lilya Espinoza
A52: 4004564 | B52: Emily Di Bernardo | C52: 51902494323 | D52: Emily.dibernardo28@gmail.com | G52: PSICOLOGIA | H52: CENTRAL | J52: 2025-II | M52: 45841 | N52: SE ENVIÓ INFORMACIÓN | V52: CENTRAL | W52: Lilya Espinoza
A53: 4047038 | B53: Javier David Meza Malpartida | C53: 989418077 | D53: mirian.meza.c@hotmail.com | E53: BERLOT BRECH | F53: ORDINARIO | G53: PSICOLOGIA | H53: BASE ANTIGUA | I53: SURQUILLO | J53: 2025-II | N53: MOSTRÓ INTERÉS | O53: MOSTRÓ INTERÉS | W53: Melisa Arciga
A54: 4084274 | B54: Edith Villanueva | C54: 997382287 | D54: edithvillanuevat@gmail.com | E54: terminé_el_colegio | G54: PSICOLOGIA | H54: PAUTA DIGITAL | K54: Admisión regular | L54: Admisión regular | M54: 45848 | N54: SE ENVIO INFORMACION | O54: NO CONTESTA | P54: NO CONTESTA | W54: Pya Pinto
A55: 4394451 | B55: Ariana Sequera Sequera | C55: 51934007737 | D55: kathy93sequera@gmail.com | G55: TURISMO | H55: CENTRAL | J55: 2025-II | M55: 45841 | N55: SE ENVIÓ INFORMACIÓN | V55: CENTRAL | W55: Lilya Espinoza
A56: 4481897 | B56: Gabriela Carrasco | C56: 958372223 | D56: gcc.gaela@gmail.com | G56: COMUNICACIONES | H56: EVENTO PRESENCIAL | I56: SURQUILLO | J56: 2025-II | N56: MOSTRÓ INTERÉS | W56: Estrella Vergara
A57: 4648225 | B57: elizabeth Ladino ll | C57: 947993533 | D57: elizabethladinollanos1788@gmail.com | E57: terminé_el_colegio | G57: COMUNICACIONES | H57: PAUTA DIGITAL | K57: Admisión regular | M57: 45851 | N57: SE ENVIO INFORMACION | O57: EVALUANDO OPCIONES | P57: EVALUANDO OPCIONES | W57: Pya Pinto
A58: 4730723 | B58: rodolfo quispe huaman | C58: 963790632 | D58: 20155003unica.edu.pe | G58: PSICOLOGIA | H58: CENTRAL | J58: 2025-II | M58: 45841 | N58: SE ENVIÓ INFORMACIÓN | V58: CENTRAL | W58: Pya Pinto
A59: 4959414 | B59: Ambhar León | C59: 952314334 | D59: ambharleon8@gmail.com | E59: TERMINÉ EL COLEGIO | F59: ORDINARIO | G59: PSICOLOGIA | H59: PAUTA DIGITAL | I59: SURQUILLO | J59: 2025-II | N59: NO CONTESTA | W59: Estrella Vergara
A60: 5213298 | B60: yerli valentina | C60: 51955365544 | D60: katherinahylin16@gmail.com | E60: terminé_el_colegio | G60: PSICOLOGIA | H60: PAUTA DIGITAL | K60: Admisión regular | L60: Open Day 3 | M60: 45859 | N60: SE ENVIÓ INFORMACIÓN | O60: NO CONTESTA | W60: Sheyla Peña
A61: 5388541 | B61: Anselmo Ojanama Mosqueda | C61: 51921978633 | D61: ojanamaanselmo3@gmail.com | E61: NO TIENE TITULO TECNICO | F61: COMPLEMENTACIÓN ACADÉMICA | G61: TURISMO | H61: PAUTA DIGITAL | I61: SURQUILLO | J61: 2025-II | N61: NO CONTESTA | O61: INCONTACTABLE | P61: INCONTACTABLE | W61: Pya Pinto
A62: 5403393 | B62: Patty Rodriguez Bravo | C62: 962327385 | D62: kristyne_28@hotmail.com | E62: terminé_el_colegio | G62: PSICOLOGIA | H62: PAUTA DIGITAL | K62: Admisión regular | L62: Admisión regular | M62: 45855 | N62: SE ENVIO INFORMACION | W62: Pya Pinto
A63: 5417514 | B63: Marian Rodriguez Tovar | C63: 923903389 | D63: multiplexrx@gmail.com | G63: PSICOLOGIA | H63: CENTRAL | J63: 2025-II | L63: Taller Vivencial 3 | M63: 45841 | N63: SE ENVIÓ INFORMACIÓN | O63: NO CONTESTA | V63: CENTRAL | W63: Sheyla Peña
A64: 5462325 | B64: Isamar Camila Parra Colina | C64: 913556727 | D64: isamarparra4@gmail.com | G64: COMUNICACIONES | H64: EVENTO PRESENCIAL | I64: SURQUILLO | J64: 2026-I | K64: VIERNES 27/06 | L64: VIERNES 27/06 | N64: NO CONTESTA | O64: NO CONTESTA | P64: NO CONTESTA | W64: Lilya Espinoza
A65: 5573682 | B65: Sara Romero | C65: 51902705369 | D65: sromero@sdlingenieros.com | E65: terminé_el_colegio | G65: PSICOLOGIA | H65: PAUTA DIGITAL | K65: Admisión regular | L65: Admisión regular | M65: 45880 | N65: SE ENVIÓ INFORMACIÓN | W65: Estrella Vergara
A66: 6023114 | B66: Juan La Torre | C66: 998466856 | D66: jlto26547@gmail.com | G66: COMUNICACIONES | H66: CENTRAL | J66: 2025-II | L66: Taller Vivencial 3 | M66: 45841 | N66: SE ENVIÓ INFORMACIÓN | O66: NO CONTESTA | V66: CENTRAL | W66: Sheyla Peña
A67: 6081420 | B67: Carmen Rosa Huamán Herrera | C67: 51976180447 | D67: carmenrosahuamanherrera@gmail.com | E67: 5TO | F67: EXAMEN DIGITAL | G67: PSICOLOGIA | H67: PAUTA DIGITAL | J67: 2026-I | N67: SE ENVIÓ INFORMACIÓN | W67: Estrella Vergara
A68: 6098938 | B68: Betty Angelino jaramillo | C68: 964915779 | D68: betty_aj@outlook.es | F68: ORDINARIO | G68: PSICOLOGIA | H68: EVENTO PRESENCIAL | I68: SURQUILLO | J68: 2025-II | N68: MOSTRÓ INTERÉS | O68: MOSTRÓ INTERÉS | P68: MOSTRÓ INTERÉS | W68: Pya Pinto
A69: 6108527 | B69: Ken Ulises Ordóñes Romero | C69: 948724376 | D69: ordonesulises504@gmail.com | E69: terminé_el_colegio | G69: COMUNICACIONES | H69: WEB | K69: Admisión regular | L69: Admisión regular | M69: 45873 | N69: SE ENVIO INFORMACION | W69: Pya Pinto
A70: 6143146 | B70: CAMILA SOFIA CHAVEZ DELGADO | C70: 977664504 | D70: cschavezd@gmail.com | G70: PSICOLOGIA | H70: CENTRAL | J70: 2025-II | M70: 45841 | N70: SE ENVIÓ INFORMACIÓN | O70: NO CONTESTA | W70: Estrella Vergara
A71: 6143223 | B71: Gabriel Eduardo peña | C71: 922213567 | D71: hemberleth2@gmail.com | E71: terminé_el_colegio | G71: COMUNICACIONES | H71: PAUTA DIGITAL | K71: Taller Vivencial 3 | L71: Taller Vivencial 3 | M71: 45850 | N71: MOSTRÓ INTERÉS | O71: SI CONFIRMÓ PARA EL EVENTO | W71: Melisa Arciga
A72: 6145916 | B72: Fabiola Belen Mamani Arias | C72: 938432562 | D72: beelyfabs@gmail.com | G72: PSICOLOGIA | H72: CENTRAL | J72: 2025-II | L72: Taller Vivencial 3 | M72: 45841 | N72: SE ENVIÓ INFORMACIÓN | O72: NO CONTESTA | V72: CENTRAL | W72: Sheyla Peña
A73: 6150075 | B73: Aixa Infante Noriega | C73: 925403341 | D73: aminnoriega13@gmail.com | G73: TURISMO | H73: CENTRAL | L73: Taller Vivencial 3 | M73: 45854 | N73: SE ENVIO INFORMACION | O73: NO CONTESTA | W73: Pya Pinto
A74: 6184412 | B74: Andrea rubi | C74: 51930774349 | D74: sol818096@gmail.com | E74: 5to_de_secundaria | G74: COMUNICACIONES | H74: PAUTA DIGITAL | K74: Open Day 3 | L74: Open Day 3 | M74: 45880 | N74: SE ENVIÓ INFORMACIÓN | W74: Sheyla Peña
A75: 6215792 | B75: Yarleis Vargas | C75: 925422390 | D75: yarleisvargas@hotmail.com | G75: PSICOLOGIA | H75: WEB | J75: 2025-II | M75: 45841 | W75: Estrella Vergara
A76: 6324084 | B76: Greici Quintero | C76: 918210887 | D76: greiciceciliaq@gmail.com | G76: PSICOLOGIA | H76: EVENTO PRESENCIAL | J76: 2025-II | L76: Taller Vivencial 3 | N76: NO CONTESTA | W76: Sheyla Peña
A77: 6646863 | B77: Ana Villegas | C77: 958365155 | D77: anavillegasvz4@gmail.com | E77: TITULADO TECNICO | F77: COMPLEMENTACIÓN ACADÉMICA | G77: TURISMO | H77: PAUTA DIGITAL | I77: SURQUILLO | J77: 2025-II | N77: SE ENVIÓ INFORMACIÓN | P77: NO CONTESTA | W77: Melisa Arciga
A78: 6659954 | B78: Lyhindhaafhlorh Becerra Castillo | C78: 902163722 | D78: rosabecerra.892@gmail.com | G78: TURISMO | H78: CENTRAL | J78: 2025-II | L78: Taller Vivencial 3 | M78: 45841 | N78: OTROS | O78: OTROS | V78: PRECIO | W78: Sheyla Peña
A79: 6662583 | B79: Marielena Cordova | C79: 938917077 | D79: elenita070767@gmail.com | E79: 5TO | G79: PSICOLOGIA | H79: PAUTA DIGITAL | I79: SURQUILLO | L79: Taller Vivencial 3 | M79: 45844 | N79: MOSTRÓ INTERÉS | O79: MOSTRÓ INTERÉS | W79: Pya Pinto
A80: 6663909 | B80: Fiorella Torre Velarde | C80: 997384461 | D80: fiorelin1911@gmail.com | G80: PSICOLOGIA | H80: WEB | J80: 2025-II | L80: Taller Vivencial 3 | M80: 45841 | N80: SELECCIONO OTRA UNIVERSIDAD | O80: SELECCIONO OTRA UNIVERSIDAD | V80: CENTRAL | W80: Sheyla Peña
A81: 6668623 | B81: Elsa Quispe | C81: 947317188 | D81: elsita1311@hotmail.com | G81: PSICOLOGIA | H81: CENTRAL | J81: 2025-II | M81: 45841 | N81: SE ENVIÓ INFORMACIÓN | V81: CENTRAL | W81: Pya Pinto
A82: 6671199 | B82: Jackeline gonzales Huaymacari Gonzales Huaymacari | C82: 51976522775 | D82: jackelinegonza31@gmail.com | G82: PSICOLOGIA | H82: EVENTO PRESENCIAL | J82: 2025-II | L82: Taller Vivencial 3 | N82: NO CONTESTA | W82: Sheyla Peña
A83: 6736704 | B83: Julio Raul Narvaez Pardave | C83: 51986663527 | D83: sudjulio@hotmail.com | E83: TITULADO TECNICO | F83: COMPLEMENTACIÓN ACADÉMICA | G83: TURISMO | H83: PAUTA DIGITAL | J83: 2025-II | L83: Taller Vivencial 3 | N83: NO CONTESTA | W83: Sheyla Peña
A84: 6752323 | B84: Vicente Ore Arango | C84: 986529513 | D84: orearangovicente@gmail.com | G84: COMUNICACIONES | H84: PAUTA DIGITAL | I84: SURQUILLO | J84: 2025-II | K84: Taller Vivencial 3 | L84: Taller Vivencial 3 | N84: MOSTRÓ INTERÉS | O84: SI CONFIRMÓ PARA EL EVENTO | W84: Pya Pinto
A85: 6765392 | B85: gilberto ayala Valenzuela | C85: 51924338307 | D85: gilberto_2024_129@hotmail.com | E85: terminé_el_colegio | G85: TURISMO | H85: PAUTA DIGITAL | K85: Examen Digital | L85: Open Day 3 | M85: 45868 | N85: SE ENVIÓ INFORMACIÓN | O85: NO CONTESTA | W85: Sheyla Peña
A86: 6773721 | B86: Ana Patricia Saravia Acostao | C86: 990330084 | D86: anapatricia.saraviaacosta@gmail.com | G86: COMUNICACIONES | H86: PAUTA DIGITAL | I86: SURQUILLO | J86: 2025-II | N86: SE ENVIÓ INFORMACIÓN | O86: MOSTRÓ INTERÉS | P86: MOSTRÓ INTERÉS | W86: Melisa Arciga
A87: 6774108 | B87: Carola Roldan | C87: 992774355 | D87: cmroldanc@hotmail.com | G87: COMUNICACIONES | H87: CENTRAL | L87: Open Day 3 | M87: 45880 | N87: SE ENVIO INFORMACION | W87: Pya Pinto
A88: 6774480 | B88: Mabel Catherine Esteban Pérez | C88: 914921797 | D88: +51 912 663 438 | G88: PSICOLOGIA | H88: EVENTO PRESENCIAL | I88: SURQUILLO | J88: 2026-I | N88: NO CONTESTA | W88: Estrella Vergara
A89: 6780766 | B89: Flor Giovana Biorggio Casasola | C89: 51988616911 | D89: giovanabiorggio6@gmail.com | E89: TERMINÉ EL COLEGIO | F89: ORDINARIO | G89: PSICOLOGIA | H89: PAUTA DIGITAL | I89: SURQUILLO | J89: 2025-II | N89: MOSTRÓ INTERÉS | O89: MOSTRÓ INTERÉS | P89: MOSTRÓ INTERÉS | W89: Pya Pinto
A90: 6781129 | B90: Maria Cerro Torres | C90: 51958908383 | D90: mariacerro2009@gmail.com | G90: PSICOLOGIA | H90: CENTRAL | J90: 2025-II | N90: SE ENVIÓ INFORMACIÓN | W90: Melisa Arciga
A91: 6784118 | B91: Silvia Llontop | C91: 51984257202 | D91: christiandrea28573@gmail.com | E91: 5to_de_secundaria | G91: COMUNICACIONES | H91: PAUTA DIGITAL | K91: Open Day 3 | L91: Open Day 3 | M91: 45874 | N91: SE ENVIÓ INFORMACIÓN | W91: Melisa Arciga
A92: 6789491 | B92: Zarela CuAyasta | C92: 51999778191 | D92: zalcua@hotmail.com | G92: PSICOLOGIA | H92: CENTRAL | L92: Taller Vivencial 3 | M92: 45854 | N92: SE ENVIÓ INFORMACIÓN | W92: Sheyla Peña
A93: 6790314 | B93: Felipe Davila | C93: 51973814195 | D93: FELIPETINTO@GMAIL.COM | G93: PSICOLOGIA | H93: CENTRAL | J93: 2025-II | M93: 45841 | N93: SE ENVIÓ INFORMACIÓN | V93: CENTRAL | W93: Lilya Espinoza
A94: 6795271 | B94: Margarita Morales Chujutalli | C94: 51989889683 | D94: iramos@america.edu.pe | G94: COMUNICACIONES | H94: PAUTA DIGITAL | I94: SURQUILLO | J94: 2025-II | K94: Taller Vivencial 2 | L94: Taller Vivencial 2 | N94: SE ENVIÓ INFORMACIÓN | O94: NO CONTESTA | P94: NO CONTESTA | W94: Pya Pinto
A95: 6796056 | B95: Maria Jesus | C95: 935192377 | D95: mariajesus-lopez@hotmail.com | G95: COMUNICACIONES | H95: CENTRAL | L95: Open Day 3 | M95: 45880 | N95: SE ENVIO INFORMACION | W95: Pya Pinto
A96: 6804524 | B96: Gladys La Flaquita | C96: 51987533993 | D96: gldumbbd@hotmail.com | G96: PSICOLOGIA | H96: PAUTA DIGITAL | J96: 2025-II | K96: Taller Vivencial 2 | L96: Taller Vivencial 2 | N96: NO CONTESTA | W96: Lilya Espinoza
A97: 6805020 | B97: Nati | C97: 959381813 | D97: nkanashiroa@hotmail.com | E97: 5to_de_secundaria | G97: COMUNICACIONES | H97: PAUTA DIGITAL | K97: Taller Vivencial 3 | L97: Taller Vivencial 3 | M97: 45850 | N97: SE ENVIÓ INFORMACIÓN | O97: ESPERANDO CONFIRMACIÓN PARA EL EVENTO | W97: Melisa Arciga
A98: 6812526 | B98: Ademir Rivera Vergara | C98: 902112427 | D98: ademirchosica@gmail.com | G98: COMUNICACIONES | H98: PAUTA DIGITAL | J98: 2025-II | K98: Taller Vivencial 2 | L98: Taller Vivencial 3 | N98: SE ENVIÓ INFORMACIÓN | O98: MOSTRÓ INTERÉS | W98: Sheyla Peña
A99: 6812583 | B99: María Esther Robles Almeida | C99: 51981538715 | D99: mera316@hotmail.com | G99: PSICOLOGIA | H99: CENTRAL | J99: 2025-II | L99: Taller Vivencial 3 | M99: 45841 | N99: SE ENVIÓ INFORMACIÓN | V99: CENTRAL | W99: Sheyla Peña
A100: 6815340 | B100: Pyter Gino Calderon Trujillo | C100: 969320881 | D100: pytergim2014@gmail.com | G100: COMUNICACIONES | H100: EVENTO PRESENCIAL | I100: SURQUILLO | J100: 2026-I | N100: NO CONTESTA | O100: NO CONTESTA | P100: NO CONTESTA | W100: Lilya Espinoza
...

Sheet BD|Pya P.
A1: DNI | B1: NOMBRES | C1: CELULAR | D1: CORREO | E1: COLEGIO DE PROCEDENCIA | F1: MODALIDAD | G1: ESCUELA | H1: ORIGEN | I1: SEDE | J1: SEMESTRE | K1: CAMPAÑA | L1: EVENTO | M1: FECHA DE INGRESO DE LEAD | N1: CONTACTO I | O1: CONTACTO II | P1: CONTACTO III | Q1: ¿PAGÓ DERECHO DE INSCRIPCIÓN? | R1: STATUS ACADÉMICO | S1: TIPO DE EXAMEN | T1: STATUS DE EXAMEN | U1: ENTREGA DE DOCUMENTOS | V1: OBSERVACION
A2: 75692011 | B2: Leonardo Joaquín Torres Soria | C2: 987844691 | D2: leonardojoaquin_ts@hotmail.com | E2: TERMINO EL COLEGIO | F2: ORDINARIO | G2: COMUNICACIONES | H2: PAUTA DIGITAL | I2: SURQUILLO | J2: 2025-II | K2: Taller Vivencial 2 | L2: Taller Vivencial 2 | N2: MOSTRÓ INTERÉS | O2: MOSTRÓ INTERÉS | P2: =TRIM(BD_PyaPinto[[#This Row],[CONTACTO II]]) -> MOSTRÓ INTERÉS | Q2: NO - VIRTUAL | R2: ADMITIDO | S2: VIRTUAL | T2: RINDIO VIRTUAL | U2: PENDIENTE TODO
A3: 74683685 | B3: Ruiz Grippa Fabian Emilio | C3: 930 802 194 | D3: fabianemilioruizgrippa@gmail.com | F3: ORDINARIO | G3: COMUNICACIONES | H3: BASE ANTIGUA | I3: SURQUILLO | J3: 2025-II | N3: MOSTRÓ INTERÉS | O3: MOSTRÓ INTERÉS | P3: =TRIM(BD_PyaPinto[[#This Row],[CONTACTO II]]) -> MOSTRÓ INTERÉS | Q3: NO - VIRTUAL | R3: ADMITIDO | S3: VIRTUAL | T3: RINDIO VIRTUAL | U3: PENDIENTE TODO
A4: 41810776 | B4: Omar Arturo Contreras Costilla | C4: 951199456 | D4: oacontrerascostilla@gmail.com | G4: COMUNICACIONES | H4: PAUTA DIGITAL | I4: SURQUILLO | J4: 2025-II | K4: Taller Vivencial 2 | L4: Open Day 3 | N4: SE ENVIÓ INFORMACIÓN | O4: ESPERANDO CONFIRMACIÓN PARA EL EVENTO | P4: ESPERANDO CONFIRMACIÓN PARA EL EVENTO
A5: 6752323 | B5: Vicente Ore Arango | C5: 986529513 | D5: orearangovicente@gmail.com | G5: COMUNICACIONES | H5: PAUTA DIGITAL | I5: SURQUILLO | J5: 2025-II | K5: Taller Vivencial 3 | L5: Taller Vivencial 3 | N5: MOSTRÓ INTERÉS | O5: SI CONFIRMÓ PARA EL EVENTO
A6: 40946106 | B6: Evelyn Leon | C6: 51992288193 | D6: eleonr2603@gmail.com | G6: COMUNICACIONES | H6: PAUTA DIGITAL | I6: SURQUILLO | J6: 2025-II | K6: Taller Vivencial 2 | L6: Taller Vivencial 2 | N6: SE ENVIÓ INFORMACIÓN | O6: MOSTRÓ INTERÉS | P6: =TRIM(BD_PyaPinto[[#This Row],[CONTACTO II]]) -> MOSTRÓ INTERÉS
A7: 71407994 | B7: Martín David Aguirre De La Cruz | C7: 931001314 | G7: TURISMO | H7: PAUTA DIGITAL | I7: SURQUILLO | J7: 2025-II | N7: MOSTRÓ INTERÉS | O7: MOSTRÓ INTERÉS | P7: =TRIM(BD_PyaPinto[[#This Row],[CONTACTO II]]) -> MOSTRÓ INTERÉS
A8: 71365616 | B8: Ariana Thais Sánchez Rupay | C8: 51992025484 | D8: arianitalinda17@gmail.com | G8: COMUNICACIONES | H8: PAUTA DIGITAL | I8: SURQUILLO | J8: 2025-II | K8: Open Day 2 | L8: Open Day 2 | N8: MOSTRÓ INTERÉS | O8: MOSTRÓ INTERÉS | P8: =TRIM(BD_PyaPinto[[#This Row],[CONTACTO II]]) -> MOSTRÓ INTERÉS
A9: 61516770 | B9: Thays Salazar | C9: 51965108345 | D9: thayssalazarvilchez@gmail.com | G9: COMUNICACIONES | H9: PAUTA DIGITAL | I9: SURQUILLO | J9: 2025-II | K9: Open Day 2 | L9: Open Day 2 | N9: NO CONTESTA | O9: MOSTRÓ INTERÉS | P9: =TRIM(BD_PyaPinto[[#This Row],[CONTACTO II]]) -> MOSTRÓ INTERÉS
A10: 42258994 | B10: LUCIA MERCEDES ROCHA MONTES | C10: 922863982 | D10: lucia.rochamontes@gmail.com | G10: COMUNICACIONES | H10: PAUTA DIGITAL | I10: SURQUILLO | J10: 2025-II | K10: Taller Vivencial 3 | L10: Open Day 3 | N10: SE ENVIÓ INFORMACIÓN | O10: ESPERANDO CONFIRMACIÓN PARA EL EVENTO | P10: ESPERANDO CONFIRMACIÓN PARA EL EVENTO
A11: 61022476 | B11: Joaquin Aleph Arribasplata Castañeda | C11: 997351278 | D11: jarribasplata88@gmail.com | E11: TERMINÉ EL COLEGIO | G11: COMUNICACIONES | H11: COUNTER | I11: SURQUILLO | J11: 2025-II | N11: MOSTRÓ INTERÉS | O11: MOSTRÓ INTERÉS | P11: =TRIM(BD_PyaPinto[[#This Row],[CONTACTO II]]) -> MOSTRÓ INTERÉS | Q11: NO - VIRTUAL | R11: ADMITIDO | S11: VIRTUAL | T11: RINDIO VIRTUAL | U11: PENDIENTE TODO
A12: 60492449 | B12: Ainnara Alvarado Paucar | C12: 941275338 | D12: Kimberlyalvarado0504@gmail.com | E12: TERMINÉ EL COLEGIO | G12: COMUNICACIONES | H12: PAUTA DIGITAL | I12: SURQUILLO | J12: 2025-II | K12: Open Day 2 | L12: Open Day 2 | N12: MOSTRÓ INTERÉS | O12: MOSTRÓ INTERÉS | P12: =TRIM(BD_PyaPinto[[#This Row],[CONTACTO II]]) -> MOSTRÓ INTERÉS
A13: 722570 | B13: Oriana | C13: 51938937145 | D13: oriana.reve@gmail.com | G13: COMUNICACIONES | H13: PAUTA DIGITAL | I13: SURQUILLO | J13: 2025-II | K13: Taller Vivencial 3 | L13: Taller Vivencial 3 | N13: MOSTRÓ INTERÉS | O13: SI CONFIRMÓ PARA EL EVENTO
B14: Juana Costilla Cahuaza | C14: 912031310 | D14: thaismencardenas@gmail.com | G14: COMUNICACIONES | H14: PAUTA DIGITAL | I14: SURQUILLO | J14: 2025-II | K14: Open Day 1 | L14: Open Day 1 | N14: MOSTRÓ INTERÉS | O14: MOSTRÓ INTERÉS | P14: =TRIM(BD_PyaPinto[[#This Row],[CONTACTO II]]) -> MOSTRÓ INTERÉS
B15: Jade Paredes Vargas | C15: 987193401 | D15: irennechafio@gmail.com | G15: COMUNICACIONES | H15: PAUTA DIGITAL | I15: SURQUILLO | J15: 2025-II | K15: Open Day 1 | L15: Open Day 1 | N15: MOSTRÓ INTERÉS | O15: MOSTRÓ INTERÉS | P15: =TRIM(BD_PyaPinto[[#This Row],[CONTACTO II]]) -> MOSTRÓ INTERÉS
B16: Ally | C16: 923025308 | D16: alexander200208ga@gmail.com | G16: COMUNICACIONES | H16: PAUTA DIGITAL | I16: SURQUILLO | J16: 2025-II | K16: Open Day 1 | L16: Open Day 1 | N16: SE ENVIÓ INFORMACIÓN | O16: NO CONTESTA | P16: =TRIM(BD_PyaPinto[[#This Row],[CONTACTO II]]) -> NO CONTESTA
B17: Lilian Rosario Oviedo Diaz | C17: 954561892 | D17: gimena9@outlook.com | G17: COMUNICACIONES | H17: PAUTA DIGITAL | I17: SURQUILLO | J17: 2025-II | K17: Open Day 1 | L17: Open Day 1 | N17: MOSTRÓ INTERÉS | O17: MOSTRÓ INTERÉS | P17: =TRIM(BD_PyaPinto[[#This Row],[CONTACTO II]]) -> MOSTRÓ INTERÉS
B18: Rosa Marin Alcantara | C18: 924148943 | D18: jennifer2007laroso@gmail.com | G18: COMUNICACIONES | H18: PAUTA DIGITAL | I18: SURQUILLO | J18: 2025-II | K18: Open Day 1 | L18: Open Day 1 | N18: NO CONTESTA | O18: NO CONTESTA | P18: =TRIM(BD_PyaPinto[[#This Row],[CONTACTO II]]) -> NO CONTESTA
B19: Juovisa | C19: 954043244 | D19: mrojasrossell.sap@gmail.com | G19: COMUNICACIONES | H19: PAUTA DIGITAL | I19: SURQUILLO | J19: 2025-II | K19: Open Day 1 | L19: Open Day 1 | N19: SE ENVIÓ INFORMACIÓN | O19: NO CONTESTA | P19: =TRIM(BD_PyaPinto[[#This Row],[CONTACTO II]]) -> NO CONTESTA
B20: Araziel Vallejo | C20: 936236347 | D20: arazielvallejo@gmail.com | G20: COMUNICACIONES | H20: PAUTA DIGITAL | I20: SURQUILLO | J20: 2025-II | K20: Open Day 1 | L20: Open Day 1 | N20: MOSTRÓ INTERÉS | O20: MOSTRÓ INTERÉS | P20: =TRIM(BD_PyaPinto[[#This Row],[CONTACTO II]]) -> MOSTRÓ INTERÉS
A21: 71182199 | B21: Avril Fernanda Trigoso Guillén | C21: 961611547 | D21: belyguillen@hotmail.com | G21: COMUNICACIONES | H21: PAUTA DIGITAL | I21: SURQUILLO | J21: 2025-II | K21: Taller Vivencial 3 | L21: Open Day 3 | N21: MOSTRÓ INTERÉS | O21: SI CONFIRMÓ PARA EL EVENTO | P21: SI CONFIRMÓ PARA EL EVENTO
A22: 43247154 | B22: flaviana Luciana Huanca Bravo | C22: 999497134 | D22: katrina2825@gmail.com | G22: COMUNICACIONES | H22: PAUTA DIGITAL | I22: SURQUILLO | J22: 2025-II | K22: Taller Vivencial 2 | L22: Taller Vivencial 2 | N22: MOSTRÓ INTERÉS | O22: MOSTRÓ INTERÉS | P22: MOSTRÓ INTERÉS
A23: 71175910 | B23: Valentino Imanol Campos Cueva | C23: 939 623 999 | D23: jessicacuevagz@gmail.com | F23: ORDINARIO | G23: PSICOLOGIA | H23: BASE ANTIGUA | I23: SURQUILLO | J23: 2025-II | N23: MOSTRÓ INTERÉS | O23: MOSTRÓ INTERÉS | P23: =TRIM(BD_PyaPinto[[#This Row],[CONTACTO II]]) -> MOSTRÓ INTERÉS | Q23: NO - VIRTUAL | R23: ADMITIDO | S23: VIRTUAL | T23: RINDIO VIRTUAL | U23: ENTREGADO-COMPLETO
A24: 70629594 | B24: Luis Fernando Martinez Ventura | C24: 926603128 | D24: martinezventuraluis1@gmail.com | E24: William Shakespeare | F24: ORDINARIO | G24: PSICOLOGIA | H24: EVENTO PRESENCIAL | I24: SURQUILLO | J24: 2025-II | L24: Taller Vivencial 3 | N24: MOSTRÓ INTERÉS | O24: MOSTRÓ INTERÉS | Q24: NO - VIRTUAL | R24: ADMITIDO | S24: VIRTUAL | T24: RINDIO VIRTUAL | U24: PENDIENTE TODO
B25: Samantha Alva | C25: 937799459 | D25: tatiana.salazar.canepa@gmail.com | G25: PSICOLOGIA | H25: PAUTA DIGITAL | I25: SURQUILLO | J25: 2025-II | K25: Open Day 1 | L25: Open Day 1 | N25: SE ENVIÓ INFORMACIÓN | O25: SE ENVIÓ INFORMACIÓN | P25: =TRIM(BD_PyaPinto[[#This Row],[CONTACTO II]]) -> SE ENVIÓ INFORMACIÓN
B26: Anjely | C26: 993229334 | D26: alberto_1177@hotmail.com | G26: PSICOLOGIA | H26: PAUTA DIGITAL | I26: SURQUILLO | J26: 2025-II | K26: Open Day 1 | L26: Open Day 1 | N26: MOSTRÓ INTERÉS | O26: MOSTRÓ INTERÉS | P26: =TRIM(BD_PyaPinto[[#This Row],[CONTACTO II]]) -> MOSTRÓ INTERÉS
B27: Akemi Inft | C27: 942972438 | D27: Rox1612.sorsan@gmal.com | G27: PSICOLOGIA | H27: PAUTA DIGITAL | I27: SURQUILLO | J27: 2025-II | K27: Open Day 1 | L27: Open Day 1 | N27: SE ENVIÓ INFORMACIÓN | O27: SE ENVIÓ INFORMACIÓN | P27: =TRIM(BD_PyaPinto[[#This Row],[CONTACTO II]]) -> SE ENVIÓ INFORMACIÓN
B28: Cristina Saavedra Huaman | C28: 971582144 | D28: vilchezpame29@gmail.com | G28: PSICOLOGIA | H28: PAUTA DIGITAL | I28: SURQUILLO | J28: 2025-II | K28: Open Day 1 | L28: Open Day 3 | N28: MOSTRÓ INTERÉS | O28: SI CONFIRMÓ PARA EL EVENTO | P28: SI CONFIRMÓ PARA EL EVENTO
B29: Dana | C29: 951133785 | D29: angescalpe@gmail.com | G29: PSICOLOGIA | H29: PAUTA DIGITAL | I29: SURQUILLO | J29: 2025-II | K29: Open Day 1 | L29: Open Day 1 | N29: NO CONTESTA | O29: NO CONTESTA | P29: =TRIM(BD_PyaPinto[[#This Row],[CONTACTO II]]) -> NO CONTESTA
B30: Anni Dariana Lazo Caceres | C30: 929159506 | D30: villanuevacastrodulce@gmail.com | G30: PSICOLOGIA | H30: PAUTA DIGITAL | I30: SURQUILLO | J30: 2025-II | K30: Open Day 1 | L30: Open Day 1 | N30: MOSTRÓ INTERÉS | O30: MOSTRÓ INTERÉS | P30: =TRIM(BD_PyaPinto[[#This Row],[CONTACTO II]]) -> MOSTRÓ INTERÉS
B31: Luis Andre Ruiz Icochea | C31: 984838423 | D31: rosa.marin.alcantara@hotmail.com | G31: PSICOLOGIA | H31: PAUTA DIGITAL | I31: SURQUILLO | J31: 2025-II | K31: Open Day 1 | L31: Open Day 1 | N31: SE ENVIÓ INFORMACIÓN | O31: SE ENVIÓ INFORMACIÓN | P31: =TRIM(BD_PyaPinto[[#This Row],[CONTACTO II]]) -> SE ENVIÓ INFORMACIÓN
B32: Yolanda Salinas Ramirez | C32: 987863691 | D32: emilycordovam15@gmail.com | G32: PSICOLOGIA | H32: PAUTA DIGITAL | I32: SURQUILLO | J32: 2025-II | K32: Open Day 1 | L32: Open Day 1 | N32: NO CONTESTA | O32: NO CONTESTA | P32: =TRIM(BD_PyaPinto[[#This Row],[CONTACTO II]]) -> NO CONTESTA
B33: Dash Rivera | C33: 945236476 | D33: sandrawongpe@gmail.com | G33: PSICOLOGIA | H33: PAUTA DIGITAL | I33: SURQUILLO | J33: 2025-II | K33: Open Day 1 | L33: Open Day 1 | N33: SE ENVIÓ INFORMACIÓN | O33: NO CONTESTA | P33: =TRIM(BD_PyaPinto[[#This Row],[CONTACTO II]]) -> NO CONTESTA
B34: Ashley | C34: 967574438 | D34: lruizicochea@gmail.com | G34: PSICOLOGIA | H34: PAUTA DIGITAL | I34: SURQUILLO | J34: 2025-II | K34: Open Day 1 | L34: Open Day 1 | N34: SE ENVIÓ INFORMACIÓN | O34: SE ENVIÓ INFORMACIÓN | P34: =TRIM(BD_PyaPinto[[#This Row],[CONTACTO II]]) -> SE ENVIÓ INFORMACIÓN
B35: Katherine Nicole Gomez Gago | C35: 982007153 | D35: msalinasramirez@hotmail.com | G35: PSICOLOGIA | H35: PAUTA DIGITAL | I35: SURQUILLO | J35: 2025-II | K35: Open Day 1 | L35: Open Day 1 | N35: MOSTRÓ INTERÉS | O35: MOSTRÓ INTERÉS | P35: =TRIM(BD_PyaPinto[[#This Row],[CONTACTO II]]) -> MOSTRÓ INTERÉS
B36: Ariana Aylas Tenorio | C36: 956251170 | D36: connietr31@gmail.com | G36: PSICOLOGIA | H36: PAUTA DIGITAL | I36: SURQUILLO | J36: 2025-II | K36: Open Day 1 | L36: Open Day 1 | N36: MOSTRÓ INTERÉS | O36: MOSTRÓ INTERÉS | P36: =TRIM(BD_PyaPinto[[#This Row],[CONTACTO II]]) -> MOSTRÓ INTERÉS
B37: Brunella | C37: 941064232 | D37: brune.scc@gmail.com | G37: PSICOLOGIA | H37: PAUTA DIGITAL | I37: SURQUILLO | J37: 2025-II | K37: Open Day 1 | L37: Open Day 1 | N37: SE ENVIÓ INFORMACIÓN | O37: NO CONTESTA | P37: =TRIM(BD_PyaPinto[[#This Row],[CONTACTO II]]) -> NO CONTESTA
A38: 42512860 | B38: Luciana Brissa Camiloaga Villanueva | C38: 933671229 | G38: PSICOLOGIA | H38: EVENTO PRESENCIAL | I38: SURQUILLO | J38: 2025-II | N38: MOSTRÓ INTERÉS | O38: MOSTRÓ INTERÉS | P38: =TRIM(BD_PyaPinto[[#This Row],[CONTACTO II]]) -> MOSTRÓ INTERÉS | Q38: NO - VIRTUAL | R38: ADMITIDO | S38: VIRTUAL | T38: RINDIO VIRTUAL | U38: PENDIENTE TODO
A39: 60919373 | B39: Fatima | C39: 993577915 | D39: ayelenur24@gmail.com | G39: COMUNICACIONES | H39: PAUTA DIGITAL | I39: SURQUILLO | J39: 2025-II | K39: Open Day 2 | L39: Open Day 2 | N39: SE ENVIÓ INFORMACIÓN | O39: NO CONTESTA | P39: =TRIM(BD_PyaPinto[[#This Row],[CONTACTO II]]) -> NO CONTESTA
A40: 7749489 | B40: Mayco Méndez Alva | C40: 51993324451 | D40: mmendezalva@gmail.com | G40: PSICOLOGIA | H40: PAUTA DIGITAL | I40: SURQUILLO | J40: 2025-II | K40: Taller Vivencial 2 | L40: Taller Vivencial 2 | N40: SE ENVIÓ INFORMACIÓN | O40: NO CONTESTA | P40: =TRIM(BD_PyaPinto[[#This Row],[CONTACTO II]]) -> NO CONTESTA
A41: 70958724 | B41: Aron Wiiliam Trinidad lengua | C41: 964498297 | D41: manchitas594@gmail.com | F41: ORDINARIO | G41: PSICOLOGIA | H41: COUNTER | I41: SURQUILLO | J41: 2025-II | N41: MOSTRÓ INTERÉS | O41: MOSTRÓ INTERÉS | P41: =TRIM(BD_PyaPinto[[#This Row],[CONTACTO II]]) -> MOSTRÓ INTERÉS | Q41: NO - VIRTUAL | R41: ADMITIDO | S41: VIRTUAL | T41: RINDIO VIRTUAL | U41: ENTREGADO-COMPLETO
A42: 72058016 | B42: Victor Samuel Mantilla Campos | C42: 975871906 | D42: samuel19234@outlook.com | F42: ORDINARIO | G42: COMUNICACIONES | H42: BASE ANTIGUA | I42: SURQUILLO | J42: 2025-II | N42: MOSTRÓ INTERÉS | O42: MOSTRÓ INTERÉS | P42: =TRIM(BD_PyaPinto[[#This Row],[CONTACTO II]]) -> MOSTRÓ INTERÉS | Q42: SI - EXAMEN PRESENCIAL | S42: PRESENCIAL | T42: RINDIO PRESENCIAL | U42: ENTREGADO-COMPLETO
A43: 72065920 | B43: Salvador Alejandro Buitrón García | C43: 971995426 | D43: salvadorbuitron67@gmail.com | F43: ORDINARIO | G43: TURISMO | H43: COUNTER | I43: SURQUILLO | J43: 2025-II | N43: MOSTRÓ INTERÉS | O43: MOSTRÓ INTERÉS | P43: =TRIM(BD_PyaPinto[[#This Row],[CONTACTO II]]) -> MOSTRÓ INTERÉS | Q43: NO - VIRTUAL | R43: ADMITIDO | S43: VIRTUAL | T43: RINDIO VIRTUAL | U43: ENTREGADO-COMPLETO
A44: 71169282 | B44: ARLETTE MARIEL RENGIFO CARRASCO | C44: 953501155 | D44: arletterengifocarrasco@gmail.com | F44: ORDINARIO | G44: PSICOLOGIA | H44: BASE ANTIGUA | I44: SURQUILLO | J44: 2025-II | N44: MOSTRÓ INTERÉS | O44: MOSTRÓ INTERÉS | P44: =TRIM(BD_PyaPinto[[#This Row],[CONTACTO II]]) -> MOSTRÓ INTERÉS | Q44: NO - VIRTUAL | R44: ADMITIDO | S44: VIRTUAL | T44: RINDIO VIRTUAL | U44: PENDIENTE TODO
A45: 71147576 | B45: NICOLLE JAZMIN CONDORI HERMOZA | C45: 928254878 | D45: vilmahermoza2020@gmail.com | F45: ORDINARIO | G45: TURISMO | H45: EVENTO PRESENCIAL | I45: SURQUILLO | J45: 2025-II | N45: MOSTRÓ INTERÉS | O45: MOSTRÓ INTERÉS | P45: =TRIM(BD_PyaPinto[[#This Row],[CONTACTO II]]) -> MOSTRÓ INTERÉS
A46: 61059294 | B46: Azul alban | C46: 964808999 | D46: azulalbanvera@gmail.com | F46: ORDINARIO | G46: PSICOLOGIA | H46: EVENTO PRESENCIAL | I46: SURQUILLO | J46: 2025-II | N46: MOSTRÓ INTERÉS | O46: NO CONTESTA | P46: NO CONTESTA
A47: 73370200 | B47: Solange Velarde | C47: 950274863 | D47: solangevelardepachas@gmail.com | F47: ORDINARIO | G47: PSICOLOGIA | H47: EVENTO PRESENCIAL | I47: SURQUILLO | J47: 2025-II | N47: MOSTRÓ INTERÉS | O47: MOSTRÓ INTERÉS | P47: =TRIM(BD_PyaPinto[[#This Row],[CONTACTO II]]) -> MOSTRÓ INTERÉS
A48: 76958880 | B48: Eddú Espada | C48: 977838494 | D48: yamirespada949@gmail.com | E48: 923 272 409 | F48: ORDINARIO | G48: PSICOLOGIA | H48: EVENTO PRESENCIAL | I48: SURQUILLO | J48: 2025-II | N48: MOSTRÓ INTERÉS | O48: MOSTRÓ INTERÉS | P48: MOSTRÓ INTERÉS
A49: 61235812 | B49: Veronica Tapia | C49: 979752657 | D49: vero.htapia1711@gmail.com | F49: ORDINARIO | G49: PSICOLOGIA | H49: EVENTO PRESENCIAL | I49: SURQUILLO | J49: 2025-II | N49: MOSTRÓ INTERÉS | O49: MOSTRÓ INTERÉS | P49: =TRIM(BD_PyaPinto[[#This Row],[CONTACTO II]]) -> MOSTRÓ INTERÉS
A50: 77658670 | B50: Flavia Alexandra Flores Llamoctanta | C50: 942244963 | D50: flaviaflores.1997@gmail.com | F50: ORDINARIO | G50: PSICOLOGIA | H50: EVENTO PRESENCIAL | I50: SURQUILLO | J50: 2025-II | N50: MOSTRÓ INTERÉS | O50: MOSTRÓ INTERÉS | P50: =TRIM(BD_PyaPinto[[#This Row],[CONTACTO II]]) -> MOSTRÓ INTERÉS
A51: 61249870 | B51: Rosa Espino (mama) | C51: 51983597435 | D51: rosaespino1512@gmail.com | F51: ORDINARIO | G51: TURISMO | H51: EVENTO PRESENCIAL | I51: SURQUILLO | J51: 2025-II | N51: MOSTRÓ INTERÉS | O51: SE ENVIÓ INFORMACIÓN | P51: SE ENVIÓ INFORMACIÓN
A52: 77094704 | B52: Andres Navarro (padre) | C52: 51908833132 | D52: andresnavarrosaenz@gmail.com | F52: ORDINARIO | G52: COMUNICACIONES | H52: EVENTO PRESENCIAL | I52: SURQUILLO | J52: 2025-II | N52: MOSTRÓ INTERÉS | O52: MOSTRÓ INTERÉS | P52: =TRIM(BD_PyaPinto[[#This Row],[CONTACTO II]]) -> MOSTRÓ INTERÉS
A53: 71676651 | B53: Sergio LV (padre) | C53: 51980489209 | D53: sergiolaime950@gmail.com | F53: ORDINARIO | G53: COMUNICACIONES | H53: EVENTO PRESENCIAL | I53: SURQUILLO | J53: 2025-II | N53: MOSTRÓ INTERÉS | O53: SE ENVIÓ INFORMACIÓN | P53: SE ENVIÓ INFORMACIÓN
A54: 76140140 | B54: Ariadna Cuya Allccahuaman | C54: 987058641 | D54: ariadnacuya.21@gmail.com | F54: ORDINARIO | G54: PSICOLOGIA | H54: EVENTO PRESENCIAL | I54: SURQUILLO | J54: 2025-II | N54: MOSTRÓ INTERÉS | O54: MOSTRÓ INTERÉS | P54: =TRIM(BD_PyaPinto[[#This Row],[CONTACTO II]]) -> MOSTRÓ INTERÉS
A55: 40282655 | B55: Verónica Fajardo | C55: 51910329961 | D55: fajardoveronicasally@gmail.com | F55: ORDINARIO | G55: PSICOLOGIA | H55: EVENTO PRESENCIAL | I55: SURQUILLO | J55: 2025-II | N55: MOSTRÓ INTERÉS | O55: MOSTRÓ INTERÉS | P55: =TRIM(BD_PyaPinto[[#This Row],[CONTACTO II]]) -> MOSTRÓ INTERÉS
A56: 74807462 | B56: Gia Suasnabar | C56: 934184083 | D56: gia_1506@hotmail.com | F56: ORDINARIO | G56: PSICOLOGIA | H56: EVENTO PRESENCIAL | I56: SURQUILLO | J56: 2025-II | N56: MOSTRÓ INTERÉS | O56: MOSTRÓ INTERÉS | P56: =TRIM(BD_PyaPinto[[#This Row],[CONTACTO II]]) -> MOSTRÓ INTERÉS
A57: 74566910 | B57: Elizabeth Huanaco huayhua | C57: 51989928993 | D57: adamelivillegashuanaco@gmail.com | F57: ORDINARIO | G57: PSICOLOGIA | H57: EVENTO PRESENCIAL | I57: SURQUILLO | J57: 2025-II | N57: MOSTRÓ INTERÉS | O57: SE ENVIÓ INFORMACIÓN | P57: SE ENVIÓ INFORMACIÓN
A58: 71673824 | B58: mayra Cabrera | C58: 51971904559 | D58: cabreraamayraa43@gmail.com | F58: ORDINARIO | G58: PSICOLOGIA | H58: EVENTO PRESENCIAL | I58: SURQUILLO | J58: 2025-II | N58: MOSTRÓ INTERÉS | O58: MOSTRÓ INTERÉS | P58: =TRIM(BD_PyaPinto[[#This Row],[CONTACTO II]]) -> MOSTRÓ INTERÉS
A59: 76374941 | B59: yamile guillen | C59: 921009660 | D59: yamileguillen793@gmail.com | F59: ORDINARIO | G59: PSICOLOGIA | H59: EVENTO PRESENCIAL | I59: SURQUILLO | J59: 2025-II | N59: MOSTRÓ INTERÉS | O59: MOSTRÓ INTERÉS | P59: =TRIM(BD_PyaPinto[[#This Row],[CONTACTO II]]) -> MOSTRÓ INTERÉS
A60: 70625513 | B60: Jos Huapaya | C60: 967323874 | D60: josehuapaya01@gmail.com | F60: ORDINARIO | G60: COMUNICACIONES | H60: EVENTO PRESENCIAL | I60: SURQUILLO | J60: 2025-II | N60: MOSTRÓ INTERÉS | O60: MOSTRÓ INTERÉS | P60: =TRIM(BD_PyaPinto[[#This Row],[CONTACTO II]]) -> MOSTRÓ INTERÉS
A61: 70634745 | B61: MEZA CUITO MIRIAN SUSAN | C61: 997462647 | D61: mirian.susana.2007@gmail.com | F61: TERCIO SUPERIOR | G61: PSICOLOGIA | H61: EVENTO PRESENCIAL | I61: SURQUILLO | J61: 2025-II | N61: MOSTRÓ INTERÉS | O61: MOSTRÓ INTERÉS | P61: MOSTRÓ INTERÉS | Q61: NO - VIRTUAL | R61: ADMITIDO | S61: VIRTUAL | T61: RINDIO VIRTUAL | U61: PENDIENTE TODO
A62: 32643987 | B62: Teodosia Salazar Huerta | C62: 995521779 | D62: teodosiasalazarhuerta@gmail.com | F62: ORDINARIO | G62: PSICOLOGIA | H62: EVENTO PRESENCIAL | I62: SURQUILLO | J62: 2025-II | N62: MOSTRÓ INTERÉS | O62: SE ENVIÓ INFORMACIÓN | P62: SE ENVIÓ INFORMACIÓN
A63: 71148895 | B63: Marcos Jesus | C63: 944396087 | D63: estradasantosmarcos968@gmail.com | F63: ORDINARIO | G63: COMUNICACIONES | H63: EVENTO PRESENCIAL | I63: SURQUILLO | J63: 2025-II | N63: MOSTRÓ INTERÉS | O63: MOSTRÓ INTERÉS | P63: =TRIM(BD_PyaPinto[[#This Row],[CONTACTO II]]) -> MOSTRÓ INTERÉS
A64: 45861161 | B64: Mhing Lhandy Sanchez Bazan | C64: 51908775094 | D64: lhanddy24@gmail.com | F64: ORDINARIO | G64: TURISMO | H64: EVENTO PRESENCIAL | I64: SURQUILLO | J64: 2025-II | N64: MOSTRÓ INTERÉS | O64: MOSTRÓ INTERÉS | P64: =TRIM(BD_PyaPinto[[#This Row],[CONTACTO II]]) -> MOSTRÓ INTERÉS
A65: 61133178 | B65: Linsayd Tapia | C65: 51916081040 | D65: linsaydmilagrostapiacuellar@gmail.com | F65: ORDINARIO | G65: TURISMO | H65: EVENTO PRESENCIAL | I65: SURQUILLO | J65: 2025-II | N65: MOSTRÓ INTERÉS | O65: MOSTRÓ INTERÉS | P65: =TRIM(BD_PyaPinto[[#This Row],[CONTACTO II]]) -> MOSTRÓ INTERÉS
A66: 76606619 | B66: Andy Bv | C66: 51995869753 | D66: andreabravot91@gmail.com | F66: ORDINARIO | G66: TURISMO | H66: EVENTO PRESENCIAL | I66: SURQUILLO | J66: 2025-II | N66: MOSTRÓ INTERÉS | O66: MOSTRÓ INTERÉS | P66: =TRIM(BD_PyaPinto[[#This Row],[CONTACTO II]]) -> MOSTRÓ INTERÉS
A67: 73496511 | B67: Xiomara Arroyo | C67: 51966104138 | D67: xiomiarroyo564@gmail.com | F67: ORDINARIO | G67: TURISMO | H67: EVENTO PRESENCIAL | I67: SURQUILLO | J67: 2025-II | N67: MOSTRÓ INTERÉS | O67: MOSTRÓ INTERÉS | P67: =TRIM(BD_PyaPinto[[#This Row],[CONTACTO II]]) -> MOSTRÓ INTERÉS
A68: 40698371 | B68: Santusa Quispe chullca | C68: 946634022 | D68: Sqch40@gmail.com | F68: ORDINARIO | G68: PSICOLOGIA | H68: EVENTO PRESENCIAL | I68: SURQUILLO | J68: 2025-II | N68: MOSTRÓ INTERÉS | O68: MOSTRÓ INTERÉS | P68: EVALUANDO OPCIONES
A69: 41439511 | B69: Guillermo Rivera Mayma | C69: 51999377150 | D69: griveramayma@gmail.com | F69: ORDINARIO | G69: TURISMO | H69: EVENTO PRESENCIAL | I69: SURQUILLO | J69: 2025-II | N69: MOSTRÓ INTERÉS | O69: SE ENVIÓ INFORMACIÓN | P69: SE ENVIÓ INFORMACIÓN
A70: 71062895 | B70: Mercedes Ushiñahua | C70: 51970087544 | D70: mercedesupiachihualopez@gmail.com | F70: ORDINARIO | G70: TURISMO | H70: EVENTO PRESENCIAL | I70: SURQUILLO | J70: 2025-II | N70: MOSTRÓ INTERÉS | O70: SE ENVIÓ INFORMACIÓN | P70: SE ENVIÓ INFORMACIÓN
A71: 62852406 | B71: Daniel Falconí Alzamora | C71: 983697523 | D71: cdaniel.falconi@outlook.com | F71: ORDINARIO | G71: COMUNICACIONES | H71: EVENTO PRESENCIAL | I71: SURQUILLO | J71: 2025-II | N71: MOSTRÓ INTERÉS | O71: MOSTRÓ INTERÉS | P71: =TRIM(BD_PyaPinto[[#This Row],[CONTACTO II]]) -> MOSTRÓ INTERÉS
A72: 10104243 | B72: Esther Malpartida (padre) | C72: 993649338 | D72: esthermalpartida6@gmail.com | F72: ORDINARIO | G72: PSICOLOGIA | H72: EVENTO PRESENCIAL | I72: SURQUILLO | J72: 2025-II | N72: MOSTRÓ INTERÉS | O72: MOSTRÓ INTERÉS | P72: =TRIM(BD_PyaPinto[[#This Row],[CONTACTO II]]) -> MOSTRÓ INTERÉS
A73: 6098938 | B73: Betty Angelino jaramillo | C73: 964915779 | D73: betty_aj@outlook.es | F73: ORDINARIO | G73: PSICOLOGIA | H73: EVENTO PRESENCIAL | I73: SURQUILLO | J73: 2025-II | N73: MOSTRÓ INTERÉS | O73: MOSTRÓ INTERÉS | P73: =TRIM(BD_PyaPinto[[#This Row],[CONTACTO II]]) -> MOSTRÓ INTERÉS
B74: Kira | C74: 984641228 | D74: Kiralinagoyzueta@gmail.com | G74: COMUNICACIONES | H74: PAUTA DIGITAL | I74: SURQUILLO | J74: 2025-II | K74: Taller Vivencial 3 | L74: Taller Vivencial 3 | N74: SE ENVIÓ INFORMACIÓN | O74: SE ENVIÓ INFORMACIÓN
B75: luluciana | C75: 51964579855 | D75: lucianadelgadokler@gmail.com | G75: COMUNICACIONES | H75: PAUTA DIGITAL | I75: SURQUILLO | J75: 2025-II | K75: Open Day 1 | L75: Open Day 1 | N75: SE ENVIÓ INFORMACIÓN | O75: SE ENVIÓ INFORMACIÓN | P75: =TRIM(BD_PyaPinto[[#This Row],[CONTACTO II]]) -> SE ENVIÓ INFORMACIÓN
B76: Zakiriit Zakiriit | C76: 51946118548 | D76: zakiravalenzuela2008@gmail.com | G76: COMUNICACIONES | H76: PAUTA DIGITAL | I76: SURQUILLO | J76: 2025-II | K76: Open Day 1 | L76: Open Day 1 | N76: MOSTRÓ INTERÉS | O76: MOSTRÓ INTERÉS | P76: =TRIM(BD_PyaPinto[[#This Row],[CONTACTO II]]) -> MOSTRÓ INTERÉS
B77: Jennifer Carey | C77: 51984440016 | D77: careyjennifer882@gmail.com | G77: COMUNICACIONES | H77: PAUTA DIGITAL | I77: SURQUILLO | J77: 2025-II | K77: Open Day 1 | L77: Open Day 1 | N77: SE ENVIÓ INFORMACIÓN | O77: NO CONTESTA | P77: =TRIM(BD_PyaPinto[[#This Row],[CONTACTO II]]) -> NO CONTESTA
B78: Nayee | C78: 51923573347 | D78: nayeliqqhh@gmail.com | G78: COMUNICACIONES | H78: PAUTA DIGITAL | I78: SURQUILLO | J78: 2025-II | K78: Open Day 1 | L78: Open Day 1 | N78: SE ENVIÓ INFORMACIÓN | O78: NO CONTESTA | P78: =TRIM(BD_PyaPinto[[#This Row],[CONTACTO II]]) -> NO CONTESTA
B79: Cintia Bravo | C79: 51985934651 | D79: mia_88445@hotmail.com | G79: COMUNICACIONES | H79: PAUTA DIGITAL | I79: SURQUILLO | J79: 2025-II | K79: Open Day 1 | L79: Open Day 1 | N79: SE ENVIÓ INFORMACIÓN | O79: NO CONTESTA | P79: =TRIM(BD_PyaPinto[[#This Row],[CONTACTO II]]) -> NO CONTESTA
B80: Angelina Casias Zamalloa | C80: 51977250157 | D80: angelinacasias0@gmail.com | G80: COMUNICACIONES | H80: PAUTA DIGITAL | I80: SURQUILLO | J80: 2025-II | K80: Open Day 1 | L80: Open Day 1 | N80: SE ENVIÓ INFORMACIÓN | O80: NO CONTESTA | P80: =TRIM(BD_PyaPinto[[#This Row],[CONTACTO II]]) -> NO CONTESTA
B81: Manuel Figueroa | C81: 921308138 | D81: manuelescorpio10@gmail.com | G81: COMUNICACIONES | H81: PAUTA DIGITAL | I81: SURQUILLO | J81: 2025-II | K81: Open Day 1 | L81: Open Day 1 | N81: SE ENVIÓ INFORMACIÓN | O81: NO CONTESTA | P81: =TRIM(BD_PyaPinto[[#This Row],[CONTACTO II]]) -> NO CONTESTA
B82: Sharon Carbonero | C82: 949101442 | D82: sharon_carbonero@hotmail.com | G82: COMUNICACIONES | H82: PAUTA DIGITAL | I82: SURQUILLO | J82: 2025-II | K82: Open Day 1 | L82: Open Day 1 | N82: SE ENVIÓ INFORMACIÓN | O82: NO CONTESTA | P82: =TRIM(BD_PyaPinto[[#This Row],[CONTACTO II]]) -> NO CONTESTA
B83: María De Fátima Flores | C83: 935443914 | D83: mariadefatimafloresrayo@gmail.com | G83: COMUNICACIONES | H83: PAUTA DIGITAL | I83: SURQUILLO | J83: 2025-II | K83: Open Day 1 | L83: Open Day 1 | N83: SE ENVIÓ INFORMACIÓN | O83: NO CONTESTA | P83: =TRIM(BD_PyaPinto[[#This Row],[CONTACTO II]]) -> NO CONTESTA
B84: Johana Mariel Buleje Aguirre | C84: 914635022 | D84: johabuleje24@gmail.com | G84: COMUNICACIONES | H84: PAUTA DIGITAL | I84: SURQUILLO | J84: 2025-II | K84: Open Day 1 | L84: Open Day 1 | N84: SE ENVIÓ INFORMACIÓN | O84: NO CONTESTA | P84: =TRIM(BD_PyaPinto[[#This Row],[CONTACTO II]]) -> NO CONTESTA
B85: Erika Angelina Zuñiga Gómez | C85: 903153038 | D85: angelinazunigagomez@gmail.com | G85: COMUNICACIONES | H85: PAUTA DIGITAL | I85: SURQUILLO | J85: 2025-II | K85: Open Day 1 | L85: Open Day 1 | N85: SE ENVIÓ INFORMACIÓN | O85: NO CONTESTA | P85: =TRIM(BD_PyaPinto[[#This Row],[CONTACTO II]]) -> NO CONTESTA
A86: 71674645 | B86: Dayana Leano | C86: 950778919 | D86: dayanaleano0@gmail.com | G86: COMUNICACIONES | H86: PAUTA DIGITAL | I86: SURQUILLO | J86: 2025-II | K86: Open Day 1 | L86: Open Day 1 | N86: MOSTRÓ INTERÉS | O86: MOSTRÓ INTERÉS | P86: =TRIM(BD_PyaPinto[[#This Row],[CONTACTO II]]) -> MOSTRÓ INTERÉS
B87: Rossy Avalos | C87: 993462191 | D87: 0calidasoleda0@gmail.com | G87: COMUNICACIONES | H87: PAUTA DIGITAL | I87: SURQUILLO | J87: 2025-II | K87: Open Day 1 | L87: Open Day 1 | N87: NO CONTESTA | O87: NO CONTESTA | P87: =TRIM(BD_PyaPinto[[#This Row],[CONTACTO II]]) -> NO CONTESTA
B88: Nick Rozas Alvarez | C88: 914799404 | D88: nicktvparaelmundo2019@gmail.com | G88: PSICOLOGIA | H88: BASE ANTIGUA | I88: SURQUILLO | J88: 2025-II | N88: SE ENVIÓ INFORMACIÓN | O88: SE ENVIÓ INFORMACIÓN | P88: =TRIM(BD_PyaPinto[[#This Row],[CONTACTO II]]) -> SE ENVIÓ INFORMACIÓN
B89: Nick | C89: 997656653 | D89: nicki023xd@gmail.com | G89: PSICOLOGIA | H89: PAUTA DIGITAL | I89: SURQUILLO | J89: 2025-II | K89: Open Day 1 | L89: Open Day 1 | N89: SE ENVIÓ INFORMACIÓN | O89: SE ENVIÓ INFORMACIÓN | P89: =TRIM(BD_PyaPinto[[#This Row],[CONTACTO II]]) -> SE ENVIÓ INFORMACIÓN
B90: Sebs Zegarra | C90: 51936896456 | D90: sebitas.2106@hotmail.com | G90: PSICOLOGIA | H90: PAUTA DIGITAL | I90: SURQUILLO | J90: 2025-II | K90: Open Day 1 | L90: Open Day 1 | N90: SE ENVIÓ INFORMACIÓN | O90: SE ENVIÓ INFORMACIÓN | P90: =TRIM(BD_PyaPinto[[#This Row],[CONTACTO II]]) -> SE ENVIÓ INFORMACIÓN
B91: Evelyn Carbonel | C91: 51945140830 | D91: evicad1038@gmail.com | G91: PSICOLOGIA | H91: PAUTA DIGITAL | I91: SURQUILLO | J91: 2025-II | K91: Open Day 1 | L91: Open Day 1 | N91: SE ENVIÓ INFORMACIÓN | O91: SE ENVIÓ INFORMACIÓN | P91: =TRIM(BD_PyaPinto[[#This Row],[CONTACTO II]]) -> SE ENVIÓ INFORMACIÓN
A92: 7494582 | B92: laura angeica huamani tito | C92: 941122845 | D92: tjcarmen74@hotmail.com | G92: PSICOLOGIA | H92: PAUTA DIGITAL | I92: SURQUILLO | J92: 2025-II | K92: Open Day 1 | L92: Open Day 1 | N92: SE ENVIÓ INFORMACIÓN | O92: NO CONTESTA | P92: =TRIM(BD_PyaPinto[[#This Row],[CONTACTO II]]) -> NO CONTESTA
B93: kiarA | C93: 997669452 | D93: ramoskiaraaec@gmail.com | G93: PSICOLOGIA | H93: PAUTA DIGITAL | I93: SURQUILLO | J93: 2025-II | K93: Open Day 1 | L93: Open Day 1 | N93: SE ENVIÓ INFORMACIÓN | O93: NO CONTESTA | P93: =TRIM(BD_PyaPinto[[#This Row],[CONTACTO II]]) -> NO CONTESTA
A94: 61137263 | B94: Dharma Gallo | C94: 922717973 | D94: dharmagallo02@gmail.com | G94: PSICOLOGIA | H94: PAUTA DIGITAL | I94: SURQUILLO | J94: 2025-II | K94: Open Day 1 | L94: Open Day 1 | N94: SE ENVIÓ INFORMACIÓN | O94: NO CONTESTA | P94: =TRIM(BD_PyaPinto[[#This Row],[CONTACTO II]]) -> NO CONTESTA
A95: 72549480 | B95: Isabel Espinoza | C95: 991489825 | D95: norlyninocente688@gmail.com | G95: PSICOLOGIA | H95: PAUTA DIGITAL | I95: SURQUILLO | J95: 2025-II | K95: Open Day 1 | L95: Open Day 1 | N95: SE ENVIÓ INFORMACIÓN | O95: SE ENVIÓ INFORMACIÓN | P95: =TRIM(BD_PyaPinto[[#This Row],[CONTACTO II]]) -> SE ENVIÓ INFORMACIÓN
B96: lisbeth Andrade | C96: 994877319 | D96: lisbethandrade85@gmail.com | G96: PSICOLOGIA | H96: PAUTA DIGITAL | I96: SURQUILLO | J96: 2025-II | K96: Open Day 1 | L96: Open Day 1 | N96: SE ENVIÓ INFORMACIÓN | O96: NO CONTESTA | P96: =TRIM(BD_PyaPinto[[#This Row],[CONTACTO II]]) -> NO CONTESTA
B97: Daniela | C97: 913205310 | D97: danielaalysontimoteomaquera@gmail.com | G97: PSICOLOGIA | H97: PAUTA DIGITAL | I97: SURQUILLO | J97: 2025-II | K97: Open Day 1 | L97: Open Day 1 | N97: SE ENVIÓ INFORMACIÓN | O97: NO CONTESTA | P97: =TRIM(BD_PyaPinto[[#This Row],[CONTACTO II]]) -> NO CONTESTA
B98: Camila Altamirano | C98: 985040891 | D98: kiaracamilaaltamiranosaune@gmail.com | G98: PSICOLOGIA | H98: PAUTA DIGITAL | I98: SURQUILLO | J98: 2025-II | K98: Open Day 1 | L98: Open Day 1 | N98: SE ENVIÓ INFORMACIÓN | O98: NO CONTESTA | P98: =TRIM(BD_PyaPinto[[#This Row],[CONTACTO II]]) -> NO CONTESTA
B99: Joaquin Paitan | C99: 972740041 | D99: joaezpa18@gmail.com | G99: PSICOLOGIA | H99: PAUTA DIGITAL | I99: SURQUILLO | J99: 2025-II | K99: Open Day 1 | L99: Open Day 1 | N99: SE ENVIÓ INFORMACIÓN | O99: NO CONTESTA | P99: =TRIM(BD_PyaPinto[[#This Row],[CONTACTO II]]) -> NO CONTESTA
B100: Gisella Diaz | C100: 998277221 | D100: giselladiazleon@gmail.com | E100: Buen Pastros Los Olivos | G100: PSICOLOGIA | H100: PAUTA DIGITAL | I100: SURQUILLO | J100: 2025-II | K100: Open Day 1 | L100: Open Day 1 | N100: SE ENVIÓ INFORMACIÓN | O100: NO CONTESTA | P100: SE ENVIÓ INFORMACIÓN
...

Sheet BD|Melisa A.
A1: DNI | B1: NOMBRES | C1: CELULAR | D1: CORREO | E1: COLEGIO DE PROCEDENCIA | F1: MODALIDAD | G1: ESCUELA | H1: ORIGEN | I1: SEDE | J1: SEMESTRE | K1: CAMPAÑA | L1: EVENTO | M1: FECHA DE INGRESO DE LEAD | N1: CONTACTO I | O1: CONTACTO II | P1: CONTACTO III | Q1: ¿PAGÓ DERECHO DE INSCRIPCIÓN? | R1: STATUS ACADÉMICO | S1: TIPO DE EXAMEN | T1: STATUS DE EXAMEN | U1: ENTREGA DE DOCUMENTOS | V1: OBSERVACION
B2: Azumy Aleshka Melany Ramos Castro | C2: 966479008 | D2: sandyrodo@gmail.com | G2: COMUNICACIONES | H2: PAUTA DIGITAL | I2: SURQUILLO | J2: 2025-II | N2: SE ENVIÓ INFORMACIÓN | O2: NO CONTESTA | P2: MOSTRÓ INTERÉS | S2: VIRTUAL | T2: RINDIO VIRTUAL | U2: ENTREGADO-COMPLETO
A3: 60973530 | B3: MACCIEL SOIREMA CHAVEZ ESTIBUR | C3: 963 333 412 | D3: macciellestibur28@gmail.com | F3: ORDINARIO | G3: COMUNICACIONES | H3: BASE ANTIGUA | I3: SURQUILLO | J3: 2025-II | K3: Open Day 3 | L3: Open Day 3 | N3: SE ENVIÓ INFORMACIÓN | O3: SI CONFIRMÓ PARA EL EVENTO | P3: SI CONFIRMÓ PARA EL EVENTO | Q3: NO- VIRTUAL | R3: ADMITIDO | S3: VIRTUAL | T3: RINDIO VIRTUAL | U3: ENTREGADO-COMPLETO
A4: 72595939 | B4: Nicolás Adriano Carrillo Castillo | C4: 956693526 | D4: kari19_05@hotmail.com | G4: COMUNICACIONES | H4: PAUTA DIGITAL | I4: SURQUILLO | J4: 2025-II | N4: SE ENVIÓ INFORMACIÓN | O4: MOSTRÓ INTERÉS | P4: MOSTRÓ INTERÉS
A5: 10119327 | B5: Giovanna MedaliYazu | C5: 51980769656 | D5: giovannahuamanchay@gmail.com | G5: COMUNICACIONES | H5: PAUTA DIGITAL | I5: SURQUILLO | J5: 2025-II | N5: SE ENVIÓ INFORMACIÓN | O5: NO CONTESTA | P5: NO CONTESTA
A6: 9877154 | B6: Janeth Huapaya | C6: 51999343475 | D6: Janyht_74@hotmail.com | G6: COMUNICACIONES | H6: PAUTA DIGITAL | I6: SURQUILLO | J6: 2025-II | N6: SE ENVIÓ INFORMACIÓN | O6: NO CONTESTA | P6: NO CONTESTA
A7: 60797702 | B7: Daniel Alcides Quispe Ataqui | C7: 992 513 409 | D7: Cremitadaniel@gmail.com | F7: ORDINARIO | G7: COMUNICACIONES | H7: BASE ANTIGUA | I7: SURQUILLO | J7: 2025-II | N7: MOSTRÓ INTERÉS | O7: MOSTRÓ INTERÉS | P7: MOSTRÓ INTERÉS | Q7: NO- VIRTUAL | R7: ADMITIDO | S7: VIRTUAL | T7: RINDIO VIRTUAL | U7: ENTREGADO-COMPLETO
A8: 42389216 | B8: niebve | C8: 51970735881 | D8: adriantomasto20@gmail.com | G8: COMUNICACIONES | H8: PAUTA DIGITAL | I8: SURQUILLO | J8: 2025-II | N8: SE ENVIÓ INFORMACIÓN | O8: MOSTRÓ INTERÉS | P8: MOSTRÓ INTERÉS
A9: 73280352 | B9: Andy Subilete ramos | C9: +51 939 944 297 | D9: tanianicolsubilete@gmail.com | G9: COMUNICACIONES | H9: PAUTA DIGITAL | I9: SURQUILLO | J9: 2025-II | N9: SE ENVIÓ INFORMACIÓN | O9: MOSTRÓ INTERÉS | P9: MOSTRÓ INTERÉS
A10: 45373198 | B10: Jose Daniel Vergara | C10: 51983604664 | D10: danver.talent.88@gmail.com | G10: COMUNICACIONES | H10: PAUTA DIGITAL | I10: SURQUILLO | J10: 2025-II | N10: SE ENVIÓ INFORMACIÓN | O10: MOSTRÓ INTERÉS | P10: NO CONTESTA
A11: 61214259 | B11: Xiomara Minaya | C11: +51 914 811 977 | D11: minayaxiomara52@gmail.com | G11: COMUNICACIONES | H11: PAUTA DIGITAL | I11: SURQUILLO | J11: 2025-II | N11: SE ENVIÓ INFORMACIÓN | O11: MOSTRÓ INTERÉS | P11: NO CONTESTA
A12: 60810207 | B12: Rodrigo Aarón Pereira Soto | C12: 903160230 | G12: COMUNICACIONES | H12: COUNTER | I12: SURQUILLO | J12: 2025-II | N12: SE ENVIÓ INFORMACIÓN | O12: MOSTRÓ INTERÉS | P12: MOSTRÓ INTERÉS
A13: 61291439 | B13: LA BARRERA ROMERO MARK ANDREW | C13: +51 910 329 954 | G13: COMUNICACIONES | H13: COUNTER | I13: SURQUILLO | J13: 2025-II | N13: SE ENVIÓ INFORMACIÓN | O13: MOSTRÓ INTERÉS | P13: MOSTRÓ INTERÉS | Q13: NO- VIRTUAL | R13: ADMITIDO | S13: VIRTUAL | T13: RENDIRÁ VIRTUAL | U13: PENDIENTE TODO
A14: :61291439 | B14: Mark Andrew La Barrera Romero | C14: +51 910 329 954 | D14: marklabarreraromero@gmail.com | G14: COMUNICACIONES | H14: COUNTER | I14: SURQUILLO | J14: 2025-II | N14: SE ENVIÓ INFORMACIÓN | O14: MOSTRÓ INTERÉS | P14: MOSTRÓ INTERÉS | Q14: NO- VIRTUAL | R14: ADMITIDO | S14: VIRTUAL | T14: RENDIRÁ VIRTUAL | U14: PENDIENTE TODO
A15: 71174516 | B15: Andrea Leon Requelme | C15: +51 989 345 213 | G15: COMUNICACIONES | H15: COUNTER | I15: SURQUILLO | J15: 2025-II | N15: SE ENVIÓ INFORMACIÓN | O15: MOSTRÓ INTERÉS | P15: MOSTRÓ INTERÉS | Q15: NO- VIRTUAL | R15: ADMITIDO | S15: VIRTUAL | T15: RENDIRÁ VIRTUAL | U15: PENDIENTE TODO
A16: 61188538 | B16: Ariela Sumie Tokuno Sota | C16: +51 957 296 870 | D16: arielasumie@gmail.com | G16: COMUNICACIONES | H16: COUNTER | I16: SURQUILLO | J16: 2025-II | N16: SE ENVIÓ INFORMACIÓN | O16: MOSTRÓ INTERÉS | P16: MOSTRÓ INTERÉS | Q16: NO- VIRTUAL | R16: ADMITIDO | S16: VIRTUAL | T16: RINDIO VIRTUAL | U16: ENTREGADO-COMPLETO | V16: YA PAGO MATRICULA
A17: 61454758 | B17: 𝒜𝓃𝒶𝓂𝓎𝓁𝑒𝑒 | C17: 51929543197 | D17: anamiledaleshka@gmail.com | G17: COMUNICACIONES | H17: PAUTA DIGITAL | I17: SURQUILLO | J17: 2025-II | N17: SE ENVIÓ INFORMACIÓN | O17: NO CONTESTA | P17: NO CONTESTA
B18: Giuliano Salazar Torres | C18: 985645048 | D18: GIULIANOSALAZARTORRES@GMAIL.COM | G18: COMUNICACIONES | H18: PAUTA DIGITAL | I18: SURQUILLO | J18: 2025-II | N18: MOSTRÓ INTERÉS | O18: MOSTRÓ INTERÉS | P18: MOSTRÓ INTERÉS
B19: Yadhira Celestino | C19: 953800626 | D19: yadhiraxiomaracelestinogalvez@gmail.com | G19: COMUNICACIONES | H19: PAUTA DIGITAL | I19: SURQUILLO | J19: 2025-II | N19: NO CONTESTA | O19: NO CONTESTA | P19: INCONTACTABLE
B20: Andersson Rubén Quiquijana Salas | C20: 936479486 | D20: fcondori.es@gmail.com | G20: COMUNICACIONES | H20: PAUTA DIGITAL | I20: SURQUILLO | J20: 2025-II | N20: SE ENVIÓ INFORMACIÓN | O20: MOSTRÓ INTERÉS | P20: MOSTRÓ INTERÉS
B21: Alejandro Romero Chu | C21: 902280258 | D21: aberrocal@lnjfg.edu.pe | G21: COMUNICACIONES | H21: PAUTA DIGITAL | I21: SURQUILLO | J21: 2025-II | N21: SE ENVIÓ INFORMACIÓN | O21: MOSTRÓ INTERÉS | P21: MOSTRÓ INTERÉS
B22: Alessandro Braga | C22: 975458726 | D22: lu.vilcg@gmail.com | G22: COMUNICACIONES | H22: PAUTA DIGITAL | I22: SURQUILLO | J22: 2025-II | N22: NO CONTESTA | O22: NO CONTESTA | P22: NO CONTESTA
B23: Bianca Bulic Castillo | C23: 956364110 | D23: ale_virgo596@hotmail.com | G23: COMUNICACIONES | H23: PAUTA DIGITAL | I23: SURQUILLO | J23: 2025-II | N23: NO CONTESTA | O23: NO CONTESTA | P23: NO CONTESTA
B24: Natalia Massiel Gibaja Valle | C24: 934036246 | D24: samirsajs09@gmail.com | G24: COMUNICACIONES | H24: PAUTA DIGITAL | I24: SURQUILLO | J24: 2025-II | N24: SE ENVIÓ INFORMACIÓN | O24: NO CONTESTA | P24: NO CONTESTA
B25: Ericka Mejia Malafaya | C25: 980 199 733 | G25: COMUNICACIONES | H25: PAUTA DIGITAL | I25: SURQUILLO | J25: 2025-II | N25: SE ENVIÓ INFORMACIÓN | O25: NO CONTESTA | P25: NO CONTESTA
B26: Jennifer La Rosa Díaz | C26: 936236347 | D26: arazielvallejo@gmail.com | G26: COMUNICACIONES | H26: PAUTA DIGITAL | I26: SURQUILLO | J26: 2025-II | N26: SE ENVIÓ INFORMACIÓN | O26: NO CONTESTA | P26: NO CONTESTA
B27: Dayraa | C27: 986763600 | D27: digseba345@gmail.com | G27: COMUNICACIONES | H27: PAUTA DIGITAL | I27: SURQUILLO | J27: 2025-II | N27: NO CONTESTA | O27: NO CONTESTA | P27: NO CONTESTA
B28: Adrina Gutierrez | C28: 920652445 | D28: fabianapr1029@gmail.com | G28: COMUNICACIONES | H28: PAUTA DIGITAL | I28: SURQUILLO | J28: 2025-II | N28: NO CONTESTA | O28: NO CONTESTA | P28: NO CONTESTA
A29: 61334034 | B29: NAYARA NAOMI TACZA HUANCA | C29: 941327543 | D29: NAYARANAOMI880@GMAIL.COM | F29: ORDINARIO | G29: COMUNICACIONES | H29: BASE ANTIGUA | I29: SURQUILLO | J29: 2025-II | N29: MOSTRÓ INTERÉS | O29: MOSTRÓ INTERÉS | P29: MOSTRÓ INTERÉS | Q29: NO- VIRTUAL | R29: ADMITIDO | S29: VIRTUAL | T29: RINDIO VIRTUAL | U29: PENDIENTE TODO
A30: 40030211 | B30: Giannina Grados | C30: 51991405952 | D30: gianninagrados@gmail.com | G30: COMUNICACIONES | H30: PAUTA DIGITAL | I30: SURQUILLO | J30: 2025-II | N30: SE ENVIÓ INFORMACIÓN | O30: NO CONTESTA | P30: NO CONTESTA
A31: 75218160 | B31: RENZO SEBASTIAN QQUELLCA LOPEZ | C31: +51 933 748 465 | D31: renzosebastianql@gmail.com | F31: ORDINARIO | G31: COMUNICACIONES | H31: COUNTER | I31: SURQUILLO | J31: 2025-II | N31: MOSTRÓ INTERÉS | O31: MOSTRÓ INTERÉS | P31: MOSTRÓ INTERÉS | Q31: NO- VIRTUAL | R31: ADMITIDO | S31: VIRTUAL | T31: RINDIO VIRTUAL | U31: ENTREGADO-COMPLETO
A32: 60919416 | B32: Santiago Andre Piñas Zumaran | C32: 940266511 | D32: sanpizum13@gmail.com | F32: ORDINARIO | G32: PSICOLOGIA | H32: COUNTER | I32: SURQUILLO | J32: 2025-II | K32: Open Day 3 | L32: Open Day 3 | N32: SE ENVIÓ INFORMACIÓN | O32: SI CONFIRMÓ PARA EL EVENTO | P32: SI CONFIRMÓ PARA EL EVENTO | Q32: NO- VIRTUAL | R32: ADMITIDO | S32: VIRTUAL | T32: RINDIO VIRTUAL | U32: ENTREGADO-COMPLETO
A33: 77807888 | B33: Joseph Díaz Aquino | C33: 971422 058 | D33: josephdiazaquino152@gmail.com | F33: ORDINARIO | G33: COMUNICACIONES | H33: BASE ANTIGUA | I33: SURQUILLO | J33: 2025-II | N33: MOSTRÓ INTERÉS | O33: MOSTRÓ INTERÉS | P33: MOSTRÓ INTERÉS | Q33: NO- VIRTUAL | R33: ADMITIDO | S33: VIRTUAL | T33: RINDIO VIRTUAL | U33: PENDIENTE TODO
A34: 60737299 | B34: Priscila Rosa Ester Avila Rojas | C34: 941140732 | D34: primix0206@gmail.com | F34: ORDINARIO | G34: COMUNICACIONES | H34: BASE ANTIGUA | I34: SURQUILLO | J34: 2025-II | N34: MOSTRÓ INTERÉS | O34: MOSTRÓ INTERÉS | P34: MOSTRÓ INTERÉS | Q34: NO- VIRTUAL | R34: ADMITIDO | S34: VIRTUAL | T34: RINDIO VIRTUAL | U34: ENTREGADO-COMPLETO
A35: 70638960 | B35: Maryorit Alison Vanesa Tutaya linares | C35: 915177778 | D35: maryori.tutaya06@gmail.com | F35: ORDINARIO | G35: TURISMO | H35: BASE ANTIGUA | I35: SURQUILLO | J35: 2025-II | N35: MOSTRÓ INTERÉS | O35: MOSTRÓ INTERÉS | P35: MOSTRÓ INTERÉS | Q35: NO- VIRTUAL | R35: ADMITIDO | S35: VIRTUAL | T35: RINDIO VIRTUAL | U35: PENDIENTE TODO
A36: 70726548 | B36: Danna Patricia Carranza Mesias | C36: 912454673 | D36: danna.carranza1508@gmail.com | F36: ORDINARIO | G36: PSICOLOGIA | H36: BASE ANTIGUA | I36: SURQUILLO | J36: 2025-II | N36: MOSTRÓ INTERÉS | O36: MOSTRÓ INTERÉS | P36: MOSTRÓ INTERÉS | Q36: NO- VIRTUAL | R36: ADMITIDO | S36: VIRTUAL | T36: RINDIO VIRTUAL | U36: PENDIENTE TODO
A37: 71144913 | B37: Romina Flores Medina | C37: 994836 815 | D37: ROMIFLOWERS5@GMAIL.COM | F37: ORDINARIO | G37: COMUNICACIONES | H37: BASE ANTIGUA | I37: SURQUILLO | J37: 2025-II | N37: MOSTRÓ INTERÉS | O37: MOSTRÓ INTERÉS | P37: MOSTRÓ INTERÉS | Q37: NO- VIRTUAL | R37: ADMITIDO | S37: VIRTUAL | T37: RINDIO VIRTUAL | U37: PENDIENTE TODO
A38: 72896294 | B38: Carlos Victor Aaron Tejada Beas | C38: 923 504 852 | D38: aarontejadabeas@gmail.com | F38: ORDINARIO | G38: PSICOLOGIA | H38: BASE ANTIGUA | I38: SURQUILLO | J38: 2025-II | N38: MOSTRÓ INTERÉS | O38: MOSTRÓ INTERÉS | P38: MOSTRÓ INTERÉS | Q38: NO- VIRTUAL | R38: ADMITIDO | S38: VIRTUAL | T38: RINDIO VIRTUAL | U38: PENDIENTE TODO
A39: 71145273 | B39: Flor de Maria Pacheco Patiño | C39: 999365741 | D39: avierorlando15@hotmail.com | F39: ORDINARIO | G39: COMUNICACIONES | H39: BASE ANTIGUA | I39: SURQUILLO | J39: 2025-II | N39: MOSTRÓ INTERÉS | O39: MOSTRÓ INTERÉS | P39: MOSTRÓ INTERÉS | Q39: NO- VIRTUAL | R39: ADMITIDO | S39: VIRTUAL | T39: RINDIO VIRTUAL | U39: PENDIENTE TODO
A40: 62051295 | B40: Sergio Roy Chi Garro | C40: 944331736 | D40: faser2708@gmail.com | F40: ORDINARIO | G40: COMUNICACIONES | H40: BASE ANTIGUA | I40: SURQUILLO | J40: 2025-II | N40: MOSTRÓ INTERÉS | O40: MOSTRÓ INTERÉS | P40: MOSTRÓ INTERÉS | Q40: NO- VIRTUAL | R40: ADMITIDO | S40: VIRTUAL | T40: RINDIO VIRTUAL | U40: ENTREGADO-COMPLETO
A41: 70631854 | B41: Jimena Rocio Villagomez Hernandez | C41: 900171670 | D41: jv64646@gmail.com | F41: ORDINARIO | G41: TURISMO | H41: BASE ANTIGUA | I41: SURQUILLO | J41: 2025-II | N41: MOSTRÓ INTERÉS | O41: MOSTRÓ INTERÉS | P41: MOSTRÓ INTERÉS | Q41: NO- VIRTUAL | R41: ADMITIDO | S41: VIRTUAL | T41: RINDIO VIRTUAL | U41: ENTREGADO-COMPLETO
A42: 72571801 | B42: YESENIA ALEXANDRA LOPEZ HINOSTROZA | C42: 913387682 | D42: YESUGOI12@GMAIL.COM | F42: ORDINARIO | G42: PSICOLOGIA | H42: BASE ANTIGUA | I42: SURQUILLO | J42: 2025-II | N42: MOSTRÓ INTERÉS | O42: MOSTRÓ INTERÉS | P42: MOSTRÓ INTERÉS | Q42: NO- VIRTUAL | R42: ADMITIDO | S42: VIRTUAL | T42: RENDIRÁ VIRTUAL | U42: PENDIENTE TODO
A43: 71686899 | B43: Luz Angelica Cadillo Sanchez | C43: 900585172 | D43: luzangelicacadillosanchez70@gmail.com | F43: ORDINARIO | G43: PSICOLOGIA | H43: BASE ANTIGUA | I43: COMAS | J43: 2025-II | N43: SE ENVIÓ INFORMACIÓN | O43: NO CONTESTA | P43: NO CONTESTA | Q43: NO- VIRTUAL | R43: ADMITIDO | S43: VIRTUAL | T43: RINDIO VIRTUAL | U43: PENDIENTE TODO
A44: 72059565 | B44: Luana Mikela Vilca Grimaldo | C44: 975458726 | D44: lu.vilcg@gmail.com | F44: ORDINARIO | G44: COMUNICACIONES | H44: BASE ANTIGUA | I44: SURQUILLO | J44: 2025-II | N44: SE ENVIÓ INFORMACIÓN | O44: NO CONTESTA | P44: NO CONTESTA | Q44: NO- VIRTUAL | R44: ADMITIDO | S44: VIRTUAL | T44: RINDIO VIRTUAL | U44: PENDIENTE TODO
B45: Bianca Bulic Castillo | C45: 960 984 751 | F45: ORDINARIO | G45: COMUNICACIONES | H45: BASE ANTIGUA | I45: SURQUILLO | J45: 2025-II | N45: SE ENVIÓ INFORMACIÓN | O45: NO CONTESTA | P45: NO CONTESTA | Q45: NO- VIRTUAL | R45: ADMITIDO | S45: VIRTUAL | T45: RINDIO VIRTUAL | U45: ENTREGADO-COMPLETO
A46: 72987469 | B46: TAFUR CALDERON FABIANA PATRICIA | C46: 938561867 | D46: gloriapatcalderon@gmail.com | F46: ORDINARIO | G46: COMUNICACIONES | H46: BASE ANTIGUA | I46: SURQUILLO | J46: 2025-II | N46: SE ENVIÓ INFORMACIÓN | O46: NO CONTESTA | P46: NO CONTESTA | Q46: NO- VIRTUAL | R46: ADMITIDO | S46: VIRTUAL | T46: RINDIO VIRTUAL | U46: PENDIENTE TODO
A47: 71166458 | B47: Diego Alejandro Romero Eyzaguirre | C47: 990374289 | D47: diegoeyzaguirrre@gmail.com%20y | F47: ORDINARIO | G47: PSICOLOGIA | H47: BASE ANTIGUA | I47: SURQUILLO | J47: 2025-II | N47: SE ENVIÓ INFORMACIÓN | O47: MOSTRÓ INTERÉS | P47: MOSTRÓ INTERÉS | Q47: NO- VIRTUAL | R47: ADMITIDO | S47: VIRTUAL | T47: RINDIO VIRTUAL | U47: ENTREGADO-COMPLETO
A48: 61187247 | B48: Nayhara ROjas Puma | C48: 981440181 | D48: VROJASPUMA@GMAIL.COM | F48: ORDINARIO | G48: COMUNICACIONES | H48: BASE ANTIGUA | I48: SURQUILLO | J48: 2025-II | N48: SE ENVIÓ INFORMACIÓN | O48: MOSTRÓ INTERÉS | P48: MOSTRÓ INTERÉS | Q48: NO- VIRTUAL | R48: ADMITIDO | S48: VIRTUAL | T48: RINDIO VIRTUAL | U48: PENDIENTE TODO
A49: 70626278 | B49: Noelia Tueros | C49: 935910466 | D49: noetue0402@gmail.com | F49: ORDINARIO | G49: PSICOLOGIA | H49: PAUTA DIGITAL | I49: SURQUILLO | J49: 2025-II | N49: SE ENVIÓ INFORMACIÓN | O49: NO CONTESTA
A50: 73831317 | B50: MILAGROS HUANCA MINAYA | C50: 994101342 | D50: 000318821@adexperu.edu.pe | F50: ORDINARIO | G50: PSICOLOGIA | H50: PAUTA DIGITAL | I50: SURQUILLO | J50: 2025-II | N50: SE ENVIÓ INFORMACIÓN | O50: NO CONTESTA
A51: 61174432 | B51: Marilia Ormachea | C51: 946143736 | D51: mariliaormachea25@gmail.com | F51: ORDINARIO | G51: PSICOLOGIA | H51: PAUTA DIGITAL | I51: SURQUILLO | J51: 2025-II | N51: SE ENVIÓ INFORMACIÓN | O51: NO CONTESTA
A52: 70714324 | B52: Naomi Mendoza | C52: 976964255 | D52: naomi.mendoza2106@gmail.com | F52: ORDINARIO | G52: PSICOLOGIA | H52: BASE ANTIGUA | I52: SURQUILLO | J52: 2025-II | N52: MOSTRÓ INTERÉS | O52: MOSTRÓ INTERÉS
B53: Claudia Adriana Bernales Cárdenas | C53: 933 048 358 | F53: ORDINARIO | G53: PSICOLOGIA | H53: PAUTA DIGITAL | I53: SURQUILLO | J53: 2025-II | N53: MOSTRÓ INTERÉS | O53: MOSTRÓ INTERÉS
A54: 60482231 | B54: Eduardo Amir | C54: 956412309 | D54: eduardoamirfuertespalpa@gmail.com | F54: ORDINARIO | G54: PSICOLOGIA | H54: BASE ANTIGUA | I54: SURQUILLO | J54: 2025-II | N54: MOSTRÓ INTERÉS | O54: MOSTRÓ INTERÉS
A55: 10818798 | B55: Ely Zarate | C55: 989910731 | D55: elidazaa@hotmail.com | F55: ORDINARIO | G55: COMUNICACIONES | H55: BASE ANTIGUA | I55: SURQUILLO | J55: 2025-II | N55: SE ENVIÓ INFORMACIÓN | O55: NO CONTESTA | P55: NO CONTESTA
A56: 75510518 | B56: Luana Martinez | C56: 924273732 | D56: martinezluana02@gmail.com | F56: ORDINARIO | G56: PSICOLOGIA | H56: BASE ANTIGUA | I56: SURQUILLO | J56: 2025-II | N56: SE ENVIÓ INFORMACIÓN | O56: NO CONTESTA
A57: 70530845 | B57: Rodrigo Sc | C57: 980725174 | F57: ORDINARIO | G57: PSICOLOGIA | H57: BASE ANTIGUA | I57: SURQUILLO | J57: 2025-II | N57: SE ENVIÓ INFORMACIÓN | O57: NO CONTESTA
A58: 44109022 | B58: Emily Lourdes Melendez Saavedra | C58: 915171703 | D58: vrisa252@gmail.com | F58: ORDINARIO | G58: PSICOLOGIA | H58: BASE ANTIGUA | I58: SURQUILLO | J58: 2025-II | N58: NO CONTESTA | O58: NO CONTESTA
A59: 77402431 | B59: Nicole Bazan Ramirez | C59: 923671964 | D59: nicole08br@gmail.com | F59: ORDINARIO | G59: PSICOLOGIA | H59: BASE ANTIGUA | I59: SURQUILLO | J59: 2025-II | N59: NO CONTESTA | O59: INCONTACTABLE
A60: 75393954 | B60: Evelin Alvarado | C60: 906552424 | D60: evelynalvaradomachare@gmail.com | F60: ORDINARIO | G60: COMUNICACIONES | H60: BASE ANTIGUA | I60: SURQUILLO | J60: 2025-II | N60: NO CONTESTA | O60: NO CONTESTA | P60: NO CONTESTA
A61: 4047038 | B61: Javier David Meza Malpartida | C61: 989418077 | D61: mirian.meza.c@hotmail.com | E61: BERLOT BRECH | F61: ORDINARIO | G61: PSICOLOGIA | H61: BASE ANTIGUA | I61: SURQUILLO | J61: 2025-II | N61: MOSTRÓ INTERÉS | O61: MOSTRÓ INTERÉS
A62: 70955787 | B62: Joa Lira | C62: 946191972 | D62: jlelirabenites@outlook.com | F62: ORDINARIO | G62: PSICOLOGIA | H62: BASE ANTIGUA | I62: SURQUILLO | J62: 2025-II | N62: MOSTRÓ INTERÉS | O62: MOSTRÓ INTERÉS
A63: 41418899 | B63: Lleny Salas | C63: 946803366 | D63: jsalassalas2017@gmail.com | F63: ORDINARIO | G63: PSICOLOGIA | H63: BASE ANTIGUA | I63: SURQUILLO | J63: 2025-II | N63: MOSTRÓ INTERÉS | O63: MOSTRÓ INTERÉS
A64: 60819448 | B64: jeremy Rondon | C64: 967562006 | D64: karlivonne16@gmail.com | F64: ORDINARIO | G64: TURISMO | H64: BASE ANTIGUA | I64: SURQUILLO | J64: 2025-II | N64: INCONTACTABLE | O64: NO HUBO PROGRESO | P64: INCONTACTABLE
A65: 25838987 | B65: Marilu uriarte quiroz | C65: 959064960 | D65: mariluuriarte23@gmail.com | F65: ORDINARIO | G65: TURISMO | H65: BASE ANTIGUA | I65: SURQUILLO | J65: 2025-II | N65: MOSTRÓ INTERÉS | O65: MOSTRÓ INTERÉS | P65: MOSTRÓ INTERÉS
A66: 72060298 | B66: Cesar Augusto Galvan Yarleque | C66: 902574391 | D66: galvancafer@gmail.com | F66: ORDINARIO | G66: PSICOLOGIA | H66: BASE ANTIGUA | I66: SURQUILLO | J66: 2025-II | N66: SE ENVIÓ INFORMACIÓN | O66: NO CONTESTA
A67: 72439643 | B67: Ricardo Pardavé Gonzales | C67: 970816646 | D67: ricardopardave530@gmail.com | F67: ORDINARIO | G67: TURISMO | H67: BASE ANTIGUA | I67: SURQUILLO | J67: 2025-II | N67: SE ENVIÓ INFORMACIÓN | O67: ESPERANDO CONFIRMACIÓN PARA EL EVENTO | P67: ESPERANDO CONFIRMACIÓN PARA EL EVENTO
A68: 48517318 | B68: Mar Arenas | C68: 959391263 | D68: mf.arenas24@gmail.com | F68: ORDINARIO | G68: TURISMO | H68: BASE ANTIGUA | I68: SURQUILLO | J68: 2025-II | N68: SE ENVIÓ INFORMACIÓN | O68: NO CONTESTA | P68: NO CONTESTA
A69: 10352456 | B69: Eduardo Antonio Peña Salvador | C69: 901297846 | D69: eduarsalvador412@gmail.com | F69: ORDINARIO | G69: COMUNICACIONES | H69: BASE ANTIGUA | I69: SURQUILLO | J69: 2025-II | N69: SE ENVIÓ INFORMACIÓN | O69: INCONTACTABLE | P69: INCONTACTABLE
A70: 61102332 | B70: Fernando Beder Cachique Capinos | C70: 924081385 | D70: fernandocachique12@gmail.com | F70: ORDINARIO | G70: TURISMO | H70: BASE ANTIGUA | I70: SURQUILLO | J70: 2025-II | N70: SE ENVIÓ INFORMACIÓN | O70: NO CONTESTA | P70: NO CONTESTA
A71: 27752604 | B71: Roger campos suarez | C71: 999034876 | D71: excombatientedelcenepa@gmail.com | F71: ORDINARIO | G71: PSICOLOGIA | H71: BASE ANTIGUA | I71: SURQUILLO | J71: 2025-II | N71: SE ENVIÓ INFORMACIÓN | O71: MOSTRÓ INTERÉS
A72: 75664725 | B72: Luhana Olano Castro | C72: 946593173 | D72: luhana.olano@gmail.com | F72: ORDINARIO | G72: TURISMO | H72: BASE ANTIGUA | I72: SURQUILLO | J72: 2025-II | N72: SE ENVIÓ INFORMACIÓN | O72: NO CONTESTA
A73: 75828834 | B73: Johanna Lizbeth Ruiz Garcia | C73: 992296143 | D73: ruizgarciajohana3@gmail.com | F73: ORDINARIO | G73: COMUNICACIONES | H73: BASE ANTIGUA | I73: SURQUILLO | J73: 2025-II | N73: SE ENVIÓ INFORMACIÓN | O73: NO CONTESTA | P73: NO CONTESTA
A74: 60960024 | B74: Mayra Esthela | C74: 932517626 | D74: xjklw1@gmail.com | F74: ORDINARIO | G74: TURISMO | H74: BASE ANTIGUA | I74: SURQUILLO | J74: 2025-II | N74: MOSTRÓ INTERÉS | O74: MOSTRÓ INTERÉS | P74: MOSTRÓ INTERÉS
A75: 72694687 | B75: Valery Salas Angelino | C75: 932636016 | D75: valerysalasangelino@gmail.com | F75: ORDINARIO | G75: PSICOLOGIA | H75: BASE ANTIGUA | I75: SURQUILLO | J75: 2025-II | N75: SE ENVIÓ INFORMACIÓN | O75: MOSTRÓ INTERÉS
A76: 75620470 | B76: Marcelo Adriano VargasVela | C76: 910871226 | D76: adrianovela2004@gmail.com | F76: ORDINARIO | G76: TURISMO | H76: BASE ANTIGUA | I76: SURQUILLO | J76: 2025-II | N76: SE ENVIÓ INFORMACIÓN | O76: NO CONTESTA
A77: 76547818 | B77: Ara Francis Pintado Flores | C77: 973228988 | D77: zairavpf0502@gmail.com | F77: ORDINARIO | G77: TURISMO | H77: BASE ANTIGUA | I77: SURQUILLO | J77: 2025-II | N77: SE ENVIÓ INFORMACIÓN | O77: NO CONTESTA
A78: 72164550 | B78: Isabella Martinez | C78: 965311480 | D78: Isabella-milena@hotmail.com | F78: ORDINARIO | G78: COMUNICACIONES | H78: BASE ANTIGUA | I78: SURQUILLO | J78: 2025-II | N78: SE ENVIÓ INFORMACIÓN | O78: MOSTRÓ INTERÉS | P78: MOSTRÓ INTERÉS
B79: Oscar David Garcia Carrasco | C79: 958 372 223 | F79: ORDINARIO | G79: COMUNICACIONES | H79: BASE ANTIGUA | I79: SURQUILLO | J79: 2025-II | N79: MOSTRÓ INTERÉS | O79: MOSTRÓ INTERÉS | P79: MOSTRÓ INTERÉS
B80: Camila Chuquizuta Quintana | C80: 965 156 715 | F80: TRASLADO EXTERNO | G80: COMUNICACIONES | H80: BASE ANTIGUA | I80: SURQUILLO | J80: 2025-II | N80: MOSTRÓ INTERÉS | O80: MOSTRÓ INTERÉS | P80: MOSTRÓ INTERÉS
A81: 71085629 | B81: Marta milagros Vite becerra | C81: 918 195 856 | F81: SEGUNDA CARRERA | G81: PSICOLOGIA | H81: BASE ANTIGUA | I81: SURQUILLO | J81: 2025-II | N81: MOSTRÓ INTERÉS | O81: MOSTRÓ INTERÉS
B82: Keira Fabiana Acosta Vargas-Machuca | C82: 981 679 620 | F82: ORDINARIO | G82: PSICOLOGIA | H82: BASE ANTIGUA | I82: SURQUILLO | J82: 2025-II | N82: SE ENVIÓ INFORMACIÓN | O82: EVALUANDO OPCIONES
B83: Abigail Coba Garibay | C83: 912 782 704 | F83: ORDINARIO | G83: COMUNICACIONES | H83: BASE ANTIGUA | I83: SURQUILLO | J83: 2025-II | N83: MOSTRÓ INTERÉS | O83: MOSTRÓ INTERÉS | P83: MOSTRÓ INTERÉS
B84: Laisha Paloma Campos | C84: 930344718 | F84: ORDINARIO | G84: TURISMO | H84: BASE ANTIGUA | I84: SURQUILLO | J84: 2025-II | N84: SE ENVIÓ INFORMACIÓN | O84: NO CONTESTA | P84: NO CONTESTA
A85: 61253387 | B85: ROCIO | C85: 940009304 | F85: ORDINARIO | G85: COMUNICACIONES | H85: BASE ANTIGUA | I85: SURQUILLO | J85: 2025-II | N85: MOSTRÓ INTERÉS | O85: MOSTRÓ INTERÉS | P85: MOSTRÓ INTERÉS
B86: suzette huamani bolaños | C86: 919690182 | G86: PSICOLOGIA | H86: COUNTER | I86: SURQUILLO | J86: 2025-II | N86: SE ENVIÓ INFORMACIÓN | O86: MOSTRÓ INTERÉS | P86: MOSTRÓ INTERÉS | Q86: NO- VIRTUAL | R86: ADMITIDO | S86: VIRTUAL | T86: RENDIRÁ VIRTUAL | U86: PENDIENTE TODO
A87: 75087454 | B87: Melany Nicole Castillo Sudario | C87: 952444148 | D87: luiscastillo_mediotru@hotmail.com y | F87: ORDINARIO | G87: PSICOLOGIA | H87: BASE ANTIGUA | I87: SURQUILLO | J87: 2025-II | N87: SE ENVIÓ INFORMACIÓN | O87: NO CONTESTA | P87: NO CONTESTA | Q87: NO- VIRTUAL | R87: ADMITIDO | S87: VIRTUAL | T87: RINDIO VIRTUAL | U87: PENDIENTE TODO
B88: Ariana Paula Carrera | C88: 973537748 | D88: arianacarrera2009@gmail.com | G88: PSICOLOGIA | H88: PAUTA DIGITAL | I88: SURQUILLO | J88: 2025-II | N88: SE ENVIÓ INFORMACIÓN | O88: NO CONTESTA
B89: Santiago Condori Támara | C89: 906902387 | D89: cynthia.ferrer772@gmail.com | G89: PSICOLOGIA | H89: PAUTA DIGITAL | I89: SURQUILLO | J89: 2025-II | N89: SE ENVIÓ INFORMACIÓN | O89: NO CONTESTA
B90: Julia | C90: 996 217 760 | D90: nataliamassielgv@gmail.com | G90: PSICOLOGIA | H90: PAUTA DIGITAL | I90: SURQUILLO | J90: 2025-II | N90: MOSTRÓ INTERÉS | O90: MOSTRÓ INTERÉS
B91: Araa | C91: 915342838 | D91: abigailcarrion109@gmail.com | G91: PSICOLOGIA | H91: PAUTA DIGITAL | I91: SURQUILLO | J91: 2025-II | N91: SE ENVIÓ INFORMACIÓN | O91: NO CONTESTA
B92: Diego Hernan Carbonero Avila | C92: 949101442 | D92: sharon_carbonero@hotmail.com | G92: COMUNICACIONES | H92: PAUTA DIGITAL | I92: SURQUILLO | J92: 2025-II | N92: SE ENVIÓ INFORMACIÓN | O92: NO CONTESTA | P92: NO CONTESTA
B93: Brenda Sharpay Capuñay Prudencio | C93: 998493118 | D93: marycar1608@hotmail.com | G93: COMUNICACIONES | H93: PAUTA DIGITAL | I93: SURQUILLO | J93: 2025-II | N93: SE ENVIÓ INFORMACIÓN | O93: NO CONTESTA | P93: NO CONTESTA
B94: Adriana Fernanda Honores García | C94: 914182253 | D94: el3ertiempoo@gmail.com | G94: COMUNICACIONES | H94: PAUTA DIGITAL | I94: SURQUILLO | J94: 2025-II | N94: MOSTRÓ INTERÉS | O94: MOSTRÓ INTERÉS | P94: MOSTRÓ INTERÉS
B95: Darlyne | C95: 946406937 | D95: hanako.x4@gmail.com | G95: COMUNICACIONES | H95: PAUTA DIGITAL | I95: SURQUILLO | J95: 2025-II | N95: MOSTRÓ INTERÉS | O95: MOSTRÓ INTERÉS | P95: MOSTRÓ INTERÉS
B96: Angelina Luisa Calderón Huerta | C96: 934001205 | D96: angelinaluisach2008@gmail.com | G96: COMUNICACIONES | H96: PAUTA DIGITAL | I96: SURQUILLO | J96: 2025-II | N96: SE ENVIÓ INFORMACIÓN | O96: INCONTACTABLE | P96: INCONTACTABLE
B97: milagros contreras | C97: 995740628 | D97: mili0414@gmail.com | G97: COMUNICACIONES | H97: PAUTA DIGITAL | I97: SURQUILLO | J97: 2025-II | N97: SE ENVIÓ INFORMACIÓN | O97: NO CONTESTA | P97: NO CONTESTA
B98: Sophiana Romina | C98: 933687200 | D98: sophianacotrina508@gmail.com | G98: COMUNICACIONES | H98: PAUTA DIGITAL | I98: SURQUILLO | J98: 2025-II | N98: SE ENVIÓ INFORMACIÓN | O98: NO CONTESTA | P98: NO CONTESTA
B99: Abigail | C99: 912 782 704 | D99: cobagaribayabigail@gmail.com | G99: COMUNICACIONES | H99: PAUTA DIGITAL | I99: SURQUILLO | J99: 2025-II | N99: MOSTRÓ INTERÉS | O99: MOSTRÓ INTERÉS | P99: MOSTRÓ INTERÉS
B100: Pedro Luís Severino Navarro | C100: 922521210 | D100: pedroseverino2021@gmail.com | G100: COMUNICACIONES | H100: PAUTA DIGITAL | I100: SURQUILLO | J100: 2025-II | N100: SE ENVIÓ INFORMACIÓN | O100: MOSTRÓ INTERÉS | P100: MOSTRÓ INTERÉS
...

Sheet BD|Lilya E.
A1: DNI | B1: NOMBRES | C1: CELULAR | D1: CORREO | E1: COLEGIO DE PROCEDENCIA | F1: MODALIDAD | G1: ESCUELA | H1: ORIGEN | I1: SEDE | J1: SEMESTRE | K1: CAMPAÑA | L1: EVENTO | M1: FECHA DE INGRESO DE LEAD | N1: CONTACTO I | O1: CONTACTO II | P1: CONTACTO III | Q1: ¿PAGÓ DERECHO DE INSCRIPCIÓN? | R1: STATUS ACADÉMICO | S1: TIPO DE EXAMEN | T1: STATUS DE EXAMEN | U1: ENTREGA DE DOCUMENTOS | V1: OBSERVACION
A2: 61530615 | B2: Dana | C2: 51934364137 | D2: dana.lossio11@gmail.com | G2: COMUNICACIONES | H2: PAUTA DIGITAL | I2: SURQUILLO | J2: 2025-II | K2: Open Day 2 | L2: Open Day 2 | N2: SE ENVIÓ INFORMACIÓN | P2: =TRIM(BD_LilyaEspinoza[[#This Row],[CONTACTO II]])
A3: 72985252 | B3: luana | C3: 51985464024 | D3: p6eljaraespinoza@gmail.com | G3: COMUNICACIONES | H3: PAUTA DIGITAL | I3: SURQUILLO | J3: 2025-II | K3: Open Day 2 | L3: Open Day 2 | N3: SE ENVIÓ INFORMACIÓN | P3: =TRIM(BD_LilyaEspinoza[[#This Row],[CONTACTO II]])
A4: 10318207 | B4: Angie Barboza (SU HIJO ESTA EN 4 AÑO, SOLO QUIERE INFORMACION) | C4: 51967579172 | D4: angiebarbozabbva@gmail.com | G4: COMUNICACIONES | H4: PAUTA DIGITAL | J4: 2025-II | K4: Open Day 2 | L4: Open Day 2 | N4: MOSTRÓ INTERÉS | O4: SE ENVIÓ INFORMACIÓN | P4: =TRIM(BD_LilyaEspinoza[[#This Row],[CONTACTO II]]) -> SE ENVIÓ INFORMACIÓN
A5: 74433285 | B5: Priscilla Jumachi Ramírez | C5: 51976035113 | D5: jumachiramirezpriscila@gmail.com | E5: TERMINÉ EL COLEGIO | F5: ORDINARIO | G5: COMUNICACIONES | H5: PAUTA DIGITAL | J5: 2025-II | K5: Taller Vivencial 2 | L5: Taller Vivencial 2 | N5: MOSTRÓ INTERÉS | O5: SE ENVIÓ INFORMACIÓN | P5: =TRIM(BD_LilyaEspinoza[[#This Row],[CONTACTO II]]) -> SE ENVIÓ INFORMACIÓN
A6: 44254678 | B6: Yessy Perez Arango | C6: 51952324378 | D6: yessy_perez_1404@hotmail.es | G6: COMUNICACIONES | H6: PAUTA DIGITAL | J6: 2025-II | K6: Open Day 2 | L6: Open Day 2 | N6: MOSTRÓ INTERÉS | P6: =TRIM(BD_LilyaEspinoza[[#This Row],[CONTACTO II]])
A7: 61493469 | B7: Luana Camila Garcia Estrada | C7: 51994919135 | D7: garciaestradaluanacamila@gmail.com | G7: COMUNICACIONES | H7: PAUTA DIGITAL | J7: 2025-II | K7: Open Day 2 | L7: Open Day 2 | N7: MOSTRÓ INTERÉS | P7: =TRIM(BD_LilyaEspinoza[[#This Row],[CONTACTO II]])
A8: 72555167 | B8: Gael Alessandro Mejia Ravelo | C8: 51922744446 | D8: gaelmejrav@gmail.com | G8: COMUNICACIONES | H8: PAUTA DIGITAL | J8: 2025-II | K8: Open Day 2 | L8: Open Day 2 | N8: OTROS | P8: =TRIM(BD_LilyaEspinoza[[#This Row],[CONTACTO II]]) | V8: DERECHO
A9: 41814832 | B9: Miguel Angel Borja Ramirez (su hija esta en 4to) | C9: 51952063649 | D9: angel_miguel5@hotmail.com | G9: COMUNICACIONES | H9: PAUTA DIGITAL | I9: SURQUILLO | J9: 2025-II | K9: Taller Vivencial 2 | N9: SE ENVIÓ INFORMACIÓN
A10: 10707384 | B10: Amalia Rosalia Huamansupa Méndez | C10: 51931663262 | D10: amaliarosalia2@gmail.com | G10: COMUNICACIONES | H10: PAUTA DIGITAL | J10: 2025-II | K10: Taller Vivencial 2 | L10: Taller Vivencial 2 | N10: SE ENVIÓ INFORMACIÓN | P10: =TRIM(BD_LilyaEspinoza[[#This Row],[CONTACTO II]])
A11: 73265708 | B11: VALERIA CELESTE BENDEZU URBINA | C11: 903588607 | D11: VALERIABENDEZU777@GMAIL.COM | E11: termino el colegio | F11: ORDINARIO | G11: COMUNICACIONES | H11: COUNTER | I11: SURQUILLO | J11: 2025-II | N11: MOSTRÓ INTERÉS | O11: MOSTRÓ INTERÉS | P11: =TRIM(BD_LilyaEspinoza[[#This Row],[CONTACTO II]]) -> MOSTRÓ INTERÉS | Q11: NO- VIRTUAL | R11: ADMITIDO | S11: VIRTUAL | T11: RINDIO VIRTUAL
A12: 47464055 | B12: Pool Guillermo Del Valle Chuquichanca | C12: 992419321 | D12: poolguillermodelvalle@gmail.com | E12: TERMINÉ EL COLEGIO | F12: ORDINARIO | G12: COMUNICACIONES | H12: PAUTA DIGITAL | I12: SURQUILLO | J12: 2025-II | N12: MOSTRÓ INTERÉS | O12: MOSTRÓ INTERÉS | P12: =TRIM(BD_LilyaEspinoza[[#This Row],[CONTACTO II]]) -> MOSTRÓ INTERÉS | Q12: NO- VIRTUAL | R12: ADMITIDO | S12: VIRTUAL | T12: RINDIO VIRTUAL
A13: 61294597 | B13: LAURA SOFIA MORALES BOBADILLA | C13: 923162958 | D13: XLAURAMORALESX@GMAIL.COM | E13: TERMINÉ EL COLEGIO | F13: ORDINARIO | G13: COMUNICACIONES | H13: COUNTER | J13: 2025-II | N13: MOSTRÓ INTERÉS | O13: MOSTRÓ INTERÉS | P13: =TRIM(BD_LilyaEspinoza[[#This Row],[CONTACTO II]]) -> MOSTRÓ INTERÉS | Q13: NO- VIRTUAL | R13: ADMITIDO | S13: VIRTUAL | T13: RINDIO VIRTUAL | U13: PENDIENTE TODO
A14: 76093066 | B14: araceli mireya hilario huarcaya | C14: 51922585910 | D14: aracelihilario12@hotmail.com | G14: COMUNICACIONES | H14: PAUTA DIGITAL | I14: SURQUILLO | J14: 2025-II | K14: Taller Vivencial 2 | L14: Taller Vivencial 2 | N14: NO CONTESTA | P14: =TRIM(BD_LilyaEspinoza[[#This Row],[CONTACTO II]])
A15: 9855340 | B15: Jeanett Rojas (busca becas deportivas) | C15: 51990644062 | D15: jeanettrb@hotmail.com | G15: COMUNICACIONES | H15: PAUTA DIGITAL | I15: SURQUILLO | J15: 2025-II | K15: Taller Vivencial 2 | L15: Taller Vivencial 2 | N15: SELECCIONÓ OTRA UNIVERSIDAD | P15: =TRIM(BD_LilyaEspinoza[[#This Row],[CONTACTO II]])
A16: 45513037 | B16: Slingger Mendez Risco (busca modalidad virtual) | C16: 51983076522 | D16: mendezrisco66@gmail.com | G16: COMUNICACIONES | H16: PAUTA DIGITAL | I16: SURQUILLO | J16: 2025-II | K16: Taller Vivencial 2 | L16: Taller Vivencial 2 | N16: SELECCIONÓ OTRA UNIVERSIDAD | P16: =TRIM(BD_LilyaEspinoza[[#This Row],[CONTACTO II]])
B17: Sandra Natalia | C17: 51929906915 | D17: sandranac7@gmail.com | G17: COMUNICACIONES | H17: PAUTA DIGITAL | I17: SURQUILLO | J17: 2025-II | K17: Open Day 1 | L17: Open Day 1 | N17: NO CONTESTA | O17: NO CONTESTA | P17: =TRIM(BD_LilyaEspinoza[[#This Row],[CONTACTO II]]) -> NO CONTESTA
B18: Thais Mendoza Cardenas | C18: 977 370 299 | G18: COMUNICACIONES | H18: PAUTA DIGITAL | I18: SURQUILLO | J18: 2025-II | K18: Open Day 1 | L18: Open Day 1 | N18: NO CONTESTA | O18: NO CONTESTA | P18: =TRIM(BD_LilyaEspinoza[[#This Row],[CONTACTO II]]) -> NO CONTESTA
B19: Tatiana Salazar | C19: 964853500 | D19: josuevsalas.22@gmail.com | G19: COMUNICACIONES | H19: PAUTA DIGITAL | I19: SURQUILLO | J19: 2025-II | K19: Open Day 1 | L19: Open Day 1 | N19: NO CONTESTA | O19: NO CONTESTA | P19: =TRIM(BD_LilyaEspinoza[[#This Row],[CONTACTO II]]) -> NO CONTESTA
B20: Lucy Saire | C20: 961605219 | D20: aquiquijanasalas@gmail.com | G20: COMUNICACIONES | H20: PAUTA DIGITAL | I20: SURQUILLO | J20: 2025-II | K20: Open Day 1 | L20: Open Day 1 | N20: NO CONTESTA | O20: NO CONTESTA | P20: =TRIM(BD_LilyaEspinoza[[#This Row],[CONTACTO II]]) -> NO CONTESTA
A21: 10478909 | B21: Leoncio Manuel Yanac Huamani | C21: 51987774324 | D21: yamashiro999@hotmail.com | G21: COMUNICACIONES | H21: PAUTA DIGITAL | I21: SURQUILLO | J21: 2025-II | K21: Taller Vivencial 2 | L21: Taller Vivencial 2 | N21: NO CONTESTA | P21: =TRIM(BD_LilyaEspinoza[[#This Row],[CONTACTO II]])
B22: Ana Arroyo Paz | C22: 977250157 | D22: angelinacasias0@gmail.com | G22: COMUNICACIONES | H22: PAUTA DIGITAL | I22: SURQUILLO | J22: 2025-II | K22: Open Day 1 | L22: Open Day 1 | N22: NO CONTESTA | O22: NO CONTESTA | P22: =TRIM(BD_LilyaEspinoza[[#This Row],[CONTACTO II]]) -> NO CONTESTA
B23: José Encarnación Mendoza Fiestas | C23: 958804504 | D23: mayorcajosecarlos@gmail.com | G23: COMUNICACIONES | H23: PAUTA DIGITAL | I23: SURQUILLO | J23: 2025-II | K23: Open Day 1 | L23: Open Day 1 | N23: NO CONTESTA | O23: NO CONTESTA | P23: =TRIM(BD_LilyaEspinoza[[#This Row],[CONTACTO II]]) -> NO CONTESTA
A24: 61422059 | B24: Yami Bautista | C24: 51933763900 | D24: yamibauqui@gmail.com | G24: COMUNICACIONES | H24: PAUTA DIGITAL | I24: SURQUILLO | J24: 2025-II | K24: Taller Vivencial 2 | L24: Taller Vivencial 2 | N24: NO CONTESTA | P24: =TRIM(BD_LilyaEspinoza[[#This Row],[CONTACTO II]])
A25: 41500340 | B25: Betsy Janet Alarcon | C25: 51991775318 | D25: betsyalarcon1620@gmail.com | G25: COMUNICACIONES | H25: PAUTA DIGITAL | I25: SURQUILLO | J25: 2025-II | K25: Taller Vivencial 2 | L25: Taller Vivencial 2 | N25: INCONTACTABLE | P25: =TRIM(BD_LilyaEspinoza[[#This Row],[CONTACTO II]])
A26: 45510408 | B26: Omar Alayo M | C26: 51981283728 | D26: omaralayo.contacto@gmail.com | G26: COMUNICACIONES | H26: PAUTA DIGITAL | I26: SURQUILLO | J26: 2025-II | K26: Taller Vivencial 2 | L26: Taller Vivencial 2 | N26: SE ENVIÓ INFORMACIÓN | P26: =TRIM(BD_LilyaEspinoza[[#This Row],[CONTACTO II]])
A27: 71151536 | B27: FABIAN ARTURO MELENDEZ ARIZAGA | C27: 949141024 | D27: fabianmcu@gmail.com | E27: TERMINÉ EL COLEGIO | F27: ORDINARIO | G27: COMUNICACIONES | H27: BASE ANTIGUA | J27: 2025-II | N27: MOSTRÓ INTERÉS | O27: MOSTRÓ INTERÉS | P27: =TRIM(BD_LilyaEspinoza[[#This Row],[CONTACTO II]]) -> MOSTRÓ INTERÉS | Q27: NO- VIRTUAL | R27: ADMITIDO | S27: VIRTUAL | T27: RINDIO VIRTUAL
A28: 72984417 | B28: CHIARA CASAPIA MONTENEGRO | C28: 976544471 | D28: CHIARACASAPIAM@GMAIL.COM | G28: COMUNICACIONES | H28: EVENTO PRESENCIAL | I28: SANTA ANITA | J28: 2025-II | N28: MOSTRÓ INTERÉS | P28: =TRIM(BD_LilyaEspinoza[[#This Row],[CONTACTO II]])
A29: 78719582 | B29: VICTOR RICARDO ARENAS HAUCASE | C29: 974339475 | D29: lesliearenas29@gmail.com | G29: PSICOLOGIA | H29: EVENTO PRESENCIAL | I29: SURQUILLO | J29: 2025-II | N29: MOSTRÓ INTERÉS | O29: SE ENVIÓ INFORMACIÓN | P29: =TRIM(BD_LilyaEspinoza[[#This Row],[CONTACTO II]]) -> SE ENVIÓ INFORMACIÓN
A30: 71166102 | B30: Xiomara Aime Peña Cahuama | C30: 927306453 | D30: Xiomaraaime15@gmail.com | G30: PSICOLOGIA | H30: EVENTO PRESENCIAL | I30: SURQUILLO | J30: 2025-II | N30: NO CONTESTA | O30: NO CONTESTA | P30: =TRIM(BD_LilyaEspinoza[[#This Row],[CONTACTO II]]) -> NO CONTESTA
A31: 70951357 | B31: Emilio Silva Molina | C31: 915 950 336 | D31: emiliosilvamolina@gmail.com | G31: TURISMO | H31: EVENTO PRESENCIAL | I31: SURQUILLO | J31: 2025-II | N31: SELECCIONÓ OTRA UNIVERSIDAD | O31: NO CONTESTA | P31: =TRIM(BD_LilyaEspinoza[[#This Row],[CONTACTO II]]) -> NO CONTESTA
A32: 75483496 | B32: Jasmin Chavez | C32: 990193900 | D32: jasminchavezkj@gmail.com | G32: COMUNICACIONES | H32: EVENTO PRESENCIAL | I32: SURQUILLO | J32: 2025-II | N32: NO CONTESTA | O32: NO CONTESTA | P32: =TRIM(BD_LilyaEspinoza[[#This Row],[CONTACTO II]]) -> NO CONTESTA
A33: 70622193 | B33: Aylin Escalante | C33: 51994840331 | D33: ailynescalantenoa@gmail.com | G33: PSICOLOGIA | H33: EVENTO PRESENCIAL | I33: SURQUILLO | J33: 2025-II | N33: NO CONTESTA | O33: NO CONTESTA | P33: =TRIM(BD_LilyaEspinoza[[#This Row],[CONTACTO II]]) -> NO CONTESTA
A34: 73537627 | B34: Adriana Huaringa | C34: 51989837748 | D34: adrianitah.1718@gmail.com | G34: PSICOLOGIA | H34: EVENTO PRESENCIAL | I34: SURQUILLO | J34: 2025-II | N34: NO CONTESTA | O34: NO CONTESTA | P34: =TRIM(BD_LilyaEspinoza[[#This Row],[CONTACTO II]]) -> NO CONTESTA
A35: 71188577 | B35: Fabian Sandi Malca | C35: 51931530179 | D35: fabiansandimalca@gmail.com | G35: PSICOLOGIA | H35: EVENTO PRESENCIAL | I35: SURQUILLO | J35: 2025-II | N35: OTROS | O35: NO CONTESTA | P35: =TRIM(BD_LilyaEspinoza[[#This Row],[CONTACTO II]]) -> NO CONTESTA | V35: PROVINCIA
A36: 61294582 | B36: Génesis Sarmiento solis | C36: 51977150446 | D36: genesismiacielo12@gmail.com | G36: COMUNICACIONES | H36: EVENTO PRESENCIAL | I36: SURQUILLO | J36: 2025-II | N36: NO CONTESTA | O36: NO CONTESTA | P36: =TRIM(BD_LilyaEspinoza[[#This Row],[CONTACTO II]]) -> NO CONTESTA
A37: 72328397 | B37: Jansel Raul Muñoz Macedo | C37: 926286360 | D37: jhans.1807@gmail.com | E37: CIBERTEC | F37: ORDINARIO | G37: PSICOLOGIA | H37: EVENTO PRESENCIAL | I37: SANTA ANITA | J37: 2025-II | N37: MOSTRÓ INTERÉS | O37: SE ENVIÓ INFORMACIÓN | P37: =TRIM(BD_LilyaEspinoza[[#This Row],[CONTACTO II]]) -> SE ENVIÓ INFORMACIÓN | Q37: NO- VIRTUAL | R37: ADMITIDO | S37: VIRTUAL | T37: RINDIO VIRTUAL | U37: PEND. CERTIFICADO
A38: 76299118 | B38: Keyco Celina Mt | C38: 51970927314 | D38: keyco.a20@gmail.com | G38: PSICOLOGIA | H38: EVENTO PRESENCIAL | I38: SURQUILLO | J38: 2025-II | N38: INCONTACTABLE | O38: MOSTRÓ INTERÉS | P38: SE ENVIÓ INFORMACIÓN
A39: 76390529 | B39: Alexia Perla | C39: 51997054491 | D39: perlayauriantonio@gmail.com | G39: PSICOLOGIA | H39: EVENTO PRESENCIAL | I39: SURQUILLO | J39: 2025-II | N39: NO CONTESTA | O39: NO CONTESTA | P39: =TRIM(BD_LilyaEspinoza[[#This Row],[CONTACTO II]]) -> NO CONTESTA
A40: 76320818 | B40: Flavio Castro Chalo | C40: 948287087 | D40: flaviocastrochalo4@gmail.com | G40: PSICOLOGIA | H40: EVENTO PRESENCIAL | I40: SURQUILLO | J40: 2025-II | N40: INCONTACTABLE | O40: INCONTACTABLE | P40: =TRIM(BD_LilyaEspinoza[[#This Row],[CONTACTO II]]) -> INCONTACTABLE
A41: 10605971 | B41: Carmen carhuancho Cela | C41: 51992548236 | D41: carmennormacarhuancho@gmail.com | G41: COMUNICACIONES | H41: EVENTO PRESENCIAL | I41: SURQUILLO | J41: 2025-II | N41: SELECCIONÓ OTRA UNIVERSIDAD | O41: SELECCIONÓ OTRA UNIVERSIDAD | P41: =TRIM(BD_LilyaEspinoza[[#This Row],[CONTACTO II]]) -> SELECCIONÓ OTRA UNIVERSIDAD
A42: 60980182 | B42: Xiomara Pacheco | C42: 51982823713 | D42: alexandrapachecoarenas@gmail.com | G42: PSICOLOGIA | H42: EVENTO PRESENCIAL | I42: SURQUILLO | J42: 2025-II | N42: NO CONTESTA | O42: NO CONTESTA | P42: =TRIM(BD_LilyaEspinoza[[#This Row],[CONTACTO II]]) -> NO CONTESTA
A43: 70723312 | B43: Mily Garay | C43: 51972292579 | D43: bchwngaraym@gmail.com | G43: COMUNICACIONES | H43: EVENTO PRESENCIAL | I43: SURQUILLO | J43: 2025-II | N43: NO CONTESTA | O43: NO CONTESTA | P43: =TRIM(BD_LilyaEspinoza[[#This Row],[CONTACTO II]]) -> NO CONTESTA
A44: 61264444 | B44: Sandy Cordova Castillo | C44: 902525468 | D44: sandyanagabriel22@gmail.com | G44: PSICOLOGIA | H44: EVENTO PRESENCIAL | I44: SURQUILLO | J44: 2025-II | N44: NO CONTESTA | O44: NO CONTESTA | P44: =TRIM(BD_LilyaEspinoza[[#This Row],[CONTACTO II]]) -> NO CONTESTA
A45: 60333923 | B45: Lucciana Espinoza Espejo | C45: 51935817353 | D45: luccianaee@gmail.com | G45: COMUNICACIONES | H45: EVENTO PRESENCIAL | I45: SURQUILLO | J45: 2025-II | N45: INCONTACTABLE | O45: INCONTACTABLE | P45: =TRIM(BD_LilyaEspinoza[[#This Row],[CONTACTO II]]) -> INCONTACTABLE
A46: 46456243 | B46: Anelisse Calderon | C46: 51927480328 | D46: valeriacalderonpi@gmail.com | G46: PSICOLOGIA | H46: EVENTO PRESENCIAL | I46: SURQUILLO | J46: 2025-II | N46: INCONTACTABLE | O46: NO CONTESTA | P46: INCONTACTABLE
A47: 44303678 | B47: Mario Ave Cesar Gonza Revilla | C47: 51 967 303 702 | D47: gonzarevillamario70@gmail.com | G47: TURISMO | H47: EVENTO PRESENCIAL | I47: SURQUILLO | J47: 2025-II | N47: NO CONTESTA | O47: NO CONTESTA | P47: =TRIM(BD_LilyaEspinoza[[#This Row],[CONTACTO II]]) -> NO CONTESTA
A48: 43063037 | B48: Katherine Santos | C48: 51 982 505 941 | D48: msantos_delgado@hotmail.com | G48: TURISMO | H48: EVENTO PRESENCIAL | I48: SURQUILLO | J48: 2025-II | N48: NO CONTESTA | O48: NO CONTESTA | P48: =TRIM(BD_LilyaEspinoza[[#This Row],[CONTACTO II]]) -> NO CONTESTA
A49: 77596165 | B49: Diana Pantoja | C49: 935 897 741 | D49: dianapantoja1105@gmail.com | G49: TURISMO | H49: EVENTO PRESENCIAL | I49: SURQUILLO | J49: 2025-II | N49: NO CONTESTA | O49: NO CONTESTA | P49: =TRIM(BD_LilyaEspinoza[[#This Row],[CONTACTO II]]) -> NO CONTESTA
A50: 73079493 | B50: Leslie Manrique | C50: 51944042043 | D50: gianella.mg@hotmail.com | G50: PSICOLOGIA | H50: EVENTO PRESENCIAL | I50: SURQUILLO | J50: 2025-II | N50: NO CONTESTA | O50: NO CONTESTA | P50: =TRIM(BD_LilyaEspinoza[[#This Row],[CONTACTO II]]) -> NO CONTESTA
A51: 507578 | B51: Mery Sosa Camma | C51: 51 992 352 828 | D51: merysosa06@gmail.com | G51: TURISMO | H51: EVENTO PRESENCIAL | I51: SURQUILLO | J51: 2025-II | N51: NO CONTESTA | O51: NO CONTESTA | P51: =TRIM(BD_LilyaEspinoza[[#This Row],[CONTACTO II]]) -> NO CONTESTA
A52: 75079922 | B52: Guido Quispe Pacho | C52: 51922146679 | D52: guimar_producciones@hotmail.com | G52: COMUNICACIONES | H52: EVENTO PRESENCIAL | I52: SURQUILLO | J52: 2025-II | N52: NO CONTESTA | O52: NO CONTESTA | P52: =TRIM(BD_LilyaEspinoza[[#This Row],[CONTACTO II]]) -> NO CONTESTA
A53: 63317810 | B53: Becerra Castilo | C53: 51 928 346 381 | D53: rosabecerra.892@gmail.com | G53: TURISMO | H53: EVENTO PRESENCIAL | I53: SURQUILLO | J53: 2025-II | N53: NO CONTESTA | O53: NO CONTESTA | P53: =TRIM(BD_LilyaEspinoza[[#This Row],[CONTACTO II]]) -> NO CONTESTA
B54: Guillermo Moretti | C54: 51936979089 | D54: Moreygutierrezjunior@gmail.com | G54: COMUNICACIONES | H54: EVENTO PRESENCIAL | I54: SURQUILLO | J54: 2025-II | N54: NO CONTESTA | O54: NO CONTESTA | P54: =TRIM(BD_LilyaEspinoza[[#This Row],[CONTACTO II]]) -> NO CONTESTA
A55: 60418475 | B55: Elizabeth Gonzales Llance | C55: 51936979089 | D55: gonzalesllanceisabelelizabeth@gmail.com | G55: COMUNICACIONES | H55: EVENTO PRESENCIAL | I55: SURQUILLO | J55: 2025-II | N55: NO CONTESTA | O55: NO CONTESTA | P55: =TRIM(BD_LilyaEspinoza[[#This Row],[CONTACTO II]]) -> NO CONTESTA
A56: 70731178 | B56: Joshua Caleb | C56: 901595245 | D56: araujoagurtojoshua12@gmail.com | G56: PSICOLOGIA | H56: EVENTO PRESENCIAL | I56: SURQUILLO | J56: 2025-II | N56: SELECCIONÓ OTRA UNIVERSIDAD | O56: NO CONTESTA | P56: =TRIM(BD_LilyaEspinoza[[#This Row],[CONTACTO II]]) -> NO CONTESTA | V56: Pide que no lo contacten
A57: 73705896 | B57: Mía Mery | C57: 51 972 121 373 | D57: meryclarapacompiaquispe438@gmail.com | G57: TURISMO | H57: EVENTO PRESENCIAL | I57: SURQUILLO | J57: 2025-II | N57: INCONTACTABLE | O57: INCONTACTABLE | P57: =TRIM(BD_LilyaEspinoza[[#This Row],[CONTACTO II]]) -> INCONTACTABLE
A58: 62851948 | B58: Sebastian (QUIERE ESTUDIAR ADMINISTRACION) | C58: 51969173195 | D58: scasastucto@gmail.com | H58: EVENTO PRESENCIAL | I58: SURQUILLO | J58: 2025-II | N58: SELECCIONÓ OTRA UNIVERSIDAD | P58: =TRIM(BD_LilyaEspinoza[[#This Row],[CONTACTO II]]) | V58: ADMINISTRACION
A59: 71112883 | B59: Yaneth | C59: 51939765792 | D59: yyhuamansuarez@gmail.com | G59: COMUNICACIONES | H59: EVENTO PRESENCIAL | I59: SURQUILLO | J59: 2025-II | N59: NO CONTESTA | O59: NO CONTESTA | P59: =TRIM(BD_LilyaEspinoza[[#This Row],[CONTACTO II]]) -> NO CONTESTA
A60: 46415001 | B60: Jenny Edith | C60: 945145216 | D60: jedithjalis88@gmail.com | G60: PSICOLOGIA | H60: EVENTO PRESENCIAL | I60: SURQUILLO | J60: 2025-II | N60: NO CONTESTA | O60: NO CONTESTA | P60: =TRIM(BD_LilyaEspinoza[[#This Row],[CONTACTO II]]) -> NO CONTESTA
A61: 9334198 | B61: Soledad Rutty | C61: 993103936 | D61: solenka.vm@gmail.com | G61: PSICOLOGIA | H61: EVENTO PRESENCIAL | I61: SURQUILLO | J61: 2025-II | N61: NO CONTESTA | O61: NO CONTESTA | P61: SELECCIONÓ OTRA UNIVERSIDAD
A62: 90045702 | B62: Geraldine Bonifacio Romero | C62: 977330059 | D62: carmen.roma2019@outlook.com | G62: COMUNICACIONES | H62: PAUTA DIGITAL | I62: SURQUILLO | J62: 2025-II | K62: Open Day 1 | L62: Open Day 1 | N62: SE ENVIÓ INFORMACIÓN | O62: MOSTRÓ INTERÉS | P62: =TRIM(BD_LilyaEspinoza[[#This Row],[CONTACTO II]]) -> MOSTRÓ INTERÉS
B63: M Zoraida Alegria | C63: 51999896875 | D63: alemarie35@hotmail.com | G63: COMUNICACIONES | H63: PAUTA DIGITAL | I63: SURQUILLO | J63: 2025-II | K63: Open Day 1 | L63: Open Day 1 | N63: NO CONTESTA | O63: NO CONTESTA | P63: =TRIM(BD_LilyaEspinoza[[#This Row],[CONTACTO II]]) -> NO CONTESTA
B64: Cam ☆ | C64: 51960690387 | D64: camivevibts@gmail.com | G64: COMUNICACIONES | H64: PAUTA DIGITAL | I64: SURQUILLO | J64: 2025-II | K64: Open Day 1 | L64: Open Day 1 | N64: NO CONTESTA | O64: NO CONTESTA | P64: =TRIM(BD_LilyaEspinoza[[#This Row],[CONTACTO II]]) -> NO CONTESTA
A65: 60575110 | B65: Fernanda Kamila Calderon Suarez | C65: 51991972209 | D65: cfernandakamila@gmail.com | G65: COMUNICACIONES | H65: PAUTA DIGITAL | I65: SURQUILLO | J65: 2025-II | K65: Open Day 1 | L65: Open Day 1 | N65: MOSTRÓ INTERÉS | O65: MOSTRÓ INTERÉS | P65: =TRIM(BD_LilyaEspinoza[[#This Row],[CONTACTO II]]) -> MOSTRÓ INTERÉS
A66: 71454758 | B66: Anamile Huarh | C66: 51929543197 | D66: huarhdanna@gmail.com | G66: COMUNICACIONES | H66: PAUTA DIGITAL | I66: SURQUILLO | J66: 2025-II | K66: Open Day 1 | L66: Open Day 1 | N66: NO CONTESTA | O66: NO CONTESTA | P66: =TRIM(BD_LilyaEspinoza[[#This Row],[CONTACTO II]]) -> NO CONTESTA
B67: Paola Rojas | C67: 51949456825 | D67: paola_rs02@hotmail.com | G67: PSICOLOGIA | H67: PAUTA DIGITAL | I67: SURQUILLO | J67: 2025-II | K67: Open Day 1 | L67: Open Day 1 | N67: NO CONTESTA | O67: MOSTRÓ INTERÉS | P67: SE ENVIÓ INFORMACIÓN
A68: 41831929 | B68: Jacqueline CARRASCO OSCANOA | C68: 51993752444 | D68: jackyeli20@hotmail.com | G68: PSICOLOGIA | H68: PAUTA DIGITAL | I68: SURQUILLO | J68: 2025-II | K68: Open Day 1 | L68: Open Day 1 | N68: SE ENVIÓ INFORMACIÓN | O68: SE ENVIÓ INFORMACIÓN | P68: =TRIM(BD_LilyaEspinoza[[#This Row],[CONTACTO II]]) -> SE ENVIÓ INFORMACIÓN
B69: Marii de Los Angeles | C69: 51976358383 | D69: mg532778@gmail.com | G69: PSICOLOGIA | H69: PAUTA DIGITAL | I69: SURQUILLO | J69: 2025-II | K69: Open Day 1 | L69: Open Day 1 | N69: NO CONTESTA | O69: NO CONTESTA | P69: =TRIM(BD_LilyaEspinoza[[#This Row],[CONTACTO II]]) -> NO CONTESTA
A70: 72060549 | B70: Luciana Zapata Molina | C70: 51970696761 | D70: luciana.zapata116@gmail.com | G70: PSICOLOGIA | H70: PAUTA DIGITAL | I70: SURQUILLO | J70: 2025-II | K70: Open Day 1 | N70: MOSTRÓ INTERÉS
B71: Camila Ventura | C71: 51916157161 | D71: camilasvp7@gmail.com | G71: PSICOLOGIA | H71: PAUTA DIGITAL | I71: SURQUILLO | J71: 2025-II | K71: Open Day 1 | L71: Open Day 1 | N71: NO CONTESTA | O71: NO CONTESTA | P71: =TRIM(BD_LilyaEspinoza[[#This Row],[CONTACTO II]]) -> NO CONTESTA
B72: Val Txz | C72: 51976817335 | D72: valeskaantara@gmail.com | G72: PSICOLOGIA | H72: PAUTA DIGITAL | I72: SURQUILLO | J72: 2025-II | K72: Open Day 1 | L72: Open Day 1 | N72: NO CONTESTA | O72: NO CONTESTA | P72: =TRIM(BD_LilyaEspinoza[[#This Row],[CONTACTO II]]) -> NO CONTESTA
B73: Luz Marcela Mendez Caceres | C73: 952825195 | D73: lucymc77@hotmail.com | G73: PSICOLOGIA | H73: PAUTA DIGITAL | I73: SURQUILLO | J73: 2025-II | K73: Open Day 1 | L73: Open Day 1 | N73: MOSTRÓ INTERÉS | O73: MOSTRÓ INTERÉS | P73: =TRIM(BD_LilyaEspinoza[[#This Row],[CONTACTO II]]) -> MOSTRÓ INTERÉS
B74: Fran | C74: 51998560425 | D74: francescaazana@gmail.com | G74: PSICOLOGIA | H74: PAUTA DIGITAL | I74: SURQUILLO | J74: 2025-II | K74: Open Day 1 | L74: Open Day 1 | N74: INCONTACTABLE | O74: INCONTACTABLE | P74: =TRIM(BD_LilyaEspinoza[[#This Row],[CONTACTO II]]) -> INCONTACTABLE
B75: Ariana | C75: 51971270851 | D75: huamanmatosandrea@gmail.com | G75: PSICOLOGIA | H75: PAUTA DIGITAL | I75: SURQUILLO | J75: 2025-II | K75: Open Day 1 | L75: Open Day 1 | N75: NO CONTESTA | O75: NO CONTESTA | P75: =TRIM(BD_LilyaEspinoza[[#This Row],[CONTACTO II]]) -> NO CONTESTA
B76: EDDY RIVERA (CARRERA DE DERECHO) | C76: 51954168212 | D76: eddyriv0105@gmail.com | G76: PSICOLOGIA | H76: PAUTA DIGITAL | I76: SURQUILLO | J76: 2025-II | K76: Open Day 1 | L76: Open Day 1 | N76: NO CONTESTA | O76: NO CONTESTA | P76: =TRIM(BD_LilyaEspinoza[[#This Row],[CONTACTO II]]) -> NO CONTESTA
A77: 41428177. | B77: Kelly Vanessa Vilela Lopez. | C77: 51983458274 | D77: marina_0682@hotmail.com | G77: PSICOLOGIA | H77: PAUTA DIGITAL | I77: SURQUILLO | J77: 2025-II | K77: Open Day 1 | L77: Open Day 1 | N77: MOSTRÓ INTERÉS | O77: MOSTRÓ INTERÉS | P77: =TRIM(BD_LilyaEspinoza[[#This Row],[CONTACTO II]]) -> MOSTRÓ INTERÉS
A78: 47621438 | B78: Mayte Alcalde Ochoa | C78: 51 922 754 392 | D78: marianarodriguez261292@gmail.com | G78: TURISMO | H78: PAUTA DIGITAL | I78: SURQUILLO | J78: 2025-II | K78: Open Day 1 | L78: Open Day 1 | N78: SE ENVIÓ INFORMACIÓN | O78: SE ENVIÓ INFORMACIÓN | P78: =TRIM(BD_LilyaEspinoza[[#This Row],[CONTACTO II]]) -> SE ENVIÓ INFORMACIÓN
A79: 74280256 | B79: Yharit Grecia Arrunategui Heredia | C79: 51924124250 | D79: Grecia8078@gmail.com | G79: PSICOLOGIA | H79: PAUTA DIGITAL | I79: SURQUILLO | J79: 2025-II | K79: Open Day 1 | L79: Open Day 1 | N79: MOSTRÓ INTERÉS | O79: MOSTRÓ INTERÉS | P79: =TRIM(BD_LilyaEspinoza[[#This Row],[CONTACTO II]]) -> MOSTRÓ INTERÉS
A80: 71686044 | B80: Fabiana Ruth Zuleika Yataco Cabada | C80: 977978588 | D80: Fabianayataco@gmail.com | G80: PSICOLOGIA | H80: PAUTA DIGITAL | I80: SURQUILLO | J80: 2025-II | K80: Open Day 1 | L80: Open Day 1 | N80: MOSTRÓ INTERÉS | O80: MOSTRÓ INTERÉS | P80: =TRIM(BD_LilyaEspinoza[[#This Row],[CONTACTO II]]) -> MOSTRÓ INTERÉS
B81: Dayan QA | C81: 51 992 192 958 | D81: dayannicoleqalccamari@gmail.com | G81: TURISMO | H81: PAUTA DIGITAL | I81: SURQUILLO | J81: 2025-II | K81: Open Day 1 | L81: Open Day 1 | N81: NO CONTESTA | P81: =TRIM(BD_LilyaEspinoza[[#This Row],[CONTACTO II]])
B82: Nicoll Cisneros | C82: 51902175804 | D82: nicolcisneroscajacuri78@gmail.com | G82: TURISMO | H82: PAUTA DIGITAL | I82: SURQUILLO | J82: 2025-II | K82: Open Day 1 | L82: Open Day 1 | N82: NO CONTESTA | P82: =TRIM(BD_LilyaEspinoza[[#This Row],[CONTACTO II]])
B83: ximena | C83: 51954649999 | D83: dontgiveup4302@hotmail.com | G83: TURISMO | H83: PAUTA DIGITAL | I83: SURQUILLO | J83: 2025-II | K83: Open Day 1 | L83: Open Day 1 | N83: NO CONTESTA | P83: =TRIM(BD_LilyaEspinoza[[#This Row],[CONTACTO II]])
B84: wii.na | C84: 51910738927 | D84: nahomypenamiranda@gmail.com | G84: TURISMO | H84: PAUTA DIGITAL | I84: SURQUILLO | J84: 2025-II | K84: Open Day 1 | L84: Open Day 1 | N84: NO CONTESTA | P84: =TRIM(BD_LilyaEspinoza[[#This Row],[CONTACTO II]])
B85: Tracy Fajardo | C85: 51952168081 | D85: tracyfajardo2603@gmail.com | G85: PSICOLOGIA | H85: PAUTA DIGITAL | I85: SURQUILLO | J85: 2025-II | K85: Open Day 1 | L85: Open Day 1 | N85: NO CONTESTA | O85: NO CONTESTA | P85: =TRIM(BD_LilyaEspinoza[[#This Row],[CONTACTO II]]) -> NO CONTESTA
B86: Alexandro Gonzales Mendoza | C86: 51990713585 | D86: ghmbusiness@gmail.com | G86: COMUNICACIONES | H86: PAUTA DIGITAL | I86: SURQUILLO | J86: 2025-II | K86: Open Day 1 | L86: Open Day 1 | N86: INCONTACTABLE | O86: INCONTACTABLE | P86: =TRIM(BD_LilyaEspinoza[[#This Row],[CONTACTO II]]) -> INCONTACTABLE
B87: Zuliana Santos | C87: 51957148465 | D87: anthuane7380@hotmail.com | G87: COMUNICACIONES | H87: PAUTA DIGITAL | I87: SURQUILLO | J87: 2025-II | K87: Open Day 1 | L87: Open Day 1 | N87: NO CONTESTA | O87: NO CONTESTA | P87: =TRIM(BD_LilyaEspinoza[[#This Row],[CONTACTO II]]) -> NO CONTESTA
B88: Liseth Lx | C88: 51944540238 | D88: rodriguezhuayllayoselin@gmail.com | G88: TURISMO | H88: PAUTA DIGITAL | I88: SURQUILLO | J88: 2025-II | K88: Open Day 1 | L88: Open Day 1 | N88: NO CONTESTA | O88: NO CONTESTA | P88: =TRIM(BD_LilyaEspinoza[[#This Row],[CONTACTO II]]) -> NO CONTESTA
B89: Zahara | C89: 51967074202 | D89: louderthanbombsss3012@gmail.com | G89: TURISMO | H89: PAUTA DIGITAL | I89: SURQUILLO | J89: 2025-II | K89: Open Day 1 | L89: Open Day 1 | N89: NO CONTESTA | O89: NO CONTESTA | P89: =TRIM(BD_LilyaEspinoza[[#This Row],[CONTACTO II]]) -> NO CONTESTA
B90: Adriana Arias Giuria | C90: 51994359025 | D90: gino.arias@hotmail.com | G90: COMUNICACIONES | H90: PAUTA DIGITAL | I90: SURQUILLO | J90: 2025-II | K90: Open Day 1 | L90: Open Day 1 | N90: NO CONTESTA | O90: NO CONTESTA | P90: =TRIM(BD_LilyaEspinoza[[#This Row],[CONTACTO II]]) -> NO CONTESTA
B91: CIELO 1 | C91: 51902501921 | D91: valdiviacarhuaspilar@gmail.com | G91: TURISMO | H91: PAUTA DIGITAL | I91: SURQUILLO | J91: 2025-II | K91: Open Day 1 | L91: Open Day 1 | N91: INCONTACTABLE | O91: NO CONTESTA | P91: =TRIM(BD_LilyaEspinoza[[#This Row],[CONTACTO II]]) -> NO CONTESTA
B92: 𝕷𝖚 𝕲𝖆𝖗𝖈í𝖆 | C92: 51986885866 | D92: violetagarcialayan@gmail.com | G92: TURISMO | H92: PAUTA DIGITAL | I92: SURQUILLO | J92: 2025-II | K92: Open Day 1 | L92: Open Day 1 | N92: SE ENVIÓ INFORMACIÓN | P92: =TRIM(BD_LilyaEspinoza[[#This Row],[CONTACTO II]])
B93: Alexandra Buleje Barcena | C93: 51936804007 | D93: alexandrabarcena1708@gmail.com | G93: COMUNICACIONES | H93: PAUTA DIGITAL | I93: SURQUILLO | J93: 2025-II | K93: Open Day 1 | L93: Open Day 1 | N93: SE ENVIÓ INFORMACIÓN | P93: =TRIM(BD_LilyaEspinoza[[#This Row],[CONTACTO II]])
B94: mafer | C94: 51982852529 | D94: mafersaq@gmail.com | G94: COMUNICACIONES | H94: PAUTA DIGITAL | I94: SURQUILLO | J94: 2025-II | K94: Open Day 1 | L94: Open Day 1 | N94: SE ENVIÓ INFORMACIÓN | P94: =TRIM(BD_LilyaEspinoza[[#This Row],[CONTACTO II]])
B95: Vanessa Valenzuela | C95: 51969400070 | D95: vanessita10@hotmail.com | G95: COMUNICACIONES | H95: PAUTA DIGITAL | I95: SURQUILLO | J95: 2025-II | K95: Open Day 1 | L95: Open Day 1 | N95: SE ENVIÓ INFORMACIÓN | P95: =TRIM(BD_LilyaEspinoza[[#This Row],[CONTACTO II]])
B96: Briseyda Airaldi | C96: 51982264219 | D96: kliana1826@hotmail.com | G96: PSICOLOGIA | H96: PAUTA DIGITAL | I96: SANTA ANITA | J96: 2025-II | K96: Open Day 1 | L96: Open Day 1 | N96: SE ENVIÓ INFORMACIÓN
B97: Jhade | C97: 51926252319 | D97: jhademacpherson@gmail.com | G97: TURISMO | H97: PAUTA DIGITAL | I97: SURQUILLO | J97: 2025-II | K97: Open Day 1 | L97: Open Day 1 | N97: NO CONTESTA | O97: NO CONTESTA | P97: =TRIM(BD_LilyaEspinoza[[#This Row],[CONTACTO II]]) -> NO CONTESTA
B98: Stephany ST | C98: 51927444301 | D98: stephanysulcatineo@gmail.com | G98: COMUNICACIONES | H98: PAUTA DIGITAL | I98: SURQUILLO | J98: 2025-II | K98: Open Day 1 | L98: Open Day 1 | N98: NO CONTESTA | O98: NO CONTESTA | P98: =TRIM(BD_LilyaEspinoza[[#This Row],[CONTACTO II]]) -> NO CONTESTA
B99: Jhadde Nicolle Rospigliosi Gutiérrez (ES DE AREQUIPA) | C99: 51903239763 | D99: jhadderispigliosi@gmail.com | G99: PSICOLOGIA | H99: PAUTA DIGITAL | I99: SURQUILLO | J99: 2025-II | K99: Open Day 1 | L99: Open Day 1 | N99: SELECCIONÓ OTRA UNIVERSIDAD | P99: =TRIM(BD_LilyaEspinoza[[#This Row],[CONTACTO II]])
A100: 70736357 | B100: Zarella Yamileth Flores Tito | C100: 981 388 008 | D100: talaxa1207@gmail.com | E100: UTP | F100: ORDINARIO | G100: TURISMO | H100: PAUTA DIGITAL | I100: SURQUILLO | J100: 2025-II | K100: Open Day 1 | L100: Open Day 1 | N100: NO CONTESTA | P100: =TRIM(BD_LilyaEspinoza[[#This Row],[CONTACTO II]])
...

Sheet BD|Sheyla P.
A1: DNI | B1: NOMBRES | C1: CELULAR | D1: CORREO | E1: COLEGIO DE PROCEDENCIA | F1: MODALIDAD | G1: ESCUELA | H1: ORIGEN | I1: SEDE | J1: SEMESTRE | K1: CAMPAÑA | L1: EVENTO | M1: FECHA DE INGRESO DE LEAD | N1: CONTACTO I | O1: CONTACTO II | P1: CONTACTO III | Q1: ¿PAGÓ DERECHO DE INSCRIPCIÓN? | R1: STATUS ACADÉMICO | S1: TIPO DE EXAMEN | T1: STATUS DE EXAMEN | U1: ENTREGA DE DOCUMENTOS | V1: OBSERVACION
A2: 71192234 | B2: Piero Eduardo Garibotto Cuervas | C2: 943274989 | G2: PSICOLOGIA | L2: Open Day 3 | M2: 45880
A3: 74919051 | B3: Carlos Rubén Gutiérrez Silva | C3: 947764639 | L3: Open Day 3 | M3: 45880 | N3: MOSTRÓ INTERÉS | O3: MOSTRÓ INTERÉS | P3: SI CONFIRMÓ PARA EL EVENTO | Q3: NO - VIRTUAL | R3: INSCRITO | S3: VIRTUAL | T3: RENDIRA VIRTUAL | U3: PENDIENTE TODO | V3: examen agendado
C4: 973 814 991 | E4: 2da carrera | G4: TURISMO | L4: Open Day 3 | M4: 45880 | N4: MOSTRÓ INTERÉS | O4: MOSTRÓ INTERÉS | P4: MOSTRÓ INTERÉS
B5: AMBULAY LOPEZ JAEL | C5: 932340545 | G5: PSICOLOGIA | H5: VISITA A COLEGIOS | L5: Open Day 3 | M5: 45880 | N5: SE ENVIÓ INFORMACIÓN
A6: 61454141 | B6: GUZMAN FLORES JOAQUIN ALFONSO | C6: 920691058 | G6: TURISMO | H6: VISITA A COLEGIOS | L6: Open Day 3 | M6: 45880 | N6: SE ENVIÓ INFORMACIÓN
A7: 72062571 | B7: QUEVEDO AYARZA SOFIA | C7: 986694205 | G7: PSICOLOGIA | H7: VISITA A COLEGIOS | L7: Open Day 3 | M7: 45880 | N7: SE ENVIÓ INFORMACIÓN | O7: MOSTRÓ INTERÉS | P7: SI CONFIRMÓ PARA EL EVENTO | V7: primera opc. derecho
B8: Enrique | C8: 931 277 290 | L8: Open Day 3 | M8: 45880 | N8: SE ENVIÓ INFORMACIÓN
A9: 60934639 | B9: Tadeo Chaupis Acevedo | C9: 991279767 | D9: cyntty3@hotmail.com | F9: ORDINARIO | G9: PSICOLOGIA | H9: PAUTA DIGITAL | L9: Open Day 3 | M9: 45877 | N9: MOSTRÓ INTERÉS | O9: MOSTRÓ INTERÉS | P9: MOSTRÓ INTERÉS | Q9: NO - VIRTUAL | R9: INSCRITO | S9: VIRTUAL | T9: RENDIRA VIRTUAL | U9: PENDIENTE TODO | V9: examen agendado
A10: 73185903 | B10: Danitza Díaz | C10: 951 077 597 | G10: PSICOLOGIA | H10: COUNTER | L10: Open Day 3 | M10: 45876 | N10: MOSTRÓ INTERÉS | O10: MOSTRÓ INTERÉS | P10: SI CONFIRMÓ PARA EL EVENTO
A11: 61330183 | B11: Fiorella Herrera García | C11: 968042118 | G11: COMUNICACIONES | H11: WEB | L11: Open Day 3 | M11: 45877 | N11: SE ENVIÓ INFORMACIÓN
A12: 72591161 | B12: ROJAS CALLAHUI KENDRA NICOLE | C12: 908502802 | G12: PSICOLOGIA | H12: COUNTER | L12: Open Day 3 | M12: 45876 | N12: MOSTRÓ INTERÉS | O12: MOSTRÓ INTERÉS | P12: MOSTRÓ INTERÉS | Q12: NO - VIRTUAL | R12: ADMITIDO | S12: VIRTUAL | T12: RINDIO VIRTUAL | U12: PENDIENTE TODO
A13: 73153352 | B13: Angelina Milagros Chavez Lino | C13: 904386445 | G13: COMUNICACIONES | H13: COUNTER | L13: Open Day 3 | M13: 45876 | N13: MOSTRÓ INTERÉS | O13: MOSTRÓ INTERÉS | P13: SI CONFIRMÓ PARA EL EVENTO | V13: dio examen en jpckey
A14: 61507953 | B14: JUAN MANUEL DEL AGUILA TELLO | C14: 972 121 263 | G14: TURISMO | H14: WEB | L14: Open Day 3 | M14: 45874 | N14: SE ENVIÓ INFORMACIÓN | O14: NO HUBO PROGRESO | P14: NO HUBO PROGRESO | V14: no es de lima. llega en oct
A15: 61179579 | B15: Luciana Macarena Campos Luque | C15: 918 536 943 | F15: ORDINARIO | L15: Open Day 3 | M15: 45874 | N15: SE ENVIÓ INFORMACIÓN | O15: MOSTRÓ INTERÉS | P15: MOSTRÓ INTERÉS
C16: 973 814 991 | G16: TURISMO | H16: COUNTER | L16: Open Day 3 | M16: 45870 | N16: SE ENVIÓ INFORMACIÓN | O16: NO CONTESTA
A17: 61355150 | B17: Carmen Lucia Domínguez Chávez | C17: 918134943 | F17: CEA | G17: PSICOLOGIA | H17: PAUTA DIGITAL | I17: SURQUILLO | L17: Open Day 3 | M17: 45870 | N17: MOSTRÓ INTERÉS | O17: MOSTRÓ INTERÉS | P17: MOSTRÓ INTERÉS | Q17: NO - VIRTUAL | R17: ADMITIDO | S17: VIRTUAL | T17: RINDIO VIRTUAL | U17: PENDIENTE TODO
A18: 72839888 | B18: Ariana Antezana | C18: 902298310 | F18: ORDINARIO | G18: PSICOLOGIA | H18: COUNTER | I18: SURQUILLO | L18: Open Day 3 | M18: 45870 | N18: SE ENVIÓ INFORMACIÓN | O18: MOSTRÓ INTERÉS
A19: 71364379 | B19: Luciana Herrada Blanco | C19: 963067320 | F19: ORDINARIO | G19: PSICOLOGIA | H19: COUNTER | L19: Open Day 3 | M19: 45870 | N19: MOSTRÓ INTERÉS | O19: MOSTRÓ INTERÉS | P19: SI CONFIRMÓ PARA EL EVENTO
A20: 73280134 | B20: Regina Sofía Alcántara Cueva | C20: 934629374 | D20: karinacueva0@gmail.com | F20: PRIMERA ALTERNATIVA | G20: PSICOLOGIA | H20: COUNTER | I20: COMAS | L20: Open Day 3 | M20: 45869 | N20: MOSTRÓ INTERÉS | O20: MOSTRÓ INTERÉS | P20: SI CONFIRMÓ PARA EL EVENTO | Q20: NO - VIRTUAL | R20: ADMITIDO | S20: VIRTUAL | T20: RINDIO VIRTUAL | U20: PENDIENTE TODO
A21: 71155955 | B21: Alex Fernando Gonzales Alvarado | C21: 913148015 | D21: pedritogonzales80@gmail.com | E21: 973 814 991 | G21: PSICOLOGIA | H21: COUNTER | L21: Open Day 3 | M21: 45869 | N21: SE ENVIÓ INFORMACIÓN | O21: NO CONTESTA
C22: 983 323 640 | G22: PSICOLOGIA | L22: Taller Vivencial 3 | N22: SE ENVIÓ INFORMACIÓN
B23: Richard Josue Parra Muñoz | C23: 952826055 | F23: ORDINARIO | G23: COMUNICACIONES | H23: COUNTER | N23: SE ENVIÓ INFORMACIÓN
A25: 61845695 | B25: camila crisanto basurto | C25: 979439393 | G25: PSICOLOGIA | L25: Taller Vivencial 3 | N25: INCONTACTABLE | O25: INCONTACTABLE | P25: INCONTACTABLE
A26: 61506496 | B26: margiori cabrera adrian | C26: 954251630 | F26: PA | G26: PSICOLOGIA | H26: COUNTER | L26: Taller Vivencial 3 | N26: MOSTRÓ INTERÉS | O26: MOSTRÓ INTERÉS | P26: MOSTRÓ INTERÉS | Q26: NO - VIRTUAL | R26: INSCRITO | S26: VIRTUAL | T26: RENDIRA VIRTUAL | U26: PENDIENTE TODO | V26: Generado en sta anita con quivocacion, desea surquillo
A27: 72068503 | B27: Renata Cristina Chávez Musayon | C27: 945464773 | D27: renatachavezmusayon@gmail.com | G27: COMUNICACIONES | H27: PAUTA DIGITAL | L27: Taller Vivencial 3 | N27: SE ENVIÓ INFORMACIÓN
A28: 70099277 | B28: jonny ashley quezada barboza | C28: 903176498 | F28: ORDINARIO | G28: PSICOLOGIA | H28: COUNTER | I28: LIMA | M28: 45853 | N28: =TRIM(BD_PyaPinto[[#This Row],[CONTACTO II]]) -> SI CONFIRMÓ PARA EL EVENTO | O28: =TRIM(BD_PyaPinto[[#This Row],[CONTACTO II]]) -> SI CONFIRMÓ PARA EL EVENTO | Q28: NO - VIRTUAL | R28: ADMITIDO | S28: VIRTUAL | T28: RINDIO VIRTUAL | U28: PENDIENTE TODO
A29: 42375540 | B29: Marco Antonio Jesus Avila Chavez | C29: 993165586 | F29: ORDINARIO | G29: COMUNICACIONES | H29: COUNTER | L29: Taller Vivencial 3 | M29: 45853 | N29: =TRIM(BD_PyaPinto[[#This Row],[CONTACTO II]]) -> NO CONTESTA | O29: =TRIM(BD_PyaPinto[[#This Row],[CONTACTO II]]) -> NO CONTESTA
A30: 70731653 | B30: Adriano Sanchez Muñoz | C30: 948520404 | E30: terminé_el_colegio | F30: ORDINARIO | G30: COMUNICACIONES | H30: COUNTER | L30: Taller Vivencial 3 | M30: 45852 | N30: =TRIM(BD_PyaPinto[[#This Row],[CONTACTO II]]) -> MOSTRÓ INTERÉS | O30: =TRIM(BD_PyaPinto[[#This Row],[CONTACTO II]]) -> MOSTRÓ INTERÉS | Q30: NO - VIRTUAL | R30: ADMITIDO | S30: VIRTUAL | T30: RINDIO VIRTUAL | U30: PENDIENTE TODO
B31: LUANA FERNANDA CORONEL ARIAS | C31: 983139506 | D31: 4TO SEC | H31: EVENTO PRESENCIAL | L31: Taller Vivencial 3 | M31: 45849 | N31: SE ENVIÓ INFORMACIÓN
B32: MARCO ANTONIO VELARDE SANTA CRUZ | C32: 999341285 | H32: EVENTO PRESENCIAL | J32: 2026-I | M32: 45849 | N32: INCONTACTABLE
A33: 61472194 | B33: PINTO YACTAYO LUCIANO ANDRE | C33: 966167041 | F33: CEA | G33: COMUNICACIONES | H33: COUNTER | L33: Taller Vivencial 3 | M33: 45848 | N33: MOSTRÓ INTERÉS | O33: MOSTRÓ INTERÉS | Q33: NO - VIRTUAL | R33: ADMITIDO | S33: VIRTUAL | T33: RINDIO VIRTUAL | U33: PENDIENTE TODO
A34: 72269404 | B34: Anabel Geraldine Magallanes Vega | C34: 953352104 | F34: ORDINARIO | G34: PSICOLOGIA | H34: COUNTER | I34: LIMA | M34: 45848 | N34: MOSTRÓ INTERÉS | O34: MOSTRÓ INTERÉS | Q34: NO - VIRTUAL | R34: ADMITIDO | S34: VIRTUAL | T34: RINDIO VIRTUAL | U34: PENDIENTE TODO
A35: 0.8195499 | B35: Daniel Cornejo Marsano | C35: 935177607 | G35: COMUNICACIONES | H35: COUNTER | J35: 2026-I | L35: Taller Vivencial 3 | N35: MOSTRÓ INTERÉS
A36: 72704004 | B36: Claudia Ximena Salazar Herrera | C36: 960933725 | D36: clau_xime_01@hotmail.com | G36: COMUNICACIONES | H36: PAUTA DIGITAL | J36: 2025-II | K36: Taller Vivencial 2 | L36: Taller Vivencial 3 | N36: NO CONTESTA
A37: 77524572 | B37: April Mill Julca yaranga | C37: 954741421 | D37: apriljulca7@gmail.com | F37: ORDINARIO | G37: COMUNICACIONES | H37: BASE ANTIGUA | I37: SURQUILLO | J37: 2025-II | L37: Taller Vivencial 3 | N37: MOSTRÓ INTERÉS | O37: MOSTRÓ INTERÉS | Q37: NO- VIRTUAL | R37: ADMITIDO | S37: VIRTUAL | T37: RINDIO VIRTUAL | U37: ENTREGADO-COMPLETO
A38: 77804413 | B38: Antonella Ramos Lopez | C38: 944549724 | D38: anto_754@hotmail.com | F38: ORDINARIO | G38: COMUNICACIONES | H38: BASE ANTIGUA | I38: SURQUILLO | J38: 2025-II | L38: Taller Vivencial 3 | N38: MOSTRÓ INTERÉS | O38: MOSTRÓ INTERÉS | Q38: SÍ- EXAMEN PRESENCIAL | R38: INSCRITO | S38: PRESENCIAL | T38: RENDIRÁ PRESENCIAL | U38: PENDIENTE TODO
A39: 7525972 | B39: Eliana Espejo Romero | C39: 951233434 | D39: zoilipe17@gmail.com | G39: COMUNICACIONES | H39: EVENTO PRESENCIAL | J39: 2025-II | L39: Taller Vivencial 3 | N39: NO CONTESTA
A40: 72421499 | B40: Angie Darlene Panta Rodriguez(mamá) | C40: 934092100 | D40: angie369momo@gmail.com | G40: COMUNICACIONES | H40: EVENTO PRESENCIAL | J40: 2025-II | L40: Taller Vivencial 3 | N40: NO CONTESTA
B41: edu(INTERES POR OTRA DERECHO) | C41: 918826973 | D41: reydelmar2026@gmail.com | F41: TRASLADO EXTERNO | G41: COMUNICACIONES | H41: PAUTA DIGITAL | I41: instituto | J41: 2025-II | L41: Taller Vivencial 3 | N41: NO CONTESTA
A42: 61096345 | B42: Adriana Otoya Bejar | C42: 966488927 | D42: otoya271131@gmail.com | F42: tmb turismo | G42: COMUNICACIONES | H42: PAUTA DIGITAL | J42: 2025-II | K42: Open Day 2 | L42: Taller Vivencial 3 | N42: MOSTRÓ INTERÉS
A43: 72818818 | B43: Daniella <3 | C43: 993502489 | D43: daniella.guerra.sanchez@gmail.com | G43: COMUNICACIONES | H43: PAUTA DIGITAL | J43: 2025-II | K43: Open Day 2 | L43: Taller Vivencial 3 | N43: MOSTRÓ INTERÉS
A44: 73397513 | B44: Anghely Olivares Yalaupari | C44: 981853956 | D44: noemi.yalaupari@gmail.com | G44: COMUNICACIONES | H44: PAUTA DIGITAL | J44: 2025-II | K44: Taller Vivencial 2 | L44: Taller Vivencial 3 | N44: MOSTRÓ INTERÉS
A45: 70533390 | B45: Nicol Subilete | C45: 924 276 209 | D45: tanianicolsubilete@gmail.com | G45: COMUNICACIONES | H45: PAUTA DIGITAL | J45: 2025-II | K45: Open Day 2 | L45: Taller Vivencial 3 | N45: MOSTRÓ INTERÉS
A46: 60842571 | B46: YAURI MALLMA EMERSON JHORDANY_x000D_ | C46: 922605244 | D46: emersonmor50@gmail.com | F46: ORDINARIO | G46: COMUNICACIONES | H46: PAUTA DIGITAL | J46: 2025-II | K46: Open Day 2 | L46: Taller Vivencial 3 | N46: MOSTRÓ INTERÉS | O46: MOSTRÓ INTERÉS | Q46: NO- VIRTUAL | R46: ADMITIDO | S46: VIRTUAL | T46: RINDIO VIRTUAL | U46: PENDIENTE TODO
A47: 73285825 | B47: Ariana | C47: 996191365 | D47: ari14aquino@gmail.com | G47: COMUNICACIONES | H47: PAUTA DIGITAL | J47: 2025-II | K47: Open Day 2 | L47: Taller Vivencial 3 | N47: MOSTRÓ INTERÉS | O47: NO CONTESTA
A48: 61186869 | B48: Janice Zarela Terrones Cruz | C48: 939643384 | D48: janicezarelate10@gmail.com | G48: COMUNICACIONES | H48: PAUTA DIGITAL | J48: 2025-II | K48: Open Day 2 | L48: Taller Vivencial 3 | N48: MOSTRÓ INTERÉS | O48: MOSTRÓ INTERÉS | Q48: NO- VIRTUAL | R48: ADMITIDO | S48: VIRTUAL | T48: RINDIO VIRTUAL | U48: PENDIENTE TODO
A49: 61170857 | B49: Lizaida Castañeda - meli - lead repetido | C49: 942 091 617 | D49: lizaicr14@gmail.com | G49: COMUNICACIONES | H49: PAUTA DIGITAL | J49: 2025-II | K49: Open Day 2 | L49: Taller Vivencial 3 | N49: MOSTRÓ INTERÉS | O49: MOSTRÓ INTERÉS
A50: 2879220 | B50: Carolina Caro | C50: 991887301 | D50: Carolina.silva@gruposcp.com | G50: COMUNICACIONES | H50: PAUTA DIGITAL | J50: 2025-II | K50: Open Day 2 | L50: Taller Vivencial 3 | N50: MOSTRÓ INTERÉS | O50: MOSTRÓ INTERÉS
A51: 74432603 | B51: Christian giovanni Orrego Telles | C51: 960 904 896 | F51: TRASLADO EXTERNO | G51: COMUNICACIONES | H51: PAUTA DIGITAL | J51: 2025-II | L51: Taller Vivencial 3 | N51: MOSTRÓ INTERÉS | O51: MOSTRÓ INTERÉS
A52: 10699425 | B52: Ketty Véliz Mayta | C52: 982056458 | G52: COMUNICACIONES | H52: PAUTA DIGITAL | J52: 2025-II | K52: Open Day 2 | L52: Taller Vivencial 3 | N52: MOSTRÓ INTERÉS | O52: MOSTRÓ INTERÉS
A53: 62025601 | B53: Mathias Sebastian Levano Valladares (BD 2026-1) | C53: 913952293 | D53: mvalladaresc2017@gmail.com | G53: COMUNICACIONES | H53: PAUTA DIGITAL | J53: 2025-II | K53: Open Day 2 | L53: Taller Vivencial 3 | N53: MOSTRÓ INTERÉS | O53: MOSTRÓ INTERÉS
A54: 61252778 | B54: Valeria Alejandra Cruzado Molina | C54: 924 1133 09 | D54: cruzadlmolina17@gmail.com | F54: ORDINARIO | G54: PSICOLOGIA | H54: BASE ANTIGUA | I54: SURQUILLO | J54: 2025-II | L54: Taller Vivencial 3 | N54: MOSTRÓ INTERÉS | O54: MOSTRÓ INTERÉS | Q54: NO- VIRTUAL | R54: ADMITIDO | S54: VIRTUAL | T54: RINDIO VIRTUAL | U54: ENTREGADO-COMPLETO
A55: 76092820 | B55: Diana Antonella Serrano Pardo | C55: 931 988 810 | D55: dianaserranopardo09@gmail.com | F55: ORDINARIO | G55: PSICOLOGIA | H55: BASE ANTIGUA | I55: SURQUILLO | J55: 2025-II | L55: Taller Vivencial 3 | N55: MOSTRÓ INTERÉS | O55: MOSTRÓ INTERÉS | Q55: NO- VIRTUAL | R55: ADMITIDO | S55: VIRTUAL | T55: RINDIO VIRTUAL | U55: PENDIENTE TODO
A56: 72344435 | B56: Yadhira Torres Mejia | C56: 987 555 184 | E56: Trilce VES | G56: PSICOLOGIA | H56: PAUTA DIGITAL | J56: 2025-II | L56: Taller Vivencial 3 | N56: MOSTRÓ INTERÉS | O56: SE ENVIO INFORMACIÓN
B57: Matilde Juanita Espinoza Donaire | C57: 963696884 | D57: myriam.donaire.c@gmail.com | E57: SACO OLIVEROS | G57: PSICOLOGIA | H57: PAUTA DIGITAL | J57: 2025-II | K57: Open Day 1 | L57: Taller Vivencial 3 | N57: NO CONTESTA | O57: MOSTRÓ INTERÉS
A58: CE 002709301 | B58: Sofia Valentina Antequera Sifontes | C58: 51953745767 | D58: sofivalentinasifontes@gmail.com | E58: NUESTRA SEÑORA DE LA LUZ | G58: PSICOLOGIA | H58: PAUTA DIGITAL | J58: 2025-II | K58: Open Day 1 | L58: Taller Vivencial 3 | N58: NO CONTESTA | O58: MOSTRÓ INTERÉS
A59: 74442562 | B59: Romi mendoza | C59: 51982909774 | D59: mendozsmontes@gmail.com | G59: PSICOLOGIA | H59: PAUTA DIGITAL | J59: 2025-II | K59: Open Day 1 | L59: Taller Vivencial 3 | N59: MOSTRÓ INTERÉS
B60: Marisol Guillén | C60: 51996950250 | D60: mg9757666@gmail.com | G60: PSICOLOGIA | H60: PAUTA DIGITAL | J60: 2025-II | K60: Open Day 1 | L60: Taller Vivencial 3 | N60: MOSTRÓ INTERÉS | O60: MOSTRÓ INTERÉS
A61: 60786953 | B61: Jhannela Rojas | C61: 51913453729 | D61: rojassalinasj3087ccf@gmail.com | E61: TERMINÉ EL COLEGIO | G61: PSICOLOGIA | H61: PAUTA DIGITAL | J61: 2025-II | K61: Open Day 1 | L61: Taller Vivencial 3 | N61: SE ENVIÓ INFORMACIÓN | O61: NO CONTESTA
A62: 70175375 | B62: CELESTE LAUREANO GRADOS | C62: 981 290 147 | G62: PSICOLOGIA | J62: 2025-II | L62: Taller Vivencial 3 | N62: MOSTRÓ INTERÉS
A63: 76313955 | B63: Jarumy Alarcon | C63: 51968804379 | D63: jarumyalarcon@gmail.com | E63: NO TIENE TECNICO | F63: COMPLEMENTACIÓN ACADÉMICA | G63: TURISMO | H63: PAUTA DIGITAL | J63: 2025-II | L63: Taller Vivencial 3 | N63: SE ENVIÓ INFORMACIÓN | O63: NO CONTESTA
A64: 73158735 | B64: Luana Reyes | C64: +51 974 088 973 | D64: luanareyes681@gmail.com | G64: COMUNICACIONES | H64: PAUTA DIGITAL | J64: 2025-II | K64: Open Day 2 | L64: Taller Vivencial 3 | N64: MOSTRÓ INTERÉS
A65: 74704769 | B65: Jesus Alberto Suarez Torres | C65: 954524004 | F65: TRASLADO EXTERNO | G65: COMUNICACIONES | H65: COUNTER | J65: 2025-II | L65: Taller Vivencial 3 | N65: MOSTRÓ INTERÉS | O65: MOSTRÓ INTERÉS | Q65: SÍ- EXAMEN PRESENCIAL | R65: NO INSCRITO | S65: PRESENCIAL | T65: RENDIRÁ PRESENCIAL | U65: PENDIENTE TODO
A66: 46430107 | B66: Ariana Nayeli | C66: 51935450694 | D66: shakyme_2015@hotmal.com | G66: COMUNICACIONES | H66: PAUTA DIGITAL | J66: 2025-II | K66: Taller Vivencial 2 | L66: Taller Vivencial 3 | N66: MOSTRÓ INTERÉS
A67: 46753848 | B67: Kelly Briceño Gomez | C67: 51947785920 | D67: key.bg4@gmail.com | E67: TERMINÉ EL COLEGIO | G67: PSICOLOGIA | H67: PAUTA DIGITAL | J67: 2025-II | L67: Taller Vivencial 3 | N67: SE ENVIÓ INFORMACIÓN | O67: MOSTRÓ INTERÉS
A68: 73163569 | B68: Vania Peralta | C68: 51933699218 | D68: vaniaperalta37@gmail.com | F68: 5to | G68: PSICOLOGIA | H68: PAUTA DIGITAL | J68: 2025-II | K68: Open Day 2 | L68: Taller Vivencial 3 | N68: MOSTRÓ INTERÉS
A69: 43355212 | B69: Alexandra Pamela Chávez Herrera | C69: 51902428904 | D69: alexandra.chhe@gmail.com | E69: TERMINÉ EL COLEGIO | F69: EXAMEN DIGITAL | G69: PSICOLOGIA | H69: PAUTA DIGITAL | J69: 2025-II | L69: Taller Vivencial 3 | N69: SE ENVIÓ INFORMACIÓN | O69: NO CONTESTA
A70: 77381925 | B70: Juan Pablo Ubillus Olano | C70: 51902719043 | D70: jpubilluso@gmail.com | F70: ORDINARIO | G70: COMUNICACIONES | H70: PAUTA DIGITAL | J70: 2025-II | K70: Open Day 2 | L70: Taller Vivencial 3 | N70: MOSTRÓ INTERÉS | O70: MOSTRÓ INTERÉS | Q70: NO- VIRTUAL | R70: ADMITIDO | S70: VIRTUAL | T70: RINDIO VIRTUAL | U70: PENDIENTE TODO | V70: PAGO MATRICULA
A71: 72066492 | B71: Romina Saenz / Lilya | C71: 51986665217 | D71: rominasaenzv16@gmail.com | G71: COMUNICACIONES | H71: PAUTA DIGITAL | J71: 2025-II | K71: Open Day 2 | L71: Taller Vivencial 3 | N71: MOSTRÓ INTERÉS
A72: 76832880 | B72: Miguel Alejandro Gálvez Dueñas | C72: 51920206348 | D72: mgalvez0603@gmail.com | G72: PSICOLOGIA | H72: PAUTA DIGITAL | J72: 2025-II | K72: Taller Vivencial 2 | L72: Taller Vivencial 3 | N72: NO CONTESTA
A73: 61755187 | B73: Luana Nazareth Albarrán Rojas | C73: 51913474004 | D73: lunalbarran24@gmail.com | G73: PSICOLOGIA | H73: PAUTA DIGITAL | J73: 2025-II | K73: Taller Vivencial 2 | L73: Taller Vivencial 3 | N73: MOSTRÓ INTERÉS | O73: MOSTRÓ INTERÉS
A74: 25847119 | B74: Carmen Villena | C74: 51989762229 | D74: richard_gomezc@hotmail.com | G74: PSICOLOGIA | H74: PAUTA DIGITAL | J74: 2025-II | K74: Taller Vivencial 2 | L74: Taller Vivencial 3 | N74: NO CONTESTA
A75: 93999570 | B75: Kiara | C75: 51939995701 | D75: lunakawai456@gmail.com | G75: COMUNICACIONES | H75: PAUTA DIGITAL | J75: 2025-II | L75: Taller Vivencial 3 | N75: MOSTRÓ INTERÉS
A76: 61099400 | B76: Kamil Paola Rubina Weill | C76: 957289234 | D76: kamil.rubina.weill13@gmail.com | F76: ORDINARIO | G76: COMUNICACIONES | H76: BASE ANTIGUA | I76: SURQUILLO | J76: 2025-II | L76: Taller Vivencial 3 | N76: MOSTRÓ INTERÉS | O76: MOSTRÓ INTERÉS | Q76: SÍ- EXAMEN PRESENCIAL | R76: ADMITIDO | S76: PRESENCIAL | T76: RINDIÓ PRESENCIAL | U76: ENTREGADO-COMPLETO
A77: 70697633 | B77: Merializabet Denis Cardoso Medrano | C77: 976281888 | D77: medranodenis2020@gmail.com | F77: TERCIO SUPERIOR | G77: COMUNICACIONES | H77: BASE ANTIGUA | I77: SURQUILLO | J77: 2025-II | L77: Taller Vivencial 3 | N77: MOSTRÓ INTERÉS | O77: MOSTRÓ INTERÉS | Q77: NO- VIRTUAL | R77: ADMITIDO | S77: VIRTUAL | T77: RINDIO VIRTUAL | U77: ENTREGADO-COMPLETO
A78: 61313698 | B78: Fiorela Giovanna Rosales Gamio | C78: 992 908 611 | F78: ORDINARIO | G78: PSICOLOGIA | H78: COUNTER | I78: SURQUILLO | J78: 2025-II | L78: Taller Vivencial 3 | N78: MOSTRÓ INTERÉS | O78: MOSTRÓ INTERÉS | Q78: NO- VIRTUAL | R78: ADMITIDO | S78: VIRTUAL | T78: RINDIO VIRTUAL | U78: ENTREGADO-COMPLETO
A79: 61187126 | B79: Nathalia Rocio Alayza Arca | C79: 979042178 | D79: nathi1608@gmail.com | F79: ORDINARIO | G79: COMUNICACIONES | H79: BASE ANTIGUA | I79: SURQUILLO | J79: 2025-II | L79: Taller Vivencial 3 | N79: MOSTRÓ INTERÉS | O79: MOSTRÓ INTERÉS | Q79: NO- VIRTUAL | R79: ADMITIDO | S79: VIRTUAL | T79: RINDIO VIRTUAL | U79: PENDIENTE TODO | V79: ASISTE SABADO 19
A80: 61236483 | B80: Arely Marily Vargas Rosales | C80: 983313941 | D80: Cintyarosalesmora@gmail.com | F80: ORDINARIO | G80: PSICOLOGIA | H80: BASE ANTIGUA | I80: SURQUILLO | J80: 2025-II | L80: Taller Vivencial 3 | N80: MOSTRÓ INTERÉS | O80: MOSTRÓ INTERÉS | Q80: NO- VIRTUAL | R80: ADMITIDO | S80: VIRTUAL | T80: RINDIO VIRTUAL | U80: PENDIENTE TODO
B81: Bryan Carlos Ronquillo Zevallos | C81: 947392888 | F81: TRASLADO EXTERNO | G81: PSICOLOGIA | H81: COUNTER | J81: 2025-II | L81: Taller Vivencial 3 | N81: MOSTRÓ INTERÉS
A82: 74009635 | B82: Lia Samira Nuñez Sanchez | C82: 976459728 | D82: Liasami0727@gmail.com | F82: ORDINARIO | G82: PSICOLOGIA | H82: BASE ANTIGUA | I82: SURQUILLO | J82: 2025-II | L82: Taller Vivencial 3 | N82: MOSTRÓ INTERÉS | O82: MOSTRÓ INTERÉS | Q82: NO- VIRTUAL | R82: ADMITIDO | S82: VIRTUAL | T82: RINDIO VIRTUAL | U82: ENTREGADO-COMPLETO
A83: 62602341 | B83: Luna del Pilar Guerrero Macedo | C83: 990814082 | D83: lunadelpilargm@gmail.com | F83: ORDINARIO | G83: PSICOLOGIA | H83: BASE ANTIGUA | I83: SURQUILLO | J83: 2025-II | L83: Taller Vivencial 3 | N83: MOSTRÓ INTERÉS | O83: MOSTRÓ INTERÉS | Q83: NO- VIRTUAL | R83: ADMITIDO | S83: VIRTUAL | T83: RINDIO VIRTUAL | U83: ENTREGADO-COMPLETO
A84: 71857906 | B84: Nayely Rosalinda Huaman Huari | C84: 978 400 592 | D84: naye.ros22.12@gmail.com | F84: ORDINARIO | G84: PSICOLOGIA | H84: BASE ANTIGUA | I84: SANTA ANITA | J84: 2025-II | L84: Taller Vivencial 3 | N84: MOSTRÓ INTERÉS | O84: MOSTRÓ INTERÉS | Q84: NO- VIRTUAL | R84: ADMITIDO | S84: VIRTUAL | T84: RINDIO VIRTUAL | U84: ENTREGADO-COMPLETO
A85: 74311334 | B85: Harid Francesco Gianello Rosales | C85: 907642240 | D85: harid11032005@gmail.com | F85: ORDINARIO | G85: COMUNICACIONES | H85: BASE ANTIGUA | I85: SURQUILLO | J85: 2025-II | L85: Taller Vivencial 3 | N85: MOSTRÓ INTERÉS | O85: MOSTRÓ INTERÉS | Q85: NO- VIRTUAL | R85: ADMITIDO | S85: VIRTUAL | T85: RINDIO VIRTUAL | U85: ENTREGADO-COMPLETO
A86: 60819548 | B86: Genesis Miranda Huapaya Rojas | C86: 962702103 | F86: ORDINARIO | G86: COMUNICACIONES | H86: BASE ANTIGUA | I86: SURQUILLO | J86: 2025-II | L86: Taller Vivencial 3 | N86: MOSTRÓ INTERÉS | O86: MOSTRÓ INTERÉS | Q86: NO- VIRTUAL | R86: ADMITIDO | S86: VIRTUAL | T86: RINDIO VIRTUAL | U86: PENDIENTE TODO | V86: PAGO MATRICULA
A87: 72056188 | B87: Angie | C87: 51902495748 | D87: villanuevaguevaraangie@gmail.com | G87: PSICOLOGIA | H87: PAUTA DIGITAL | J87: 2025-II | K87: Open Day 2 | L87: Taller Vivencial 3 | N87: MOSTRÓ INTERÉS
A88: 76568567 | B88: Lady Xiomara Mendoza Laura | C88: 915385449 | D88: xiomimendozalaura@gmail.com | F88: TERCIO SUPERIOR | G88: PSICOLOGIA | H88: BASE ANTIGUA | I88: SANTA ANITA | J88: 2025-II | L88: Taller Vivencial 3 | N88: MOSTRÓ INTERÉS | O88: MOSTRÓ INTERÉS | Q88: NO- VIRTUAL | R88: ADMITIDO | S88: VIRTUAL | T88: RINDIO VIRTUAL | U88: ENTREGADO-COMPLETO
A89: 71673422 | B89: Adriana Lucía Balbin Orozco | C89: 978768982 | D89: adrianabalor@gmail.com | F89: ORDINARIO | G89: TURISMO | H89: BASE ANTIGUA | I89: SURQUILLO | J89: 2025-II | L89: Taller Vivencial 3 | N89: MOSTRÓ INTERÉS | O89: MOSTRÓ INTERÉS | Q89: NO- VIRTUAL | R89: ADMITIDO | S89: VIRTUAL | T89: RINDIO VIRTUAL | U89: ENTREGADO-COMPLETO
A90: 74915062 | B90: Iseth Xiomara Alderete Nuñez | C90: 927244049 | D90: alderetexiomara31@gmail.com | F90: ORDINARIO | G90: PSICOLOGIA | H90: BASE ANTIGUA | I90: SURQUILLO | J90: 2025-II | L90: Taller Vivencial 3 | N90: MOSTRÓ INTERÉS | O90: MOSTRÓ INTERÉS | Q90: NO- VIRTUAL | R90: ADMITIDO | S90: VIRTUAL | T90: RINDIO VIRTUAL | U90: PENDIENTE TODO
A91: 70460183 | B91: Sergio Israel Rivera Garcia | C91: 976 842 511 | D91: sergio.rivera.garcia2006@gmail.com | F91: TERCIO SUPERIOR | G91: COMUNICACIONES | H91: BASE ANTIGUA | I91: SURQUILLO | J91: 2025-II | L91: Taller Vivencial 3 | N91: MOSTRÓ INTERÉS | O91: MOSTRÓ INTERÉS | Q91: NO- VIRTUAL | R91: ADMITIDO | S91: VIRTUAL | T91: RINDIO VIRTUAL | U91: ENTREGADO-COMPLETO | V91: PAGO MATRICULA
A92: 60843273 | B92: Mathias Facundo Escriba Crisostomo | C92: 981 696 483 | D92: Escribamathias356@gmail.com | F92: TRASLADA INTERNO | G92: COMUNICACIONES | H92: BASE ANTIGUA | I92: SURQUILLO | J92: 2025-II | L92: Taller Vivencial 3 | N92: MOSTRÓ INTERÉS | O92: MOSTRÓ INTERÉS | Q92: SÍ- EXAMEN PRESENCIAL | R92: ADMITIDO | S92: PRESENCIAL | T92: RINDIÓ PRESENCIAL | U92: ENTREGADO-COMPLETO
A93: 61165845 | B93: Hillary Belen Valles Manrique | C93: 942492078 | F93: ORDINARIO | G93: PSICOLOGIA | H93: BASE ANTIGUA | I93: SANTA ANITA | J93: 2025-II | L93: Taller Vivencial 3 | N93: MOSTRÓ INTERÉS | O93: MOSTRÓ INTERÉS | Q93: NO- VIRTUAL | R93: ADMITIDO | S93: VIRTUAL | T93: RINDIO VIRTUAL | U93: PENDIENTE TODO
A94: 61313496 | B94: María Fernanda Narcizo Gutiérrez | C94: 966731176 | F94: ORDINARIO | G94: COMUNICACIONES | H94: BASE ANTIGUA | I94: SURQUILLO | J94: 2025-II | L94: Taller Vivencial 3 | N94: MOSTRÓ INTERÉS | O94: MOSTRÓ INTERÉS | Q94: NO- VIRTUAL | R94: ADMITIDO | S94: VIRTUAL | T94: RINDIO VIRTUAL | U94: PENDIENTE TODO | V94: PAGO MATRICULA
A95: 61252956 | B95: Christabella Maria Julia Vivanco Paredes | C95: 936868389 | F95: TERCIO SUPERIOR | G95: TURISMO | H95: COUNTER | I95: SURQUILLO | J95: 2025-II | L95: Taller Vivencial 3 | N95: MOSTRÓ INTERÉS | O95: MOSTRÓ INTERÉS | Q95: NO- VIRTUAL | R95: ADMITIDO | S95: VIRTUAL | T95: RINDIO VIRTUAL | U95: ENTREGADO-COMPLETO
A96: 70718402 | B96: Tatyana Danitsa Villalobos Laguna | C96: 982 562 230 | D96: andersonvillaloboslaguna@gmail.com | F96: TERCIO SUPERIOR | G96: COMUNICACIONES | H96: COUNTER | I96: SURQUILLO | J96: 2025-II | L96: Taller Vivencial 3 | N96: MOSTRÓ INTERÉS | O96: MOSTRÓ INTERÉS | Q96: NO- VIRTUAL | R96: ADMITIDO | S96: VIRTUAL | T96: RINDIO VIRTUAL | U96: ENTREGADO-COMPLETO
A97: 72480699 | B97: Valery Katherine Pinto Zedano | C97: 970563311 | D97: Valerypintozedano14@gmail.com | F97: ORDINARIO | G97: PSICOLOGIA | H97: BASE ANTIGUA | I97: SURQUILLO | J97: 2025-II | L97: Taller Vivencial 3 | N97: MOSTRÓ INTERÉS | O97: MOSTRÓ INTERÉS | Q97: NO- VIRTUAL | R97: ADMITIDO | S97: VIRTUAL | T97: RINDIO VIRTUAL | U97: PENDIENTE TODO
A98: 70590266 | B98: Maria Cóndor Urrutia | C98: 924199270 | D98: mihrimahyue228@gmail.com | F98: ORDINARIO | G98: PSICOLOGIA | H98: BASE ANTIGUA | I98: SANTA ANITA | J98: 2025-II | L98: Taller Vivencial 3 | N98: MOSTRÓ INTERÉS | O98: MOSTRÓ INTERÉS | Q98: NO- VIRTUAL | R98: INSCRITO | S98: VIRTUAL | T98: RINDIO VIRTUAL | U98: PENDIENTE TODO
A99: 61008521 | B99: Nayara Naomi Gonzales Moron | C99: 946 557 564 | D99: nayara19gonzales@gmail.com | F99: ORDINARIO | G99: PSICOLOGIA | H99: BASE ANTIGUA | I99: SANTA ANITA | J99: 2025-II | L99: Taller Vivencial 3 | N99: MOSTRÓ INTERÉS | O99: MOSTRÓ INTERÉS | Q99: NO- VIRTUAL | R99: ADMITIDO | S99: VIRTUAL | T99: RINDIO VIRTUAL | U99: ENTREGADO-COMPLETO
A100: 74961427 | B100: Jhon Hairo Moya Santiago | C100: 908661946 | D100: hairito06@gmail.com | F100: ORDINARIO | G100: PSICOLOGIA | H100: BASE ANTIGUA | I100: SANTA ANITA | J100: 2025-II | L100: Taller Vivencial 3 | N100: MOSTRÓ INTERÉS | O100: MOSTRÓ INTERÉS | Q100: NO- VIRTUAL | R100: ADMITIDO | S100: VIRTUAL | T100: RINDIO VIRTUAL | U100: ENTREGADO-COMPLETO
A101: 76308293 | B101: Sandy Ana Cordova Castillo | C101: 920476001 | D101: Sandyanagabriel22@gmail.com | F101: ORDINARIO | G101: PSICOLOGIA | H101: BASE ANTIGUA | I101: SANTA ANITA | J101: 2025-II | L101: Taller Vivencial 3 | N101: MOSTRÓ INTERÉS | O101: MOSTRÓ INTERÉS | Q101: NO- VIRTUAL | R101: ADMITIDO | S101: VIRTUAL | T101: RINDIO VIRTUAL | U101: ENTREGADO-COMPLETO
...

Sheet BD|Estrella V.
A1: DNI | B1: NOMBRES | C1: CELULAR | D1: CORREO | E1: COLEGIO DE PROCEDENCIA | F1: MODALIDAD | G1: ESCUELA | H1: ORIGEN | I1: SEDE | J1: SEMESTRE | K1: CAMPAÑA | L1: EVENTO | M1: FECHA DE INGRESO DE LEAD | N1: CONTACTO I | O1: CONTACTO II | P1: CONTACTO III | Q1: ¿PAGÓ DERECHO DE INSCRIPCIÓN? | R1: STATUS ACADÉMICO | S1: TIPO DE EXAMEN | T1: STATUS DE EXAMEN | U1: ENTREGA DE DOCUMENTOS | V1: OBSERVACION
A2: 70190769 | B2: Gressi Bernal | C2: 946509653 | D2: gressi.bernal7@outlook.com | G2: PSICOLOGIA | H2: EVENTO PRESENCIAL | I2: SURQUILLO | J2: 2025-II | N2: NO CONTESTA | O2: NO CONTESTA
A3: 4481897 | B3: Gabriela Carrasco | C3: 958372223 | D3: gcc.gaela@gmail.com | G3: COMUNICACIONES | H3: EVENTO PRESENCIAL | I3: SURQUILLO | J3: 2025-II | N3: MOSTRÓ INTERÉS | P3: =TRIM(BD_EstrellaVergara[[#This Row],[CONTACTO II]])
A4: 71977585 | B4: Kriz Figueroa | C4: 980709093 | D4: cristtina.figueroa@hotmail.com | G4: PSICOLOGIA | H4: EVENTO PRESENCIAL | I4: SURQUILLO | J4: 2025-II | N4: NO CONTESTA | O4: NO CONTESTA
A5: 61045287 | B5: Gianella liz Ccahuana Muñoz | C5: 977412641 | D5: gianellaliz12@gmail.com | G5: COMUNICACIONES | H5: EVENTO PRESENCIAL | I5: SURQUILLO | J5: 2025-II | N5: NO CONTESTA | P5: =TRIM(BD_EstrellaVergara[[#This Row],[CONTACTO II]])
A6: 93741783 | B6: Calet Barriga | C6: 966124384 | D6: caletbaldiviezo@gmail.com | G6: PSICOLOGIA | H6: EVENTO PRESENCIAL | I6: SURQUILLO | J6: 2025-II | N6: NO CONTESTA | O6: NO CONTESTA
A7: 61213274 | B7: Ale Herrera | C7: 964664077 | D7: ale1607herrera@gmail.com | G7: PSICOLOGIA | H7: EVENTO PRESENCIAL | I7: SURQUILLO | J7: 2025-II | N7: NO CONTESTA | O7: NO CONTESTA
A8: 74329437 | B8: Sheyla Guillen | C8: 921043308 | D8: sheyla31guillen@gmail.com | G8: PSICOLOGIA | H8: EVENTO PRESENCIAL | I8: SURQUILLO | J8: 2025-II | N8: NO CONTESTA | O8: NO CONTESTA
A9: 77299959 | B9: Sch Yosi | C9: 918295415 | D9: sucachuctayanashiayosi@gmail.com | G9: PSICOLOGIA | H9: EVENTO PRESENCIAL | I9: SURQUILLO | J9: 2025-II | N9: INCONTACTABLE | O9: NO CONTESTA
A10: 21139947 | B10: JANNET LILIA | C10: 999333701 | D10: gut_1977@hotmail.com | G10: COMUNICACIONES | H10: EVENTO PRESENCIAL | I10: SURQUILLO | J10: 2025-II | N10: MOSTRÓ INTERÉS | P10: =TRIM(BD_EstrellaVergara[[#This Row],[CONTACTO II]])
A11: 72674597 | B11: Nayeli Saavedra | C11: 993813827 | D11: Sonrielealavida100pre@gmail.com | G11: COMUNICACIONES | H11: EVENTO PRESENCIAL | I11: SURQUILLO | J11: 2025-II | N11: MOSTRÓ INTERÉS | P11: =TRIM(BD_EstrellaVergara[[#This Row],[CONTACTO II]])
A12: 97653214 | B12: Leen MV | C12: 998705769 | D12: eileen_mv@outlook.com | G12: TURISMO | H12: EVENTO PRESENCIAL | I12: SURQUILLO | J12: 2025-II | N12: NO CONTESTA | P12: =TRIM(BD_EstrellaVergara[[#This Row],[CONTACTO II]])
A13: 80191705 | B13: Hugo Rullier | C13: 913042492 | D13: hugo.rullier@ferreyros.com.pe | G13: PSICOLOGIA | H13: EVENTO PRESENCIAL | I13: SURQUILLO | J13: 2025-II | N13: NO CONTESTA | O13: NO CONTESTA
A14: 72935622 | B14: Angela Nicole Ventura Moran | C14: 918411989 | D14: venturamoranangelanicole572@gmail.com | G14: TURISMO | H14: EVENTO PRESENCIAL | I14: SURQUILLO | J14: 2025-II | N14: SELECCIONÓ OTRA UNIVERSIDAD | P14: =TRIM(BD_EstrellaVergara[[#This Row],[CONTACTO II]])
A15: 71441440 | B15: Luis Manuel Apolinario Poma | C15: 940325813 | D15: lapolinariop@outlook.com | G15: TURISMO | H15: EVENTO PRESENCIAL | I15: SURQUILLO | J15: 2025-II | N15: MOSTRÓ INTERÉS | P15: =TRIM(BD_EstrellaVergara[[#This Row],[CONTACTO II]])
A16: 76951149 | B16: Maria Milagros Muñico Tomas | C16: 986523274 | D16: milagritos311201@gmail.com | G16: TURISMO | H16: EVENTO PRESENCIAL | I16: SURQUILLO | J16: 2025-II | N16: NO CONTESTA | P16: =TRIM(BD_EstrellaVergara[[#This Row],[CONTACTO II]])
A17: 72030731 | B17: Genesis Isla Quispe | C17: 924810252 | D17: genesisquispe7453@gmail.com | G17: TURISMO | H17: EVENTO PRESENCIAL | I17: SURQUILLO | J17: 2025-II | N17: NO CONTESTA | P17: =TRIM(BD_EstrellaVergara[[#This Row],[CONTACTO II]])
A18: 25848105 | B18: Gloria Mayta | C18: 968010615 | D18: gmayta67@gmail.com | G18: PSICOLOGIA | H18: EVENTO PRESENCIAL | I18: SURQUILLO | J18: 2025-II | N18: MOSTRÓ INTERÉS | O18: NO CONTESTA
A19: 61180262 | B19: Gearwin Moreno | C19: 935736703 | D19: geanfmr5@gmail.com | G19: PSICOLOGIA | H19: EVENTO PRESENCIAL | I19: SURQUILLO | J19: 2025-II | N19: NO CONTESTA | O19: NO CONTESTA
A20: 10057423 | B20: Ketty López | C20: 991967793 | D20: llari202020@gmail.com | G20: COMUNICACIONES | H20: EVENTO PRESENCIAL | I20: SURQUILLO | J20: 2025-II | N20: NO CONTESTA | P20: =TRIM(BD_EstrellaVergara[[#This Row],[CONTACTO II]])
A21: 75565685 | B21: Juana Jiménez | C21: 921634596 | D21: jimenezpandall.2002@gmail.com | F21: ORDINARIO | G21: PSICOLOGIA | H21: EVENTO PRESENCIAL | I21: SURQUILLO | J21: 2025-II | N21: MOSTRÓ INTERÉS | O21: MOSTRÓ INTERÉS | P21: SE ENVIÓ INFORMACIÓN
A22: 71428305 | B22: Rafael Aguirre | C22: 985661657 | D22: raguirrepascual@gmail.com | G22: TURISMO | H22: EVENTO PRESENCIAL | I22: SURQUILLO | J22: 2025-II | N22: NO CONTESTA | P22: =TRIM(BD_EstrellaVergara[[#This Row],[CONTACTO II]])
A23: 73708912 | B23: Sebastian Sante | C23: 936985709 | D23: santeguizado0@gmail.com | G23: TURISMO | H23: EVENTO PRESENCIAL | I23: SURQUILLO | J23: 2025-II | N23: NO CONTESTA | P23: =TRIM(BD_EstrellaVergara[[#This Row],[CONTACTO II]])
A24: 8467699 | B24: lizardo Condori | C24: 940005120 | D24: esthermalpartida20@gmail.com | G24: PSICOLOGIA | H24: EVENTO PRESENCIAL | I24: SURQUILLO | J24: 2025-II | N24: NO CONTESTA | O24: NO CONTESTA
A25: 71324217 | B25: Micaela Barbaran | C25: 921146328 | D25: isabelbarbaran554@gmail.com | G25: COMUNICACIONES | H25: EVENTO PRESENCIAL | I25: SURQUILLO | J25: 2025-II | N25: SELECCIONÓ OTRA UNIVERSIDAD | P25: =TRIM(BD_EstrellaVergara[[#This Row],[CONTACTO II]])
A26: 75016687 | B26: Andrea De la Cruz | C26: 955047202 | D26: delacruzbertha484@gmail.com | G26: TURISMO | H26: EVENTO PRESENCIAL | I26: SURQUILLO | J26: 2025-II | N26: NO CONTESTA | P26: =TRIM(BD_EstrellaVergara[[#This Row],[CONTACTO II]])
A27: 60861804 | B27: Vanessa Huamani | C27: 912929983 | D27: vanessahuamani035@gmail.com | G27: PSICOLOGIA | H27: EVENTO PRESENCIAL | I27: SURQUILLO | J27: 2025-II | N27: MOSTRÓ INTERÉS | O27: NO CONTESTA | P27: =TRIM(BD_EstrellaVergara[[#This Row],[CONTACTO II]]) -> NO CONTESTA
B28: Carmen Molocho Vitor | C28: 998766782 | D28: carmen.molocho@hotmail.com | G28: COMUNICACIONES | H28: PAUTA DIGITAL | I28: SURQUILLO | J28: 2025-II | K28: Open Day 1 | L28: Open Day 1 | N28: NO CONTESTA | P28: =TRIM(BD_EstrellaVergara[[#This Row],[CONTACTO II]])
A29: 73732606 | B29: amy santos silva | C29: 949903377 | D29: barby_1216@hotmail.com | G29: COMUNICACIONES | H29: PAUTA DIGITAL | I29: SURQUILLO | J29: 2025-II | K29: Open Day 1 | L29: Open Day 1 | N29: MOSTRÓ INTERÉS | P29: =TRIM(BD_EstrellaVergara[[#This Row],[CONTACTO II]])
B30: Ariana Ninahuanca | C30: 983760292 | D30: ariana.ninahuanca4@gmail.com | G30: COMUNICACIONES | H30: PAUTA DIGITAL | I30: SURQUILLO | J30: 2025-II | K30: Open Day 1 | L30: Open Day 1 | N30: MOSTRÓ INTERÉS | P30: =TRIM(BD_EstrellaVergara[[#This Row],[CONTACTO II]])
A31: 70956935 | B31: Camila Taite reyes | C31: 999618790-981148402 | D31: rcarmen_jessica@hotmail.com | F31: ORDINARIO | G31: COMUNICACIONES | H31: PAUTA DIGITAL | I31: SURQUILLO | J31: 2025-II | K31: Open Day 1 | L31: Open Day 1 | N31: MOSTRÓ INTERÉS | P31: =TRIM(BD_EstrellaVergara[[#This Row],[CONTACTO II]]) | Q31: NO- VIRTUAL | R31: ADMITIDO | S31: VIRTUAL | T31: RINDIO VIRTUAL | U31: PENDIENTE TODO
A32: 70956943 | B32: Karla Taite Reyes | C32: 999618790 | D32: rcarmen_jessica@hotmail.com | G32: PSICOLOGIA | H32: PAUTA DIGITAL | I32: SURQUILLO | J32: 2025-II | K32: Open Day 1 | L32: Open Day 1 | N32: MOSTRÓ INTERÉS | O32: NO CONTESTA | P32: =TRIM(BD_EstrellaVergara[[#This Row],[CONTACTO II]]) -> NO CONTESTA
B33: Yadhira Meneses | C33: 925641716 | D33: camilamenesescuri@gmail.com | G33: PSICOLOGIA | H33: PAUTA DIGITAL | I33: SURQUILLO | J33: 2025-II | K33: Open Day 1 | L33: Open Day 1 | N33: MOSTRÓ INTERÉS | O33: NO CONTESTA | P33: =TRIM(BD_EstrellaVergara[[#This Row],[CONTACTO II]]) -> NO CONTESTA
A34: 61366147 | B34: mikaela enriquez | C34: 958675134 | D34: viannyaa@hotmail.com | G34: PSICOLOGIA | H34: PAUTA DIGITAL | I34: SURQUILLO | J34: 2025-II | K34: Open Day 1 | L34: Open Day 1 | N34: MOSTRÓ INTERÉS | O34: NO CONTESTA | P34: =TRIM(BD_EstrellaVergara[[#This Row],[CONTACTO II]]) -> NO CONTESTA
B35: Joaquin Paitan Cortez | C35: 972740041 | D35: joaezpa18@gmail.com | G35: PSICOLOGIA | H35: PAUTA DIGITAL | I35: SURQUILLO | J35: 2025-II | K35: Open Day 1 | L35: Open Day 1 | N35: MOSTRÓ INTERÉS | O35: NO CONTESTA | P35: =TRIM(BD_EstrellaVergara[[#This Row],[CONTACTO II]]) -> NO CONTESTA
B36: dome | C36: 932663601 | D36: dtuirolaos@gmail.com | G36: PSICOLOGIA | H36: PAUTA DIGITAL | I36: SURQUILLO | J36: 2025-II | K36: Open Day 1 | L36: Open Day 1 | N36: NO CONTESTA | O36: NO CONTESTA | P36: =TRIM(BD_EstrellaVergara[[#This Row],[CONTACTO II]]) -> NO CONTESTA
A37: 71366984 | B37: Romina Flores | C37: 905467988 | D37: rominasofia.fc@gmail.com | E37: Santiago Apostol | F37: ORDINARIO | G37: PSICOLOGIA | H37: PAUTA DIGITAL | I37: SURQUILLO | J37: 2025-II | K37: Open Day 1 | L37: Open Day 1 | N37: MOSTRÓ INTERÉS | O37: MOSTRÓ INTERÉS | P37: SE ENVIÓ INFORMACIÓN
A38: 61509014 | B38: David Diaz Fuentes | C38: 992248894 | D38: s.fuentes.educazione@gmail.com | G38: PSICOLOGIA | H38: PAUTA DIGITAL | I38: SURQUILLO | J38: 2025-II | K38: Open Day 1 | L38: Open Day 1 | N38: MOSTRÓ INTERÉS | O38: NO CONTESTA | P38: =TRIM(BD_EstrellaVergara[[#This Row],[CONTACTO II]]) -> NO CONTESTA
A39: 61022688 | B39: Elisa Cotrina Meza | C39: 910493054 | D39: elicotrinam07@gmail.com | G39: PSICOLOGIA | H39: PAUTA DIGITAL | I39: SURQUILLO | J39: 2025-II | K39: Open Day 1 | L39: Open Day 1 | N39: MOSTRÓ INTERÉS | O39: NO CONTESTA | P39: =TRIM(BD_EstrellaVergara[[#This Row],[CONTACTO II]]) -> NO CONTESTA
B40: pamela Martinez | C40: 902620130 | D40: p.martinzp2@gmail.com | G40: PSICOLOGIA | H40: PAUTA DIGITAL | I40: SURQUILLO | J40: 2025-II | K40: Open Day 1 | L40: Open Day 1 | N40: NO CONTESTA | O40: NO CONTESTA | P40: =TRIM(BD_EstrellaVergara[[#This Row],[CONTACTO II]]) -> NO CONTESTA
B41: aymar saravia | C41: 941731646 | D41: abregumayra631@gmail.com | G41: PSICOLOGIA | H41: PAUTA DIGITAL | I41: SURQUILLO | J41: 2025-II | K41: Open Day 1 | L41: Taller Vivencial 3 | N41: NO CONTESTA | O41: NO CONTESTA
B42: Montoya robles | C42: 997774393 | D42: t.montoya.robles@gmail.com | G42: TURISMO | H42: PAUTA DIGITAL | I42: SURQUILLO | J42: 2025-II | K42: Open Day 1 | L42: Open Day 1 | N42: MOSTRÓ INTERÉS | P42: =TRIM(BD_EstrellaVergara[[#This Row],[CONTACTO II]])
A43: 70626543 | B43: Sebastián Medina Quijano | C43: 933470160 | D43: medinasebastianwilly@gmail.com | G43: COMUNICACIONES | H43: EVENTO PRESENCIAL | I43: SURQUILLO | J43: 2025-II | N43: NO CONTESTA | P43: =TRIM(BD_EstrellaVergara[[#This Row],[CONTACTO II]])
A44: 62573909 | B44: Jimena Luciana Martínez Quispe | C44: 992219752 | D44: martinezjimena399@gmail.com | G44: PSICOLOGIA | H44: EVENTO PRESENCIAL | I44: SURQUILLO | J44: 2025-II | N44: MOSTRÓ INTERÉS | O44: NO CONTESTA | P44: =TRIM(BD_EstrellaVergara[[#This Row],[CONTACTO II]]) -> NO CONTESTA
A45: 71668474 | B45: Silvana Martinez | C45: 953418092 | D45: lmontlop19@gmail.com | G45: COMUNICACIONES | H45: EVENTO PRESENCIAL | I45: SURQUILLO | J45: 2025-II | N45: NO CONTESTA | P45: =TRIM(BD_EstrellaVergara[[#This Row],[CONTACTO II]])
A46: 76232980 | B46: André Leonardo Lira Flores | C46: 934732191 | D46: leogoosefifi@gmail.com | G46: COMUNICACIONES | H46: EVENTO PRESENCIAL | I46: SURQUILLO | J46: 2025-II | N46: MOSTRÓ INTERÉS | P46: =TRIM(BD_EstrellaVergara[[#This Row],[CONTACTO II]])
A47: 61511667 | B47: Ana Lucero Ancco Estrada | C47: 945381405 | D47: al.anccoes@gmail.com | G47: COMUNICACIONES | H47: EVENTO PRESENCIAL | I47: SURQUILLO | J47: 2025-II | N47: NO CONTESTA | P47: =TRIM(BD_EstrellaVergara[[#This Row],[CONTACTO II]])
A48: 74680044 | B48: Adriana Morales Cordova | C48: 951217487 | D48: adrianamoralescordova.23@gmail.com | G48: COMUNICACIONES | H48: EVENTO PRESENCIAL | I48: SURQUILLO | J48: 2025-II | N48: MOSTRÓ INTERÉS | P48: =TRIM(BD_EstrellaVergara[[#This Row],[CONTACTO II]])
A49: 72060491 | B49: Desiree Priscila Pucutay Torres | C49: 965827782 | D49: desireepucutay@gmail.com | G49: COMUNICACIONES | H49: EVENTO PRESENCIAL | I49: SURQUILLO | J49: 2025-II | N49: MOSTRÓ INTERÉS | P49: =TRIM(BD_EstrellaVergara[[#This Row],[CONTACTO II]])
A50: 61420834 | B50: Daniela Luana Zavaleta Martinez | C50: 992481519 | D50: daniluazavmar@gmail.com | G50: PSICOLOGIA | H50: EVENTO PRESENCIAL | I50: SURQUILLO | J50: 2025-II | N50: MOSTRÓ INTERÉS | O50: NO CONTESTA | P50: =TRIM(BD_EstrellaVergara[[#This Row],[CONTACTO II]]) -> NO CONTESTA
A51: 73927305 | B51: Abril Bianca Aitana Santiago Miranda | C51: 972297583 | G51: PSICOLOGIA | H51: EXPOUNIVERSIDAD | I51: SURQUILLO | J51: 2025-II | N51: SELECCIONÓ OTRA UNIVERSIDAD | O51: NO CONTESTA | P51: =TRIM(BD_EstrellaVergara[[#This Row],[CONTACTO II]]) -> NO CONTESTA
A52: 73155808 | B52: Emily Grisel Toribio Paucar | C52: 946493395 | D52: griseltori29@gmail.com | G52: PSICOLOGIA | H52: EVENTO PRESENCIAL | I52: SURQUILLO | J52: 2025-II | N52: NO CONTESTA | O52: NO CONTESTA | P52: NO HUBO PROGRESO
A53: 72840562 | B53: Raúl Gabriel Zamudio Sinche | C53: 980272503 | D53: zamudiosincher@gmail.com | G53: PSICOLOGIA | H53: EVENTO PRESENCIAL | I53: SURQUILLO | J53: 2025-II | N53: NO CONTESTA | O53: NO CONTESTA | P53: =TRIM(BD_EstrellaVergara[[#This Row],[CONTACTO II]]) -> NO CONTESTA
A54: 72825145 | B54: Miranda Celeste Suppo Valdiviezo | C54: 907883754 | D54: mirisuppo@gmail.com | G54: PSICOLOGIA | H54: EVENTO PRESENCIAL | I54: SURQUILLO | J54: 2025-II | N54: NO CONTESTA | O54: NO CONTESTA | P54: =TRIM(BD_EstrellaVergara[[#This Row],[CONTACTO II]]) -> NO CONTESTA
A55: 62049842 | B55: Luciana Mariela Chavez Perez | C55: 923466464 | D55: Lucianachavez2702@gmail.com | G55: PSICOLOGIA | H55: EVENTO PRESENCIAL | I55: SURQUILLO | J55: 2025-II | N55: MOSTRÓ INTERÉS | O55: MOSTRÓ INTERÉS | P55: SE ENVIÓ INFORMACIÓN
A56: 10244080 | B56: Andrea Isabel Berrocal Clemente | C56: 993391472 | D56: berrocalandreasjb@gmail.com | G56: PSICOLOGIA | H56: EVENTO PRESENCIAL | I56: SURQUILLO | J56: 2025-II | N56: NO CONTESTA | O56: NO CONTESTA | P56: =TRIM(BD_EstrellaVergara[[#This Row],[CONTACTO II]]) -> NO CONTESTA
A57: 75044432 | B57: Xiomara Martinez Omonte | C57: 926737235 | D57: maraomnt@gmail.com | G57: PSICOLOGIA | H57: EVENTO PRESENCIAL | I57: SURQUILLO | J57: 2025-II | N57: NO CONTESTA | O57: NO CONTESTA | P57: =TRIM(BD_EstrellaVergara[[#This Row],[CONTACTO II]]) -> NO CONTESTA
A58: 76496696 | B58: Fátima Muñante Cueto | C58: 949748982 | D58: fatimamutantecueto@gmail.com | G58: PSICOLOGIA | H58: EVENTO PRESENCIAL | I58: SURQUILLO | J58: 2025-II | N58: MOSTRÓ INTERÉS | O58: NO CONTESTA | P58: =TRIM(BD_EstrellaVergara[[#This Row],[CONTACTO II]]) -> NO CONTESTA
A59: 61453683 | B59: Yamile capcha carpio | C59: 907309656 | D59: Yamile.morvelli@gmail.com | G59: PSICOLOGIA | H59: EVENTO PRESENCIAL | I59: SURQUILLO | J59: 2025-II | N59: INCONTACTABLE | O59: NO CONTESTA | P59: =TRIM(BD_EstrellaVergara[[#This Row],[CONTACTO II]]) -> NO CONTESTA
A60: 72064877 | B60: Gianella Alexandra Rivera rios | C60: 913595831 | D60: gianellarivera122@gmail.com | G60: PSICOLOGIA | H60: EVENTO PRESENCIAL | I60: SURQUILLO | J60: 2025-II | N60: MOSTRÓ INTERÉS | O60: NO CONTESTA | P60: =TRIM(BD_EstrellaVergara[[#This Row],[CONTACTO II]]) -> NO CONTESTA
A61: 72618223 | B61: Kevin junior Santamaria Santamaria | C61: 912808096 | D61: kevin2908.ss@gmail.com | F61: ORDINARIO | G61: PSICOLOGIA | H61: EVENTO PRESENCIAL | I61: SURQUILLO | J61: 2025-II | K61: Open Day 1 | L61: Open Day 1 | N61: MOSTRÓ INTERÉS | O61: NO CONTESTA | P61: =TRIM(BD_EstrellaVergara[[#This Row],[CONTACTO II]]) -> NO CONTESTA | Q61: NO- VIRTUAL | R61: ADMITIDO | S61: VIRTUAL | T61: RINDIO VIRTUAL | U61: PENDIENTE TODO
A62: 74019326 | B62: Fabianna Anthonella | C62: 902709804 | D62: fabianna.anthonella.cr@gmail.com | G62: TURISMO | H62: EVENTO PRESENCIAL | I62: SURQUILLO | J62: 2025-II | N62: NO CONTESTA | P62: =TRIM(BD_EstrellaVergara[[#This Row],[CONTACTO II]])
A63: 73847520 | B63: Laisha Paloma Campos | C63: 930344718 | D63: laishacollas12@gmail.com | G63: TURISMO | H63: EVENTO PRESENCIAL | I63: SURQUILLO | J63: 2025-II | N63: NO CONTESTA | P63: =TRIM(BD_EstrellaVergara[[#This Row],[CONTACTO II]])
A64: 71188133 | B64: Valeria ocas basurto | C64: 970843666 | D64: Valeriaocasbasurto@gmail.com | G64: TURISMO | H64: EVENTO PRESENCIAL | I64: SURQUILLO | J64: 2025-II | N64: MOSTRÓ INTERÉS | P64: =TRIM(BD_EstrellaVergara[[#This Row],[CONTACTO II]])
A65: 71684925 | B65: Diego almonte quiroz | C65: 913263521 | D65: diegoalmontequiroz@gmail.com | G65: TURISMO | H65: EVENTO PRESENCIAL | I65: SURQUILLO | J65: 2025-II | N65: NO CONTESTA | P65: =TRIM(BD_EstrellaVergara[[#This Row],[CONTACTO II]])
A66: 73561456 | B66: Gabriela Camila De Paz Robles | C66: 967313098 | D66: gabrieladepaz31@gmail.com | G66: TURISMO | H66: EVENTO PRESENCIAL | I66: SURQUILLO | J66: 2025-II | N66: MOSTRÓ INTERÉS | P66: =TRIM(BD_EstrellaVergara[[#This Row],[CONTACTO II]])
A67: 70628225 | B67: Zaira Verónica Pintado Flores | C67: 982921891 | D67: zairapintado07@gmail.com | G67: TURISMO | H67: EVENTO PRESENCIAL | I67: SURQUILLO | J67: 2025-II | N67: MOSTRÓ INTERÉS | P67: =TRIM(BD_EstrellaVergara[[#This Row],[CONTACTO II]])
A68: 71359482 | B68: Genesis Myrella Lozano Lozano | C68: 950087832 | D68: genesismyrellal@gmail.com | G68: TURISMO | H68: EVENTO PRESENCIAL | I68: SURQUILLO | J68: 2025-II | N68: MOSTRÓ INTERÉS | P68: =TRIM(BD_EstrellaVergara[[#This Row],[CONTACTO II]])
A69: 75912118 | B69: Diego Abad Holguin | C69: 979353654 | F69: ORDINARIO | G69: COMUNICACIONES | H69: PAUTA DIGITAL | I69: SURQUILLO | J69: 2025-II | K69: Open Day 1 | L69: Open Day 1 | N69: MOSTRÓ INTERÉS | O69: SELECCIONÓ OTRA UNIVERSIDAD | P69: =TRIM(BD_EstrellaVergara[[#This Row],[CONTACTO II]]) -> SELECCIONÓ OTRA UNIVERSIDAD | Q69: NO- VIRTUAL | R69: ADMITIDO | S69: VIRTUAL | T69: RINDIO VIRTUAL | U69: PENDIENTE TODO
A70: 61789830 | B70: Joanna Uriol Christensen | C70: 938717761 | G70: TURISMO | H70: PAUTA DIGITAL | I70: SURQUILLO | J70: 2025-II | N70: MOSTRÓ INTERÉS | P70: =TRIM(BD_EstrellaVergara[[#This Row],[CONTACTO II]])
A71: 70341201 | B71: Lucero Gastañadui | C71: 953509600 | G71: COMUNICACIONES | H71: PAUTA DIGITAL | I71: SURQUILLO | J71: 2025-II | N71: MOSTRÓ INTERÉS | O71: MOSTRÓ INTERÉS | P71: EVALUANDO OPCIONES | Q71: NO- VIRTUAL | R71: INSCRITO | S71: VIRTUAL | T71: RENDIRÁ VIRTUAL | U71: PENDIENTE TODO
A72: 61218143 | B72: Vale | C72: 972403311 | D72: valeriagalaxycat92@gmail.com | E72: TERMINÉ EL COLEGIO | G72: PSICOLOGIA | H72: PAUTA DIGITAL | I72: SURQUILLO | J72: 2025-II | N72: NO CONTESTA | O72: NO CONTESTA | P72: =TRIM(BD_EstrellaVergara[[#This Row],[CONTACTO II]]) -> NO CONTESTA
A73: 48357919 | B73: Shirley P. Arraiza | C73: 918732207 | D73: shirley_paz18@hotmail.com | E73: TERMINÉ EL COLEGIO | G73: PSICOLOGIA | H73: PAUTA DIGITAL | I73: SURQUILLO | J73: 2025-II | N73: NO CONTESTA | O73: MOSTRÓ INTERÉS | P73: SE ENVIÓ INFORMACIÓN
A74: 72758772 | B74: Lesly Iman Munarriz | C74: 906716961 | D74: leslyiman_14@hotmail.com | E74: TERMINÉ EL COLEGIO | G74: COMUNICACIONES | H74: PAUTA DIGITAL | I74: SURQUILLO | J74: 2025-II | N74: NO CONTESTA | P74: =TRIM(BD_EstrellaVergara[[#This Row],[CONTACTO II]])
A75: 72973708 | B75: Judith Vera | C75: 908595068 | D75: evelinj_05@hotmail.com | E75: TERMINÉ EL COLEGIO | G75: PSICOLOGIA | H75: PAUTA DIGITAL | I75: SURQUILLO | J75: 2025-II | N75: NO CONTESTA | O75: NO CONTESTA | P75: =TRIM(BD_EstrellaVergara[[#This Row],[CONTACTO II]]) -> NO CONTESTA
A76: 61010307 | B76: Mia escudero | C76: 987819216 | D76: maricieloescudero59@gmail.com | E76: TERMINÉ EL COLEGIO | G76: PSICOLOGIA | H76: PAUTA DIGITAL | I76: SURQUILLO | J76: 2025-II | N76: NO CONTESTA | O76: NO CONTESTA | P76: =TRIM(BD_EstrellaVergara[[#This Row],[CONTACTO II]]) -> NO CONTESTA
A77: 74116072 | B77: Diego peralta camacho | C77: 968587826 | D77: cperaltanelson@yahoo.com | G77: COMUNICACIONES | H77: PAUTA DIGITAL | I77: SURQUILLO | J77: 2025-II | K77: Taller Vivencial 2 | L77: Taller Vivencial 2 | N77: NO CONTESTA | P77: =TRIM(BD_EstrellaVergara[[#This Row],[CONTACTO II]])
A78: 71371651 | B78: Keysi | C78: 972718127 | D78: keysiemi226@gmail.com | G78: COMUNICACIONES | H78: PAUTA DIGITAL | I78: SURQUILLO | J78: 2025-II | K78: Taller Vivencial 2 | L78: Taller Vivencial 2 | N78: NO CONTESTA | P78: =TRIM(BD_EstrellaVergara[[#This Row],[CONTACTO II]])
B79: Ruth Claudia (turno noche, egresó 2015) | C79: 976342155 | D79: rtueros927@gmail.com | F79: COMPLEMENTACIÓN ACADÉMICA | G79: TURISMO | H79: PAUTA DIGITAL | I79: ESITUR | J79: 2025-II | N79: NO CONTESTA | O79: MOSTRÓ INTERÉS
A80: 73724855 | B80: Freddy Eddy huaracha Álvarez | C80: 994914208 | D80: bambamfotho@gmail.com | F80: ORDINARIO | G80: COMUNICACIONES | H80: COUNTER | I80: SURQUILLO | J80: 2025-II | N80: MOSTRÓ INTERÉS | O80: SE ENVIÓ INFORMACIÓN | P80: =TRIM(BD_EstrellaVergara[[#This Row],[CONTACTO II]]) -> SE ENVIÓ INFORMACIÓN | Q80: NO- VIRTUAL | R80: ADMITIDO | S80: VIRTUAL | T80: RINDIO VIRTUAL | U80: PENDIENTE TODO
A81: 73363719 | B81: Fabrizio Fernandini Amaya | C81: 983633631 | D81: ffernandini10@gmail.com | F81: TRASLADO EXTERNO | G81: COMUNICACIONES | H81: COUNTER | I81: SURQUILLO | J81: 2025-II | N81: MOSTRÓ INTERÉS | O81: SE ENVIÓ INFORMACIÓN | P81: =TRIM(BD_EstrellaVergara[[#This Row],[CONTACTO II]]) -> SE ENVIÓ INFORMACIÓN | Q81: SÍ- EXAMEN PRESENCIAL | R81: ADMITIDO | S81: PRESENCIAL | T81: RENDIRÁ PRESENCIAL | U81: PENDIENTE TODO | V81: 1000280396
A82: 75011487 | B82: nicole sotero | C82: 952173822 | D82: nicolesotero15@gmail.com | F82: ORDINARIO | G82: TURISMO | H82: COUNTER | I82: SURQUILLO | J82: 2025-II | N82: MOSTRÓ INTERÉS | O82: SE ENVIÓ INFORMACIÓN | P82: SE ENVIÓ INFORMACIÓN | Q82: NO- VIRTUAL | R82: ADMITIDO | S82: VIRTUAL | T82: RINDIO VIRTUAL | U82: PENDIENTE TODO
A83: 63513263 | B83: Katia Sandovalrojas | C83: 962773085 | D83: katiasandovalrojas10@gmail.com | E83: TERMINÉ EL COLEGIO | G83: PSICOLOGIA | H83: PAUTA DIGITAL | I83: SURQUILLO | J83: 2025-II | N83: NO CONTESTA | O83: NO CONTESTA | P83: =TRIM(BD_EstrellaVergara[[#This Row],[CONTACTO II]]) -> NO CONTESTA
A84: 72454081 | B84: Dana Nizama Castillo | C84: 995709843 | D84: dananizamacastillo@gmail.com | E84: TERMINÉ EL COLEGIO | G84: PSICOLOGIA | H84: PAUTA DIGITAL | I84: SURQUILLO | J84: 2025-II | N84: NO CONTESTA | O84: SELECCIONÓ OTRA UNIVERSIDAD
A85: 71181567 | B85: Sofia Medina Milla | C85: 991460165 | D85: karimil8448@gmail.com | E85: TERMINÉ EL COLEGIO | F85: EXAMEN DIGITAL | G85: COMUNICACIONES | H85: PAUTA DIGITAL | I85: SURQUILLO | J85: 2025-II | N85: NO CONTESTA | P85: =TRIM(BD_EstrellaVergara[[#This Row],[CONTACTO II]])
A86: Universidad católica de Chimbote | B86: Celeste Laureano Grados (turno noche, 2019-2023 VII ciclo) Universidad católica de Chimbote | C86: 981290147 | D86: walterlaureanom@yahoo.es | F86: TRASLADO EXTERNO | G86: TURISMO | H86: PAUTA DIGITAL | I86: SURQUILLO | J86: 2025-II | N86: NO CONTESTA | P86: =TRIM(BD_EstrellaVergara[[#This Row],[CONTACTO II]])
A87: 74332873 | B87: Yoe Mendoza | C87: 921552451 | D87: yoenitma@gmail.com | E87: TERMINÉ EL COLEGIO | F87: ORDINARIO | G87: PSICOLOGIA | H87: PAUTA DIGITAL | I87: SURQUILLO | J87: 2025-II | N87: NO CONTESTA | O87: NO CONTESTA | P87: =TRIM(BD_EstrellaVergara[[#This Row],[CONTACTO II]]) -> NO CONTESTA
A88: 60548740 | B88: Esmeralda CB | C88: 922591776 | D88: yaniracarrascobelito@gmail.com | E88: TERMINÉ EL COLEGIO | F88: ORDINARIO | G88: PSICOLOGIA | H88: PAUTA DIGITAL | I88: SURQUILLO | J88: 2025-II | N88: NO CONTESTA | O88: NO CONTESTA | P88: =TRIM(BD_EstrellaVergara[[#This Row],[CONTACTO II]]) -> NO CONTESTA
A89: 60771057 | B89: Yazuri Yulissa Mayta Ramirez | C89: 940567049 | D89: zussa.rm@gmail.com | F89: TERCIO SUPERIOR | G89: COMUNICACIONES | H89: COUNTER | I89: SURQUILLO | J89: 2025-II | N89: MOSTRÓ INTERÉS | O89: SE ENVIÓ INFORMACIÓN | P89: =TRIM(BD_EstrellaVergara[[#This Row],[CONTACTO II]]) -> SE ENVIÓ INFORMACIÓN | Q89: NO- VIRTUAL | R89: ADMITIDO | S89: VIRTUAL | T89: RINDIO VIRTUAL | U89: PENDIENTE TODO
A90: 71164126 | B90: Xiomara | C90: 995157240 | D90: minkukkie1234@gmail.com | E90: ES DE CHICLAYO | G90: PSICOLOGIA | H90: PAUTA DIGITAL | I90: SURQUILLO | J90: 2025-II | K90: Open Day 2 | L90: Open Day 2 | N90: NO CONTESTA | O90: SELECCIONÓ OTRA UNIVERSIDAD | P90: =TRIM(BD_EstrellaVergara[[#This Row],[CONTACTO II]]) -> SELECCIONÓ OTRA UNIVERSIDAD
A91: 45130285 | B91: Edison Escalante | C91: 930236732 | G91: COMUNICACIONES | H91: PAUTA DIGITAL | I91: SURQUILLO | J91: 2025-II | N91: SE ENVIÓ INFORMACIÓN | P91: =TRIM(BD_EstrellaVergara[[#This Row],[CONTACTO II]])
A92: 60733069 | B92: Dani Atalaya | C92: 940694853 | D92: dany.atalaya65@gmail.com | G92: PSICOLOGIA | H92: PAUTA DIGITAL | I92: SURQUILLO | J92: 2025-II | K92: Open Day 2 | L92: Open Day 2 | N92: NO CONTESTA | O92: NO CONTESTA | P92: =TRIM(BD_EstrellaVergara[[#This Row],[CONTACTO II]]) -> NO CONTESTA
A93: 10641930 | B93: Jon Wik | C93: 927961137 | D93: jwik10028@gmail.com | G93: TURISMO | H93: PAUTA DIGITAL | I93: SURQUILLO | J93: 2025-II | K93: Open Day 3 | L93: Open Day 3 | N93: SE ENVIÓ INFORMACIÓN | P93: =TRIM(BD_EstrellaVergara[[#This Row],[CONTACTO II]])
A94: 7828197 | B94: Baudelia Antezana | C94: 900591705 | G94: COMUNICACIONES | H94: PAUTA DIGITAL | I94: SURQUILLO | J94: 2025-II | N94: SE ENVIÓ INFORMACIÓN | P94: =TRIM(BD_EstrellaVergara[[#This Row],[CONTACTO II]])
A95: 9714024 | B95: Marita Lozano Cueva | C95: 999330606 | D95: maritalozanoc@yahoo.com | G95: PSICOLOGIA | H95: PAUTA DIGITAL | I95: SURQUILLO | J95: 2025-II | K95: Taller Vivencial 2 | L95: Taller Vivencial 2 | N95: NO CONTESTA | O95: NO CONTESTA | P95: =TRIM(BD_EstrellaVergara[[#This Row],[CONTACTO II]]) -> NO CONTESTA
A96: 61471493 | B96: Ariana Chunga Lanza | C96: 907007604 | D96: chungalanzaariana3ro@gmail.com | G96: PSICOLOGIA | H96: PAUTA DIGITAL | I96: SURQUILLO | J96: 2025-II | K96: Taller Vivencial 2 | L96: Taller Vivencial 2 | N96: INCONTACTABLE | O96: NO CONTESTA | P96: =TRIM(BD_EstrellaVergara[[#This Row],[CONTACTO II]]) -> NO CONTESTA
A97: 73560291 | B97: Stephany Barboza Tello | C97: 940250693 | D97: gbarbozatello@gmail.com | G97: TURISMO | H97: PAUTA DIGITAL | I97: SURQUILLO | J97: 2025-II | K97: Open Day 2 | L97: Open Day 2 | N97: MOSTRÓ INTERÉS | O97: NO CONTESTA | P97: =TRIM(BD_EstrellaVergara[[#This Row],[CONTACTO II]]) -> NO CONTESTA
A98: 73157221 | B98: Marce Avelez | C98: 944299316 | D98: marcelavelez009@gmail.com | G98: COMUNICACIONES | H98: PAUTA DIGITAL | I98: SURQUILLO | J98: 2025-II | K98: Open Day 2 | L98: Open Day 2 | N98: INCONTACTABLE | P98: =TRIM(BD_EstrellaVergara[[#This Row],[CONTACTO II]])
A99: 61497611 | B99: Almendra Aguirre | C99: 989182183 | D99: almendraaguirre073@gmail.com | G99: PSICOLOGIA | H99: PAUTA DIGITAL | I99: SURQUILLO | J99: 2025-II | K99: Open Day 2 | L99: Open Day 2 | N99: NO CONTESTA | O99: NO CONTESTA
A100: 60946526 | B100: raquel marin hugo | C100: 938211716 | D100: rmarinhugo@gmail.com | G100: TURISMO | H100: PAUTA DIGITAL | I100: SURQUILLO | J100: 2025-II | K100: Open Day 2 | L100: Open Day 2 | N100: NO CONTESTA | P100: =TRIM(BD_EstrellaVergara[[#This Row],[CONTACTO II]])
...

Sheet REPORTE| Agenda
B1: AVANCE ADMITIDOS 2025 - II | Por Asesora | Y1: AVANCE ADMITIDOS 2026 - I | Por Asesora
B3: Escuela | C3: Abril | G3: Mayo | K3: Junio | O3: Julio | S3: Agosto | Y3: Escuela | Z3: Abril | AD3: Mayo | AH3: Junio | AL3: Julio | AP3: Agosto
B5: Pya Pinto | C5: S1 | D5: S2 | E5: S3 | F5: S4 | G5: S1 | H5: S2 | I5: S3 | J5: S4 | K5: S1 | L5: S2 | M5: S3 | N5: S4 | O5: S1 | P5: S2 | Q5: S3 | R5: S4 | S5: S1 | T5: S2 | U5: S3 | V5: S4 | W5: Total | Y5: Pya Pinto | Z5: S1 | AA5: S2 | AB5: S3 | AC5: S4 | AD5: S1 | AE5: S2 | AF5: S3 | AG5: S4 | AH5: S1 | AI5: S2 | AJ5: S3 | AK5: S4 | AL5: S1 | AM5: S2 | AN5: S3 | AO5: S4 | AP5: S1 | AQ5: S2 | AR5: S3 | AS5: S4 | AT5: Total
B7: PSICOLOGIA | F7: 1 | G7: =COUNTIFS(AG_Sheyla_1[MES],"Jun",AG_Sheyla_1[SEMANA],'REPORTE| Agenda'!G5,AG_Sheyla_1[ESCUELA],"PSICOLOGIA",AG_Sheyla_1[2 RINDIÓ EXAMEN],"SI",AG_Sheyla_1[ASESORA],'REPORTE| Agenda'!$B$5,AG_Sheyla_1[SEMESTRE],"2025-II") -> 2 | H7: =COUNTIFS(AG_Sheyla_1[MES],"Jun",AG_Sheyla_1[SEMANA],'REPORTE| Agenda'!H5,AG_Sheyla_1[ESCUELA],"PSICOLOGIA",AG_Sheyla_1[2 RINDIÓ EXAMEN],"SI",AG_Sheyla_1[ASESORA],'REPORTE| Agenda'!$B$5,AG_Sheyla_1[SEMESTRE],"2025-II") -> 2 | I7: =COUNTIFS(AG_Sheyla_1[MES],"Jun",AG_Sheyla_1[SEMANA],'REPORTE| Agenda'!I5,AG_Sheyla_1[ESCUELA],"PSICOLOGIA",AG_Sheyla_1[2 RINDIÓ EXAMEN],"SI",AG_Sheyla_1[ASESORA],'REPORTE| Agenda'!$B$5,AG_Sheyla_1[SEMESTRE],"2025-II") -> 1 | J7: =COUNTIFS(AG_Sheyla_1[MES],"Jun",AG_Sheyla_1[SEMANA],'REPORTE| Agenda'!J5,AG_Sheyla_1[ESCUELA],"PSICOLOGIA",AG_Sheyla_1[2 RINDIÓ EXAMEN],"SI",AG_Sheyla_1[ASESORA],'REPORTE| Agenda'!$B$5,AG_Sheyla_1[SEMESTRE],"2025-II") -> 4 | K7: =COUNTIFS(AG_Sheyla_1[MES],"Jun",AG_Sheyla_1[SEMANA],'REPORTE| Agenda'!K5,AG_Sheyla_1[ESCUELA],"PSICOLOGIA",AG_Sheyla_1[2 RINDIÓ EXAMEN],"SI",AG_Sheyla_1[ASESORA],'REPORTE| Agenda'!$B$5,AG_Sheyla_1[SEMESTRE],"2025-II") -> 2 | L7: =COUNTIFS(AG_Sheyla_1[MES],"Jun",AG_Sheyla_1[SEMANA],'REPORTE| Agenda'!L5,AG_Sheyla_1[ESCUELA],"PSICOLOGIA",AG_Sheyla_1[2 RINDIÓ EXAMEN],"SI",AG_Sheyla_1[ASESORA],'REPORTE| Agenda'!$B$5,AG_Sheyla_1[SEMESTRE],"2025-II") -> 2 | M7: =COUNTIFS(AG_Sheyla_1[MES],"Jun",AG_Sheyla_1[SEMANA],'REPORTE| Agenda'!M5,AG_Sheyla_1[ESCUELA],"PSICOLOGIA",AG_Sheyla_1[2 RINDIÓ EXAMEN],"SI",AG_Sheyla_1[ASESORA],'REPORTE| Agenda'!$B$5,AG_Sheyla_1[SEMESTRE],"2025-II") -> 1 | N7: =COUNTIFS(AG_Sheyla_1[MES],"Jun",AG_Sheyla_1[SEMANA],'REPORTE| Agenda'!N5,AG_Sheyla_1[ESCUELA],"PSICOLOGIA",AG_Sheyla_1[2 RINDIÓ EXAMEN],"SI",AG_Sheyla_1[ASESORA],'REPORTE| Agenda'!$B$5,AG_Sheyla_1[SEMESTRE],"2025-II") -> 4 | O7: =COUNTIFS(AG_Sheyla_1[MES],"Jul",AG_Sheyla_1[SEMANA],'REPORTE| Agenda'!O5,AG_Sheyla_1[ESCUELA],"PSICOLOGIA",AG_Sheyla_1[2 RINDIÓ EXAMEN],"SI",AG_Sheyla_1[ASESORA],'REPORTE| Agenda'!$B$5,AG_Sheyla_1[SEMESTRE],"2025-II") -> 3 | P7: =COUNTIFS(AG_Sheyla_1[MES],"Jul",AG_Sheyla_1[SEMANA],'REPORTE| Agenda'!P5,AG_Sheyla_1[ESCUELA],"PSICOLOGIA",AG_Sheyla_1[2 RINDIÓ EXAMEN],"SI",AG_Sheyla_1[ASESORA],'REPORTE| Agenda'!$B$5,AG_Sheyla_1[SEMESTRE],"2025-II") -> 2 | Q7: =COUNTIFS(AG_Sheyla_1[MES],"Jul",AG_Sheyla_1[SEMANA],'REPORTE| Agenda'!$Q$5,AG_Sheyla_1[ESCUELA],"PSICOLOGIA",AG_Sheyla_1[2 RINDIÓ EXAMEN],"SI",AG_Sheyla_1[ASESORA],'REPORTE| Agenda'!$B$5,AG_Sheyla_1[SEMESTRE],"2025-II") -> 4 | R7: =COUNTIFS(AG_Sheyla_1[MES],"Jul",AG_Sheyla_1[SEMANA],'REPORTE| Agenda'!$R$5,AG_Sheyla_1[ESCUELA],"PSICOLOGIA",AG_Sheyla_1[2 RINDIÓ EXAMEN],"SI",AG_Sheyla_1[ASESORA],'REPORTE| Agenda'!$B$5,AG_Sheyla_1[SEMESTRE],"2025-II") -> 2 | S7: =COUNTIFS(AG_Sheyla_1[MES],"Ago",AG_Sheyla_1[SEMANA],'REPORTE| Agenda'!S5,AG_Sheyla_1[ESCUELA],"PSICOLOGIA",AG_Sheyla_1[2 RINDIÓ EXAMEN],"SI",AG_Sheyla_1[ASESORA],'REPORTE| Agenda'!$B$5,AG_Sheyla_1[SEMESTRE],"2025-II") -> 0 | T7: =COUNTIFS(AG_Sheyla_1[MES],"Ago",AG_Sheyla_1[SEMANA],'REPORTE| Agenda'!T5,AG_Sheyla_1[ESCUELA],"PSICOLOGIA",AG_Sheyla_1[2 RINDIÓ EXAMEN],"SI",AG_Sheyla_1[ASESORA],'REPORTE| Agenda'!$B$5,AG_Sheyla_1[SEMESTRE],"2025-II") -> 0 | U7: =COUNTIFS(AG_Sheyla_1[MES],"Ago",AG_Sheyla_1[SEMANA],'REPORTE| Agenda'!U5,AG_Sheyla_1[ESCUELA],"PSICOLOGIA",AG_Sheyla_1[2 RINDIÓ EXAMEN],"SI",AG_Sheyla_1[ASESORA],'REPORTE| Agenda'!$B$5,AG_Sheyla_1[SEMESTRE],"2025-II") -> 0 | V7: =COUNTIFS(AG_Sheyla_1[MES],"Ago",AG_Sheyla_1[SEMANA],'REPORTE| Agenda'!V5,AG_Sheyla_1[ESCUELA],"PSICOLOGIA",AG_Sheyla_1[2 RINDIÓ EXAMEN],"SI",AG_Sheyla_1[ASESORA],'REPORTE| Agenda'!$B$5,AG_Sheyla_1[SEMESTRE],"2025-II") -> 0 | W7: =SUM(C7:V7) -> 30 | Y7: PSICOLOGIA | AC7: 1 | AE7: 1 | AF7: 1 | AG7: 1 | AH7: =COUNTIFS(AG_Sheyla_1[MES],"Jun",AG_Sheyla_1[SEMANA],'REPORTE| Agenda'!AH5,AG_Sheyla_1[ESCUELA],"PSICOLOGIA",AG_Sheyla_1[2 RINDIÓ EXAMEN],"SI",AG_Sheyla_1[ASESORA],'REPORTE| Agenda'!$B$5,AG_Sheyla_1[SEMESTRE],"2026-I") -> 0 | AI7: =COUNTIFS(AG_Sheyla_1[MES],"Jun",AG_Sheyla_1[SEMANA],'REPORTE| Agenda'!AI5,AG_Sheyla_1[ESCUELA],"PSICOLOGIA",AG_Sheyla_1[2 RINDIÓ EXAMEN],"SI",AG_Sheyla_1[ASESORA],'REPORTE| Agenda'!$B$5,AG_Sheyla_1[SEMESTRE],"2026-I") -> 1 | AJ7: =COUNTIFS(AG_Sheyla_1[MES],"Jun",AG_Sheyla_1[SEMANA],'REPORTE| Agenda'!AJ5,AG_Sheyla_1[ESCUELA],"PSICOLOGIA",AG_Sheyla_1[2 RINDIÓ EXAMEN],"SI",AG_Sheyla_1[ASESORA],'REPORTE| Agenda'!$B$5,AG_Sheyla_1[SEMESTRE],"2026-I") -> 2 | AK7: =COUNTIFS(AG_Sheyla_1[MES],"Jun",AG_Sheyla_1[SEMANA],'REPORTE| Agenda'!AK5,AG_Sheyla_1[ESCUELA],"PSICOLOGIA",AG_Sheyla_1[2 RINDIÓ EXAMEN],"SI",AG_Sheyla_1[ASESORA],'REPORTE| Agenda'!$B$5,AG_Sheyla_1[SEMESTRE],"2026-I") -> 0 | AL7: =COUNTIFS(AG_Sheyla_1[MES],"Jul",AG_Sheyla_1[SEMANA],'REPORTE| Agenda'!AL5,AG_Sheyla_1[ESCUELA],"PSICOLOGIA",AG_Sheyla_1[2 RINDIÓ EXAMEN],"SI",AG_Sheyla_1[ASESORA],'REPORTE| Agenda'!$B$5,AG_Sheyla_1[SEMESTRE],"2026-I") -> 0 | AM7: =COUNTIFS(AG_Sheyla_1[MES],"Jul",AG_Sheyla_1[SEMANA],'REPORTE| Agenda'!AM5,AG_Sheyla_1[ESCUELA],"PSICOLOGIA",AG_Sheyla_1[2 RINDIÓ EXAMEN],"SI",AG_Sheyla_1[ASESORA],'REPORTE| Agenda'!$B$5,AG_Sheyla_1[SEMESTRE],"2026-I") -> 2 | AN7: =COUNTIFS(AG_Sheyla_1[MES],"Jul",AG_Sheyla_1[SEMANA],'REPORTE| Agenda'!$Q$5,AG_Sheyla_1[ESCUELA],"PSICOLOGIA",AG_Sheyla_1[2 RINDIÓ EXAMEN],"SI",AG_Sheyla_1[ASESORA],'REPORTE| Agenda'!$B$5,AG_Sheyla_1[SEMESTRE],"2026-I") -> 1 | AO7: =COUNTIFS(AG_Sheyla_1[MES],"Jul",AG_Sheyla_1[SEMANA],'REPORTE| Agenda'!$R$5,AG_Sheyla_1[ESCUELA],"PSICOLOGIA",AG_Sheyla_1[2 RINDIÓ EXAMEN],"SI",AG_Sheyla_1[ASESORA],'REPORTE| Agenda'!$B$5,AG_Sheyla_1[SEMESTRE],"2026-I") -> 0 | AP7: =COUNTIFS(AG_Sheyla_1[MES],"Ago",AG_Sheyla_1[SEMANA],'REPORTE| Agenda'!AP5,AG_Sheyla_1[ESCUELA],"PSICOLOGIA",AG_Sheyla_1[2 RINDIÓ EXAMEN],"SI",AG_Sheyla_1[ASESORA],'REPORTE| Agenda'!$B$5,AG_Sheyla_1[SEMESTRE],"2026-I") -> 1 | AQ7: =COUNTIFS(AG_Sheyla_1[MES],"Ago",AG_Sheyla_1[SEMANA],'REPORTE| Agenda'!AQ5,AG_Sheyla_1[ESCUELA],"PSICOLOGIA",AG_Sheyla_1[2 RINDIÓ EXAMEN],"SI",AG_Sheyla_1[ASESORA],'REPORTE| Agenda'!$B$5,AG_Sheyla_1[SEMESTRE],"2026-I") -> 0 | AR7: =COUNTIFS(AG_Sheyla_1[MES],"Ago",AG_Sheyla_1[SEMANA],'REPORTE| Agenda'!AR5,AG_Sheyla_1[ESCUELA],"PSICOLOGIA",AG_Sheyla_1[2 RINDIÓ EXAMEN],"SI",AG_Sheyla_1[ASESORA],'REPORTE| Agenda'!$B$5,AG_Sheyla_1[SEMESTRE],"2026-I") -> 0 | AS7: =COUNTIFS(AG_Sheyla_1[MES],"Ago",AG_Sheyla_1[SEMANA],'REPORTE| Agenda'!AS5,AG_Sheyla_1[ESCUELA],"PSICOLOGIA",AG_Sheyla_1[2 RINDIÓ EXAMEN],"SI",AG_Sheyla_1[ASESORA],'REPORTE| Agenda'!$B$5,AG_Sheyla_1[SEMESTRE],"2026-I") -> 0 | AT7: =SUM(Z7:AS7) -> 11
B8: TURISMO | F8: 1 | H8: 1 | I8: 1 | J8: 1 | K8: =COUNTIFS(AG_Sheyla_1[MES],"Jun",AG_Sheyla_1[SEMANA],'REPORTE| Agenda'!K5,AG_Sheyla_1[ESCUELA],"TURISMO",AG_Sheyla_1[2 RINDIÓ EXAMEN],"SI",AG_Sheyla_1[ASESORA],'REPORTE| Agenda'!$B$5,AG_Sheyla_1[SEMESTRE],"2025-II") -> 1 | L8: =COUNTIFS(AG_Sheyla_1[MES],"Jun",AG_Sheyla_1[SEMANA],'REPORTE| Agenda'!L5,AG_Sheyla_1[ESCUELA],"TURISMO",AG_Sheyla_1[2 RINDIÓ EXAMEN],"SI",AG_Sheyla_1[ASESORA],'REPORTE| Agenda'!$B$5,AG_Sheyla_1[SEMESTRE],"2025-II") -> 0 | M8: =COUNTIFS(AG_Sheyla_1[MES],"Jun",AG_Sheyla_1[SEMANA],'REPORTE| Agenda'!M5,AG_Sheyla_1[ESCUELA],"TURISMO",AG_Sheyla_1[2 RINDIÓ EXAMEN],"SI",AG_Sheyla_1[ASESORA],'REPORTE| Agenda'!$B$5,AG_Sheyla_1[SEMESTRE],"2025-II") -> 0 | N8: =COUNTIFS(AG_Sheyla_1[MES],"Jun",AG_Sheyla_1[SEMANA],'REPORTE| Agenda'!N5,AG_Sheyla_1[ESCUELA],"TURISMO",AG_Sheyla_1[2 RINDIÓ EXAMEN],"SI",AG_Sheyla_1[ASESORA],'REPORTE| Agenda'!$B$5,AG_Sheyla_1[SEMESTRE],"2025-II") -> 0 | O8: =COUNTIFS(AG_Sheyla_1[MES],"Jul",AG_Sheyla_1[SEMANA],'REPORTE| Agenda'!$O$5,AG_Sheyla_1[ESCUELA],"TURISMO",AG_Sheyla_1[2 RINDIÓ EXAMEN],"SI",AG_Sheyla_1[ASESORA],'REPORTE| Agenda'!$B$5,AG_Sheyla_1[SEMESTRE],"2025-II") -> 0 | P8: =COUNTIFS(AG_Sheyla_1[MES],"Jul",AG_Sheyla_1[SEMANA],'REPORTE| Agenda'!$P$5,AG_Sheyla_1[ESCUELA],"TURISMO",AG_Sheyla_1[2 RINDIÓ EXAMEN],"SI",AG_Sheyla_1[ASESORA],'REPORTE| Agenda'!$B$5,AG_Sheyla_1[SEMESTRE],"2025-II") -> 0 | Q8: =COUNTIFS(AG_Sheyla_1[MES],"Jul",AG_Sheyla_1[SEMANA],'REPORTE| Agenda'!Q5,AG_Sheyla_1[ESCUELA],"TURISMO",AG_Sheyla_1[2 RINDIÓ EXAMEN],"SI",AG_Sheyla_1[ASESORA],'REPORTE| Agenda'!$B$5,AG_Sheyla_1[SEMESTRE],"2025-II") -> 1 | R8: =COUNTIFS(AG_Sheyla_1[MES],"Jul",AG_Sheyla_1[SEMANA],'REPORTE| Agenda'!R5,AG_Sheyla_1[ESCUELA],"TURISMO",AG_Sheyla_1[2 RINDIÓ EXAMEN],"SI",AG_Sheyla_1[ASESORA],'REPORTE| Agenda'!$B$5,AG_Sheyla_1[SEMESTRE],"2025-II") -> 0 | S8: =COUNTIFS(AG_Sheyla_1[MES],"Ago",AG_Sheyla_1[SEMANA],'REPORTE| Agenda'!K5,AG_Sheyla_1[ESCUELA],"TURISMO",AG_Sheyla_1[2 RINDIÓ EXAMEN],"SI",AG_Sheyla_1[ASESORA],'REPORTE| Agenda'!$B$5,AG_Sheyla_1[SEMESTRE],"2025-II") -> 0 | T8: =COUNTIFS(AG_Sheyla_1[MES],"Ago",AG_Sheyla_1[SEMANA],'REPORTE| Agenda'!T5,AG_Sheyla_1[ESCUELA],"TURISMO",AG_Sheyla_1[2 RINDIÓ EXAMEN],"SI",AG_Sheyla_1[ASESORA],'REPORTE| Agenda'!$B$5,AG_Sheyla_1[SEMESTRE],"2025-II") -> 0 | U8: =COUNTIFS(AG_Sheyla_1[MES],"Ago",AG_Sheyla_1[SEMANA],'REPORTE| Agenda'!U5,AG_Sheyla_1[ESCUELA],"TURISMO",AG_Sheyla_1[2 RINDIÓ EXAMEN],"SI",AG_Sheyla_1[ASESORA],'REPORTE| Agenda'!$B$5,AG_Sheyla_1[SEMESTRE],"2025-II") -> 0 | V8: =COUNTIFS(AG_Sheyla_1[MES],"Ago",AG_Sheyla_1[SEMANA],'REPORTE| Agenda'!V5,AG_Sheyla_1[ESCUELA],"TURISMO",AG_Sheyla_1[2 RINDIÓ EXAMEN],"SI",AG_Sheyla_1[ASESORA],'REPORTE| Agenda'!$B$5,AG_Sheyla_1[SEMESTRE],"2025-II") -> 0 | W8: =SUM(C8:V8) -> 6 | Y8: TURISMO | AD8: 1 | AG8: 1 | AH8: =COUNTIFS(AG_Sheyla_1[MES],"Jun",AG_Sheyla_1[SEMANA],'REPORTE| Agenda'!AH5,AG_Sheyla_1[ESCUELA],"TURISMO",AG_Sheyla_1[2 RINDIÓ EXAMEN],"SI",AG_Sheyla_1[ASESORA],'REPORTE| Agenda'!$B$5,AG_Sheyla_1[SEMESTRE],"2026-I") -> 0 | AI8: =COUNTIFS(AG_Sheyla_1[MES],"Jun",AG_Sheyla_1[SEMANA],'REPORTE| Agenda'!AI5,AG_Sheyla_1[ESCUELA],"TURISMO",AG_Sheyla_1[2 RINDIÓ EXAMEN],"SI",AG_Sheyla_1[ASESORA],'REPORTE| Agenda'!$B$5,AG_Sheyla_1[SEMESTRE],"2026-I") -> 0 | AJ8: =COUNTIFS(AG_Sheyla_1[MES],"Jun",AG_Sheyla_1[SEMANA],'REPORTE| Agenda'!AJ5,AG_Sheyla_1[ESCUELA],"TURISMO",AG_Sheyla_1[2 RINDIÓ EXAMEN],"SI",AG_Sheyla_1[ASESORA],'REPORTE| Agenda'!$B$5,AG_Sheyla_1[SEMESTRE],"2026-I") -> 0 | AK8: =COUNTIFS(AG_Sheyla_1[MES],"Jun",AG_Sheyla_1[SEMANA],'REPORTE| Agenda'!AK5,AG_Sheyla_1[ESCUELA],"TURISMO",AG_Sheyla_1[2 RINDIÓ EXAMEN],"SI",AG_Sheyla_1[ASESORA],'REPORTE| Agenda'!$B$5,AG_Sheyla_1[SEMESTRE],"2026-I") -> 0 | AL8: =COUNTIFS(AG_Sheyla_1[MES],"Jul",AG_Sheyla_1[SEMANA],'REPORTE| Agenda'!$O$5,AG_Sheyla_1[ESCUELA],"TURISMO",AG_Sheyla_1[2 RINDIÓ EXAMEN],"SI",AG_Sheyla_1[ASESORA],'REPORTE| Agenda'!$B$5,AG_Sheyla_1[SEMESTRE],"2026-I") -> 0 | AM8: =COUNTIFS(AG_Sheyla_1[MES],"Jul",AG_Sheyla_1[SEMANA],'REPORTE| Agenda'!$P$5,AG_Sheyla_1[ESCUELA],"TURISMO",AG_Sheyla_1[2 RINDIÓ EXAMEN],"SI",AG_Sheyla_1[ASESORA],'REPORTE| Agenda'!$B$5,AG_Sheyla_1[SEMESTRE],"2026-I") -> 0 | AN8: =COUNTIFS(AG_Sheyla_1[MES],"Jul",AG_Sheyla_1[SEMANA],'REPORTE| Agenda'!AN5,AG_Sheyla_1[ESCUELA],"TURISMO",AG_Sheyla_1[2 RINDIÓ EXAMEN],"SI",AG_Sheyla_1[ASESORA],'REPORTE| Agenda'!$B$5,AG_Sheyla_1[SEMESTRE],"2026-I") -> 0 | AO8: =COUNTIFS(AG_Sheyla_1[MES],"Jul",AG_Sheyla_1[SEMANA],'REPORTE| Agenda'!AO5,AG_Sheyla_1[ESCUELA],"TURISMO",AG_Sheyla_1[2 RINDIÓ EXAMEN],"SI",AG_Sheyla_1[ASESORA],'REPORTE| Agenda'!$B$5,AG_Sheyla_1[SEMESTRE],"2026-I") -> 0 | AP8: =COUNTIFS(AG_Sheyla_1[MES],"Ago",AG_Sheyla_1[SEMANA],'REPORTE| Agenda'!AH5,AG_Sheyla_1[ESCUELA],"TURISMO",AG_Sheyla_1[2 RINDIÓ EXAMEN],"SI",AG_Sheyla_1[ASESORA],'REPORTE| Agenda'!$B$5,AG_Sheyla_1[SEMESTRE],"2026-I") -> 1 | AQ8: =COUNTIFS(AG_Sheyla_1[MES],"Ago",AG_Sheyla_1[SEMANA],'REPORTE| Agenda'!AQ5,AG_Sheyla_1[ESCUELA],"TURISMO",AG_Sheyla_1[2 RINDIÓ EXAMEN],"SI",AG_Sheyla_1[ASESORA],'REPORTE| Agenda'!$B$5,AG_Sheyla_1[SEMESTRE],"2026-I") -> 0 | AR8: =COUNTIFS(AG_Sheyla_1[MES],"Ago",AG_Sheyla_1[SEMANA],'REPORTE| Agenda'!AR5,AG_Sheyla_1[ESCUELA],"TURISMO",AG_Sheyla_1[2 RINDIÓ EXAMEN],"SI",AG_Sheyla_1[ASESORA],'REPORTE| Agenda'!$B$5,AG_Sheyla_1[SEMESTRE],"2026-I") -> 0 | AS8: =COUNTIFS(AG_Sheyla_1[MES],"Ago",AG_Sheyla_1[SEMANA],'REPORTE| Agenda'!AS5,AG_Sheyla_1[ESCUELA],"TURISMO",AG_Sheyla_1[2 RINDIÓ EXAMEN],"SI",AG_Sheyla_1[ASESORA],'REPORTE| Agenda'!$B$5,AG_Sheyla_1[SEMESTRE],"2026-I") -> 0 | AT8: =SUM(Z8:AO8) -> 2
B9: COMUNICACIONES | I9: 1 | J9: 1 | K9: =COUNTIFS(AG_Sheyla_1[MES],"Jun",AG_Sheyla_1[SEMANA],'REPORTE| Agenda'!K5,AG_Sheyla_1[ESCUELA],"COMUNICACIONES",AG_Sheyla_1[2 RINDIÓ EXAMEN],"SI",AG_Sheyla_1[ASESORA],'REPORTE| Agenda'!$B$5,AG_Sheyla_1[SEMESTRE],"2025-II") -> 1 | L9: =COUNTIFS(AG_Sheyla_1[MES],"Jun",AG_Sheyla_1[SEMANA],'REPORTE| Agenda'!L5,AG_Sheyla_1[ESCUELA],"COMUNICACIONES",AG_Sheyla_1[2 RINDIÓ EXAMEN],"SI",AG_Sheyla_1[ASESORA],'REPORTE| Agenda'!$B$5,AG_Sheyla_1[SEMESTRE],"2025-II") -> 1 | M9: =COUNTIFS(AG_Sheyla_1[MES],"Jun",AG_Sheyla_1[SEMANA],'REPORTE| Agenda'!M5,AG_Sheyla_1[ESCUELA],"COMUNICACIONES",AG_Sheyla_1[2 RINDIÓ EXAMEN],"SI",AG_Sheyla_1[ASESORA],'REPORTE| Agenda'!$B$5,AG_Sheyla_1[SEMESTRE],"2025-II") -> 1 | N9: =COUNTIFS(AG_Sheyla_1[MES],"Jun",AG_Sheyla_1[SEMANA],'REPORTE| Agenda'!N5,AG_Sheyla_1[ESCUELA],"COMUNICACIONES",AG_Sheyla_1[2 RINDIÓ EXAMEN],"SI",AG_Sheyla_1[ASESORA],'REPORTE| Agenda'!$B$5,AG_Sheyla_1[SEMESTRE],"2025-II") -> 1 | O9: =COUNTIFS(AG_Sheyla_1[MES],"Jul",AG_Sheyla_1[SEMANA],'REPORTE| Agenda'!O5,AG_Sheyla_1[ESCUELA],"COMUNICACIONES",AG_Sheyla_1[2 RINDIÓ EXAMEN],"SI",AG_Sheyla_1[ASESORA],'REPORTE| Agenda'!$B$5,AG_Sheyla_1[SEMESTRE],"2025-II") -> 0 | P9: =COUNTIFS(AG_Sheyla_1[MES],"Jul",AG_Sheyla_1[SEMANA],'REPORTE| Agenda'!P5,AG_Sheyla_1[ESCUELA],"COMUNICACIONES",AG_Sheyla_1[2 RINDIÓ EXAMEN],"SI",AG_Sheyla_1[ASESORA],'REPORTE| Agenda'!$B$5,AG_Sheyla_1[SEMESTRE],"2025-II") -> 3 | Q9: =COUNTIFS(AG_Sheyla_1[MES],"Jul",AG_Sheyla_1[SEMANA],'REPORTE| Agenda'!Q5,AG_Sheyla_1[ESCUELA],"COMUNICACIONES",AG_Sheyla_1[2 RINDIÓ EXAMEN],"SI",AG_Sheyla_1[ASESORA],'REPORTE| Agenda'!$B$5,AG_Sheyla_1[SEMESTRE],"2025-II") -> 1 | R9: =COUNTIFS(AG_Sheyla_1[MES],"Jul",AG_Sheyla_1[SEMANA],'REPORTE| Agenda'!R5,AG_Sheyla_1[ESCUELA],"COMUNICACIONES",AG_Sheyla_1[2 RINDIÓ EXAMEN],"SI",AG_Sheyla_1[ASESORA],'REPORTE| Agenda'!$B$5,AG_Sheyla_1[SEMESTRE],"2025-II") -> 1 | S9: =COUNTIFS(AG_Sheyla_1[MES],"Ago",AG_Sheyla_1[SEMANA],'REPORTE| Agenda'!S5,AG_Sheyla_1[ESCUELA],"COMUNICACIONES",AG_Sheyla_1[2 RINDIÓ EXAMEN],"SI",AG_Sheyla_1[ASESORA],'REPORTE| Agenda'!$B$5,AG_Sheyla_1[SEMESTRE],"2025-II") -> 0 | T9: =COUNTIFS(AG_Sheyla_1[MES],"Ago",AG_Sheyla_1[SEMANA],'REPORTE| Agenda'!T5,AG_Sheyla_1[ESCUELA],"COMUNICACIONES",AG_Sheyla_1[2 RINDIÓ EXAMEN],"SI",AG_Sheyla_1[ASESORA],'REPORTE| Agenda'!$B$5,AG_Sheyla_1[SEMESTRE],"2025-II") -> 0 | U9: =COUNTIFS(AG_Sheyla_1[MES],"Ago",AG_Sheyla_1[SEMANA],'REPORTE| Agenda'!U5,AG_Sheyla_1[ESCUELA],"COMUNICACIONES",AG_Sheyla_1[2 RINDIÓ EXAMEN],"SI",AG_Sheyla_1[ASESORA],'REPORTE| Agenda'!$B$5,AG_Sheyla_1[SEMESTRE],"2025-II") -> 0 | V9: =COUNTIFS(AG_Sheyla_1[MES],"Ago",AG_Sheyla_1[SEMANA],'REPORTE| Agenda'!V5,AG_Sheyla_1[ESCUELA],"COMUNICACIONES",AG_Sheyla_1[2 RINDIÓ EXAMEN],"SI",AG_Sheyla_1[ASESORA],'REPORTE| Agenda'!$B$5,AG_Sheyla_1[SEMESTRE],"2025-II") -> 0 | W9: =SUM(C9:V9) -> 11 | Y9: COMUNICACIONES | AE9: 1 | AH9: =COUNTIFS(AG_Sheyla_1[MES],"Jun",AG_Sheyla_1[SEMANA],'REPORTE| Agenda'!AH5,AG_Sheyla_1[ESCUELA],"COMUNICACIONES",AG_Sheyla_1[2 RINDIÓ EXAMEN],"SI",AG_Sheyla_1[ASESORA],'REPORTE| Agenda'!$B$5,AG_Sheyla_1[SEMESTRE],"2026-I") -> 0 | AI9: =COUNTIFS(AG_Sheyla_1[MES],"Jun",AG_Sheyla_1[SEMANA],'REPORTE| Agenda'!AI5,AG_Sheyla_1[ESCUELA],"COMUNICACIONES",AG_Sheyla_1[2 RINDIÓ EXAMEN],"SI",AG_Sheyla_1[ASESORA],'REPORTE| Agenda'!$B$5,AG_Sheyla_1[SEMESTRE],"2026-I") -> 1 | AJ9: =COUNTIFS(AG_Sheyla_1[MES],"Jun",AG_Sheyla_1[SEMANA],'REPORTE| Agenda'!AJ5,AG_Sheyla_1[ESCUELA],"COMUNICACIONES",AG_Sheyla_1[2 RINDIÓ EXAMEN],"SI",AG_Sheyla_1[ASESORA],'REPORTE| Agenda'!$B$5,AG_Sheyla_1[SEMESTRE],"2026-I") -> 0 | AK9: =COUNTIFS(AG_Sheyla_1[MES],"Jun",AG_Sheyla_1[SEMANA],'REPORTE| Agenda'!AK5,AG_Sheyla_1[ESCUELA],"COMUNICACIONES",AG_Sheyla_1[2 RINDIÓ EXAMEN],"SI",AG_Sheyla_1[ASESORA],'REPORTE| Agenda'!$B$5,AG_Sheyla_1[SEMESTRE],"2026-I") -> 1 | AL9: =COUNTIFS(AG_Sheyla_1[MES],"Jul",AG_Sheyla_1[SEMANA],'REPORTE| Agenda'!AL5,AG_Sheyla_1[ESCUELA],"COMUNICACIONES",AG_Sheyla_1[2 RINDIÓ EXAMEN],"SI",AG_Sheyla_1[ASESORA],'REPORTE| Agenda'!$B$5,AG_Sheyla_1[SEMESTRE],"2026-I") -> 0 | AM9: =COUNTIFS(AG_Sheyla_1[MES],"Jul",AG_Sheyla_1[SEMANA],'REPORTE| Agenda'!AM5,AG_Sheyla_1[ESCUELA],"COMUNICACIONES",AG_Sheyla_1[2 RINDIÓ EXAMEN],"SI",AG_Sheyla_1[ASESORA],'REPORTE| Agenda'!$B$5,AG_Sheyla_1[SEMESTRE],"2026-I") -> 0 | AN9: =COUNTIFS(AG_Sheyla_1[MES],"Jul",AG_Sheyla_1[SEMANA],'REPORTE| Agenda'!AN5,AG_Sheyla_1[ESCUELA],"COMUNICACIONES",AG_Sheyla_1[2 RINDIÓ EXAMEN],"SI",AG_Sheyla_1[ASESORA],'REPORTE| Agenda'!$B$5,AG_Sheyla_1[SEMESTRE],"2026-I") -> 4 | AO9: =COUNTIFS(AG_Sheyla_1[MES],"Jul",AG_Sheyla_1[SEMANA],'REPORTE| Agenda'!AO5,AG_Sheyla_1[ESCUELA],"COMUNICACIONES",AG_Sheyla_1[2 RINDIÓ EXAMEN],"SI",AG_Sheyla_1[ASESORA],'REPORTE| Agenda'!$B$5,AG_Sheyla_1[SEMESTRE],"2026-I") -> 2 | AP9: =COUNTIFS(AG_Sheyla_1[MES],"Ago",AG_Sheyla_1[SEMANA],'REPORTE| Agenda'!AP5,AG_Sheyla_1[ESCUELA],"COMUNICACIONES",AG_Sheyla_1[2 RINDIÓ EXAMEN],"SI",AG_Sheyla_1[ASESORA],'REPORTE| Agenda'!$B$5,AG_Sheyla_1[SEMESTRE],"2026-I") -> 0 | AQ9: =COUNTIFS(AG_Sheyla_1[MES],"Ago",AG_Sheyla_1[SEMANA],'REPORTE| Agenda'!AQ5,AG_Sheyla_1[ESCUELA],"COMUNICACIONES",AG_Sheyla_1[2 RINDIÓ EXAMEN],"SI",AG_Sheyla_1[ASESORA],'REPORTE| Agenda'!$B$5,AG_Sheyla_1[SEMESTRE],"2026-I") -> 0 | AR9: =COUNTIFS(AG_Sheyla_1[MES],"Ago",AG_Sheyla_1[SEMANA],'REPORTE| Agenda'!AR5,AG_Sheyla_1[ESCUELA],"COMUNICACIONES",AG_Sheyla_1[2 RINDIÓ EXAMEN],"SI",AG_Sheyla_1[ASESORA],'REPORTE| Agenda'!$B$5,AG_Sheyla_1[SEMESTRE],"2026-I") -> 0 | AS9: =COUNTIFS(AG_Sheyla_1[MES],"Ago",AG_Sheyla_1[SEMANA],'REPORTE| Agenda'!AS5,AG_Sheyla_1[ESCUELA],"COMUNICACIONES",AG_Sheyla_1[2 RINDIÓ EXAMEN],"SI",AG_Sheyla_1[ASESORA],'REPORTE| Agenda'!$B$5,AG_Sheyla_1[SEMESTRE],"2026-I") -> 0 | AT9: =SUM(Z9:AO9) -> 9
B10: Sub Total por Semana | C10: =SUM(C7:C9) -> 0 | D10: =SUM(D7:D9) -> 0 | E10: =SUM(E7:E9) -> 0 | F10: =SUM(F7:F9) -> 2 | G10: =SUM(G7:G9) -> 2 | H10: =SUM(H7:H9) -> 3 | I10: =SUM(I7:I9) -> 3 | J10: =SUM(J7:J9) -> 6 | ... V10: =SUM(V7:V9) -> 0 | W10: =SUM(C10:V10) -> 47 | Y10: Sub Total por Semana | Z10: =SUM(Z7:Z9) -> 0 | AA10: =SUM(AA7:AA9) -> 0 | AB10: =SUM(AB7:AB9) -> 0 | AC10: =SUM(AC7:AC9) -> 1 | AD10: =SUM(AD7:AD9) -> 1 | AE10: =SUM(AE7:AE9) -> 2 | AF10: =SUM(AF7:AF9) -> 1 | AG10: =SUM(AG7:AG9) -> 2 | ... AS10: =SUM(AS7:AS9) -> 0 | AT10: =SUM(Z10:AO10) -> 21
B11: Total por Mes | C11: =SUM(C10:F10) -> 2 | G11: =SUM(G10:J10) -> 14 | K11: =SUM(K10:N10) -> 14 | O11: =SUM(O10:R10) -> 17 | S11: =SUM(S10:V10) -> 0 | W11: =SUM(C11:V11) -> 47 | Y11: Total por Mes | Z11: =SUM(Z10:AC10) -> 1 | AD11: =SUM(AD10:AG10) -> 6 | AH11: =SUM(AH10:AK10) -> 5 | AL11: =SUM(AL10:AO10) -> 9 | AP11: =SUM(AP10:AS10) -> 2 | AT11: =SUM(Z11:AS11) -> 23
B13: Estrella Vergara | C13: S1 | D13: S2 | E13: S3 | F13: S4 | G13: S1 | H13: S2 | I13: S3 | J13: S4 | K13: S1 | L13: S2 | M13: S3 | N13: S4 | O13: S1 | P13: S2 | Q13: S3 | R13: S4 | S13: S1 | T13: S2 | U13: S3 | V13: S4 | W13: Total | Y13: Estrella Vergara | Z13: S1 | AA13: S2 | AB13: S3 | AC13: S4 | AD13: S1 | AE13: S2 | AF13: S3 | AG13: S4 | AH13: S1 | AI13: S2 | AJ13: S3 | AK13: S4 | AL13: S1 | AM13: S2 | AN13: S3 | AO13: S4 | AP13: S1 | AQ13: S2 | AR13: S3 | AS13: S4 | AT13: Total
B15: PSICOLOGIA | J15: =COUNTIFS(AG_Sheyla_1[MES],"May",AG_Sheyla_1[SEMANA],'REPORTE| Agenda'!$J$13,AG_Sheyla_1[ESCUELA],"PSICOLOGIA",AG_Sheyla_1[2 RINDIÓ EXAMEN],"SI",AG_Sheyla_1[ASESORA],'REPORTE| Agenda'!$B$13,AG_Sheyla_1[SEMESTRE],"2025-II") -> 0 | K15: =COUNTIFS(AG_Sheyla_1[MES],"Jun",AG_Sheyla_1[SEMANA],'REPORTE| Agenda'!$K$13,AG_Sheyla_1[ESCUELA],"PSICOLOGIA",AG_Sheyla_1[2 RINDIÓ EXAMEN],"SI",AG_Sheyla_1[ASESORA],'REPORTE| Agenda'!$B$13,AG_Sheyla_1[SEMESTRE],"2025-II") -> 1 | L15: =COUNTIFS(AG_Sheyla_1[MES],"Jun",AG_Sheyla_1[SEMANA],'REPORTE| Agenda'!$L$13,AG_Sheyla_1[ESCUELA],"PSICOLOGIA",AG_Sheyla_1[2 RINDIÓ EXAMEN],"SI",AG_Sheyla_1[ASESORA],'REPORTE| Agenda'!$B$13,AG_Sheyla_1[SEMESTRE],"2025-II") -> 0 | M15: =COUNTIFS(AG_Sheyla_1[MES],"Jun",AG_Sheyla_1[SEMANA],'REPORTE| Agenda'!$M$5,AG_Sheyla_1[ESCUELA],"PSICOLOGIA",AG_Sheyla_1[2 RINDIÓ EXAMEN],"SI",AG_Sheyla_1[ASESORA],'REPORTE| Agenda'!$B$5,AG_Sheyla_1[SEMESTRE],"2025-II") -> 1 | N15: =COUNTIFS(AG_Sheyla_1[MES],"Jun",AG_Sheyla_1[SEMANA],'REPORTE| Agenda'!$N$13,AG_Sheyla_1[ESCUELA],"PSICOLOGIA",AG_Sheyla_1[2 RINDIÓ EXAMEN],"SI",AG_Sheyla_1[ASESORA],'REPORTE| Agenda'!$B$13,AG_Sheyla_1[SEMESTRE],"2025-II") -> 3 | O15: =COUNTIFS(AG_Sheyla_1[MES],"Jul",AG_Sheyla_1[SEMANA],'REPORTE| Agenda'!$O$5,AG_Sheyla_1[ESCUELA],"PSICOLOGIA",AG_Sheyla_1[2 RINDIÓ EXAMEN],"SI",AG_Sheyla_1[ASESORA],'REPORTE| Agenda'!$B$13,AG_Sheyla_1[SEMESTRE],"2025-II") -> 1 | P15: =COUNTIFS(AG_Sheyla_1[MES],"Jul",AG_Sheyla_1[SEMANA],'REPORTE| Agenda'!$P$5,AG_Sheyla_1[ESCUELA],"PSICOLOGIA",AG_Sheyla_1[2 RINDIÓ EXAMEN],"SI",AG_Sheyla_1[ASESORA],'REPORTE| Agenda'!$B$13,AG_Sheyla_1[SEMESTRE],"2025-II") -> 1 | Q15: =COUNTIFS(AG_Sheyla_1[MES],"Jul",AG_Sheyla_1[SEMANA],'REPORTE| Agenda'!$Q$5,AG_Sheyla_1[ESCUELA],"PSICOLOGIA",AG_Sheyla_1[2 RINDIÓ EXAMEN],"SI",AG_Sheyla_1[ASESORA],'REPORTE| Agenda'!$B$13,AG_Sheyla_1[SEMESTRE],"2025-II") -> 2 | R15: =COUNTIFS(AG_Sheyla_1[MES],"Jul",AG_Sheyla_1[SEMANA],'REPORTE| Agenda'!$R$5,AG_Sheyla_1[ESCUELA],"PSICOLOGIA",AG_Sheyla_1[2 RINDIÓ EXAMEN],"SI",AG_Sheyla_1[ASESORA],'REPORTE| Agenda'!$B$13,AG_Sheyla_1[SEMESTRE],"2025-II") -> 1 | S15: =COUNTIFS(AG_Sheyla_1[MES],"Ago",AG_Sheyla_1[SEMANA],'REPORTE| Agenda'!S13,AG_Sheyla_1[ESCUELA],"PSICOLOGIA",AG_Sheyla_1[2 RINDIÓ EXAMEN],"SI",AG_Sheyla_1[ASESORA],'REPORTE| Agenda'!$B$13,AG_Sheyla_1[SEMESTRE],"2025-II") -> 0 | T15: =COUNTIFS(AG_Sheyla_1[MES],"Ago",AG_Sheyla_1[SEMANA],'REPORTE| Agenda'!$T$13,AG_Sheyla_1[ESCUELA],"PSICOLOGIA",AG_Sheyla_1[2 RINDIÓ EXAMEN],"SI",AG_Sheyla_1[ASESORA],'REPORTE| Agenda'!$B$13,AG_Sheyla_1[SEMESTRE],"2025-II") -> 0 | U15: =COUNTIFS(AG_Sheyla_1[MES],"Ago",AG_Sheyla_1[SEMANA],'REPORTE| Agenda'!$U$13,AG_Sheyla_1[ESCUELA],"PSICOLOGIA",AG_Sheyla_1[2 RINDIÓ EXAMEN],"SI",AG_Sheyla_1[ASESORA],'REPORTE| Agenda'!$B$13,AG_Sheyla_1[SEMESTRE],"2025-II") -> 0 | V15: =COUNTIFS(AG_Sheyla_1[MES],"Ago",AG_Sheyla_1[SEMANA],'REPORTE| Agenda'!$V$13,AG_Sheyla_1[ESCUELA],"PSICOLOGIA",AG_Sheyla_1[2 RINDIÓ EXAMEN],"SI",AG_Sheyla_1[ASESORA],'REPORTE| Agenda'!$B$13,AG_Sheyla_1[SEMESTRE],"2025-II") -> 0 | W15: =SUM(C15:V15) -> 10 | Y15: PSICOLOGIA | AF15: =COUNTIFS(AG_Sheyla_1[MES],"May",AG_Sheyla_1[SEMANA],'REPORTE| Agenda'!AF13,AG_Sheyla_1[ESCUELA],"PSICOLOGIA",AG_Sheyla_1[2 RINDIÓ EXAMEN],"SI",AG_Sheyla_1[ASESORA],'REPORTE| Agenda'!$Y$13,AG_Sheyla_1[SEMESTRE],"2026-I") -> 0 | AG15: =COUNTIFS(AG_Sheyla_1[MES],"May",AG_Sheyla_1[SEMANA],'REPORTE| Agenda'!AG13,AG_Sheyla_1[ESCUELA],"PSICOLOGIA",AG_Sheyla_1[2 RINDIÓ EXAMEN],"SI",AG_Sheyla_1[ASESORA],'REPORTE| Agenda'!$Y$13,AG_Sheyla_1[SEMESTRE],"2026-I") -> 2 | AH15: =COUNTIFS(AG_Sheyla_1[MES],"Jun",AG_Sheyla_1[SEMANA],'REPORTE| Agenda'!AH13,AG_Sheyla_1[ESCUELA],"PSICOLOGIA",AG_Sheyla_1[2 RINDIÓ EXAMEN],"SI",AG_Sheyla_1[ASESORA],'REPORTE| Agenda'!$Y$13,AG_Sheyla_1[SEMESTRE],"2026-I") -> 0 | AI15: =COUNTIFS(AG_Sheyla_1[MES],"Jun",AG_Sheyla_1[SEMANA],'REPORTE| Agenda'!AI13,AG_Sheyla_1[ESCUELA],"PSICOLOGIA",AG_Sheyla_1[2 RINDIÓ EXAMEN],"SI",AG_Sheyla_1[ASESORA],'REPORTE| Agenda'!$Y$13,AG_Sheyla_1[SEMESTRE],"2026-I") -> 2 | AJ15: =COUNTIFS(AG_Sheyla_1[MES],"Jun",AG_Sheyla_1[SEMANA],'REPORTE| Agenda'!AJ13,AG_Sheyla_1[ESCUELA],"PSICOLOGIA",AG_Sheyla_1[2 RINDIÓ EXAMEN],"SI",AG_Sheyla_1[ASESORA],'REPORTE| Agenda'!$Y$13,AG_Sheyla_1[SEMESTRE],"2026-I") -> 3 | AK15: =COUNTIFS(AG_Sheyla_1[MES],"Jun",AG_Sheyla_1[SEMANA],'REPORTE| Agenda'!AK13,AG_Sheyla_1[ESCUELA],"PSICOLOGIA",AG_Sheyla_1[2 RINDIÓ EXAMEN],"SI",AG_Sheyla_1[ASESORA],'REPORTE| Agenda'!$Y$13,AG_Sheyla_1[SEMESTRE],"2026-I") -> 2 | AL15: =COUNTIFS(AG_Sheyla_1[MES],"Jul",AG_Sheyla_1[SEMANA],'REPORTE| Agenda'!AL13,AG_Sheyla_1[ESCUELA],"PSICOLOGIA",AG_Sheyla_1[2 RINDIÓ EXAMEN],"SI",AG_Sheyla_1[ASESORA],'REPORTE| Agenda'!$Y$13,AG_Sheyla_1[SEMESTRE],"2026-I") -> 0 | AM15: =COUNTIFS(AG_Sheyla_1[MES],"Jul",AG_Sheyla_1[SEMANA],'REPORTE| Agenda'!AM13,AG_Sheyla_1[ESCUELA],"PSICOLOGIA",AG_Sheyla_1[2 RINDIÓ EXAMEN],"SI",AG_Sheyla_1[ASESORA],'REPORTE| Agenda'!$Y$13,AG_Sheyla_1[SEMESTRE],"2026-I") -> 3 | AN15: =COUNTIFS(AG_Sheyla_1[MES],"Jul",AG_Sheyla_1[SEMANA],'REPORTE| Agenda'!$Q$5,AG_Sheyla_1[ESCUELA],"PSICOLOGIA",AG_Sheyla_1[2 RINDIÓ EXAMEN],"SI",AG_Sheyla_1[ASESORA],'REPORTE| Agenda'!$Y$13,AG_Sheyla_1[SEMESTRE],"2026-I") -> 2 | AO15: =COUNTIFS(AG_Sheyla_1[MES],"Jul",AG_Sheyla_1[SEMANA],'REPORTE| Agenda'!$R$5,AG_Sheyla_1[ESCUELA],"PSICOLOGIA",AG_Sheyla_1[2 RINDIÓ EXAMEN],"SI",AG_Sheyla_1[ASESORA],'REPORTE| Agenda'!$Y$13,AG_Sheyla_1[SEMESTRE],"2026-I") -> 0 | AP15: =COUNTIFS(AG_Sheyla_1[MES],"Ago",AG_Sheyla_1[SEMANA],'REPORTE| Agenda'!AP13,AG_Sheyla_1[ESCUELA],"PSICOLOGIA",AG_Sheyla_1[2 RINDIÓ EXAMEN],"SI",AG_Sheyla_1[ASESORA],'REPORTE| Agenda'!$Y$13,AG_Sheyla_1[SEMESTRE],"2026-I") -> 1 | AQ15: =COUNTIFS(AG_Sheyla_1[MES],"Ago",AG_Sheyla_1[SEMANA],'REPORTE| Agenda'!AQ13,AG_Sheyla_1[ESCUELA],"PSICOLOGIA",AG_Sheyla_1[2 RINDIÓ EXAMEN],"SI",AG_Sheyla_1[ASESORA],'REPORTE| Agenda'!$Y$13,AG_Sheyla_1[SEMESTRE],"2026-I") -> 0 | AR15: =COUNTIFS(AG_Sheyla_1[MES],"Ago",AG_Sheyla_1[SEMANA],'REPORTE| Agenda'!AR13,AG_Sheyla_1[ESCUELA],"PSICOLOGIA",AG_Sheyla_1[2 RINDIÓ EXAMEN],"SI",AG_Sheyla_1[ASESORA],'REPORTE| Agenda'!$Y$13,AG_Sheyla_1[SEMESTRE],"2026-I") -> 0 | AS15: =COUNTIFS(AG_Sheyla_1[MES],"Ago",AG_Sheyla_1[SEMANA],'REPORTE| Agenda'!AS13,AG_Sheyla_1[ESCUELA],"PSICOLOGIA",AG_Sheyla_1[2 RINDIÓ EXAMEN],"SI",AG_Sheyla_1[ASESORA],'REPORTE| Agenda'!$Y$13,AG_Sheyla_1[SEMESTRE],"2026-I") -> 0 | AT15: =SUM(Z15:AS15) -> 15
